Workbook

Sheet Working
A2: Category | B2: Venue | C2: No of courts | D2: Teams | E2: Est Time (in mins) | F2: Total matches | G2: Total Time (in hrs) | H2: 05th | I2: 11th | J2: 12th | K2: Court charges | M2: Teams
A3: Open Women's Doubles | B3: GB | C3: 3 | D3: 12 | E3: 13 | F3: 24 | G3: =(F3*E3)/60/C3 -> 1.7333333 | H3: ☑ | K3: 400 | M3: No of matches calculation | N3: 32 | O3: 28 | P3: 24 | Q3: 16 | R3: 12
A4: 45+ Split Doubles | B4: GB | C4: 3 | D4: 24 | E4: =E3 -> 13 | F4: 48 | G4: =(F4*E4)/60/C4 -> 3.4666667 | H4: ☑ | K4: =K3 -> 400 | N4: =N3/4 -> 8 | O4: =O3/4 -> 7 | P4: =P3/4 -> 6 | Q4: =Q3/4 -> 4 | R4: =R3/4 -> 3
A5: Beginner Men's Doubles | B5: GB | C5: 3 | D5: 32 | E5: =E4 -> 13 | F5: 63 | G5: =(F5*E5)/60/C5 -> 4.55 | H5: ☑ | K5: =K4 -> 400 | N5: =N4*6 -> 48 | O5: =O4*6 -> 42 | P5: =P4*6 -> 36 | Q5: =Q4*6 -> 24 | R5: =R4*6 -> 18
A6: Beginner Mixed Doubles | B6: GB | C6: 3 | D6: 24 | E6: =E5 -> 13 | F6: 48 | G6: =(F6*E6)/60/C6 -> 3.4666667 | H6: ☑ | K6: =K5 -> 400 | N6: 8 | O6: 7 | P6: 6 | Q6: 4 | R6: 3
A7: Intermediate Men's Doubles | B7: Adda | C7: 2 | D7: 32 | E7: =E6 -> 13 | F7: 63 | G7: =(F7*E7)/60/C7 -> 6.825 | I7: ☑ | K7: 600 | N7: 4 | O7: 4 | P7: 3 | Q7: 2 | R7: 2
A8: Intermediate 35+ Split Doubles | B8: Adda | C8: 2 | D8: 12 | E8: =E7 -> 13 | F8: 24 | G8: =(F8*E8)/60/C8 -> 2.6 | I8: ☑ | K8: 600 | N8: 2 | O8: 2 | P8: 2 | Q8: 1 | R8: 1
A9: Open Men's Singles | B9: Adda | C9: 2 | D9: 24 | E9: 10 | F9: 48 | G9: =(F9*E9)/60/C9 -> 4 | I9: ☑ | K9: =K7 -> 600 | N9: 1 | O9: 1 | P9: 1
A10: Open Mixed Doubles | B10: Adda | C10: 2 | D10: 24 | E10: =E7 -> 13 | F10: =D10*2 -> 48 | G10: =(F10*E10)/60/C10 -> 5.2 | J10: ☑ | K10: =K9 -> 600
A11: Advanced Men's Doubles | B11: Adda | C11: 2 | D11: 24 | E11: 16 | F11: 48 | G11: =(F11*E11)/60/C11 -> 6.4 | J11: ☑ | K11: =K10 -> 600
A14: GB PnL
A16: Income: | C16: 1600
A17: Open Women's Doubles | B17: =D3 -> 12 | C17: =$B17*C$16 -> 19200
A18: 45+ Split Doubles | B18: =D4 -> 24 | C18: =$B18*C$16 -> 38400
A19: Beginner Men's Doubles | B19: =D5 -> 32 | C19: =$B19*C$16 -> 51200
A20: Beginner Mixed Doubles | B20: =D6 -> 24 | C20: =$B20*C$16 -> 38400
A21: Fee income | C21: =SUM(C17:C20) -> 147200
A23: Expense:
A24: Court charges | C24: =SUM(G3:G6)*C3*K3 -> 15860
A25: Ref fees | C25: =1500*3 -> 4500
A26: Ball cost (Ash100) | C26: =100*10 -> 1000
A27: Prize Pool | C27: =SUM(B71:E71) -> 12000
A28: F&B (tea & snacks) | C28: =50*100 -> 5000
A29: Live stream (3 courts) | C29: 18000
A30: Misc | C30: 15000
A31: Total expense | C31: =SUM(C24:C30) -> 71360
A33: Total Profit | C33: =C21-C31 -> 75840
A35: Adda PnL
A36: Income: | C36: Case 1
A37: Adv Doubles | C37: 2200
A38: Doubles | C38: 2000
A39: Singles | C39: 1000
A40: Intermediate Men's Doubles | B40: =D7 -> 32 | C40: =C$38*$B40 -> 64000
A41: Intermediate 35+ Split Doubles | B41: 12 | C41: =C$38*$B41 -> 24000
A42: Open Men's Singles | B42: =D9 -> 24 | C42: =C$39*$B42 -> 24000
A43: Open Mixed Doubles | B43: =D10 -> 24 | C43: =C$38*$B43 -> 48000
A44: Advanced Men's Doubles | B44: =D11 -> 24 | C44: =C$38*$B44 -> 48000
A45: Other income | C45: 30000
A46: Total income | C46: =SUM(C40:C45) -> 238000
A48: Expense:
A49: Court charges | C49: =SUM(G7:G11)*C7*K7 -> 30030
A50: Ref fees | C50: =1500*2*2 -> 6000
A51: Ball cost (Franklin) | C51: =155*15 -> 2325
A52: Prize Pool | C52: =SUM(F71:I71) -> 85000
A53: F&B (tea & snacks) | C53: =C28 -> 5000
A54: Live stream (2 courts) | C54: 15000
A55: Décor (Stands) | C55: 40000
A56: Misc | C56: 15000
A57: Total expense | C57: =SUM(C49:C56) -> 198355
A59: Total Profit | C59: =C46-C57 -> 39645
A61: Grand total:
A62: Income | C62: =C46+C21 -> 385200
A63: Expense | C63: =C57+C31 -> 269715
A64: Net profit | C64: =C62-C63 -> 115485
A67: Prize money breakup
B68: Open Women's Doubles | C68: 45+ Split Doubles | D68: Beginner Men's Doubles | E68: Beginner Mixed Doubles | F68: Intermediate Men's Doubles | G68: Open Men's Singles | H68: Open Mixed Doubles | I68: Advanced Men's Doubles | J68: Intermediate 35+ Split Doubles
A69: 1st prize | B69: =C69 -> 2000 | C69: =D69 -> 2000 | D69: =E69 -> 2000 | E69: 2000 | F69: 15000 | G69: =G71*0.7 -> 7000 | H69: 15000 | I69: 22000
A70: 2nd prize | B70: =C70 -> 1000 | C70: =D70 -> 1000 | D70: =E70 -> 1000 | E70: =E69/2 -> 1000 | F70: =F71-F69 -> 6000 | G70: =G71-G69 -> 3000 | H70: =H71-H69 -> 6000 | I70: 11000
A71: Total | B71: =C71 -> 3000 | C71: =D71 -> 3000 | D71: =E71 -> 3000 | E71: 3000 | F71: 21000 | G71: 10000 | H71: 21000 | I71: =SUM(I69:I70) -> 33000
A73: Entry fee | B73: =C16 -> 1600 | C73: =B73 -> 1600 | D73: =C73 -> 1600 | E73: =D73 -> 1600 | F73: =C38 -> 2000 | G73: =C39 -> 1000 | H73: =C38 -> 2000 | I73: =C37 -> 2200
A75: % increase
A76: 1st prize | B76: =B69/B$73 -> 1.25 | C76: =C69/C$73 -> 1.25 | D76: =D69/D$73 -> 1.25 | E76: =E69/E$73 -> 1.25 | F76: =F69/F$73 -> 7.5 | G76: =G69/G$73 -> 7 | H76: =H69/H$73 -> 7.5 | I76: =I69/I$73 -> 10
A77: 2nd prize | B77: =B70/B$73 -> 0.625 | C77: =C70/C$73 -> 0.625 | D77: =D70/D$73 -> 0.625 | E77: =E70/E$73 -> 0.625 | F77: =F70/F$73 -> 3 | G77: =G70/G$73 -> 3 | H77: =H70/H$73 -> 3 | I77: =I70/I$73 -> 5
A80: Gross Margin
B81: Open Women's Doubles | C81: 45+ Split Doubles | D81: Beginner Men's Doubles | E81: Beginner Mixed Doubles | F81: Intermediate Men's Doubles | G81: Open Men's Singles | H81: Open Mixed Doubles | I81: Advanced Men's Doubles
A82: Income | B82: =C17 -> 19200 | C82: =C18 -> 38400 | D82: =C19 -> 51200 | E82: =C20 -> 38400 | F82: =C40 -> 64000 | G82: =C42 -> 24000 | H82: =C43 -> 48000 | I82: =C44 -> 48000
A83: Court fees | B83: =G3*3*K3 -> 2080 | C83: =G4*3*K3 -> 4160 | D83: =G5*3*K3 -> 5460 | E83: =G6*3*K3 -> 4160 | F83: =G7*2*K7 -> 8190 | G83: =G9*2*K7 -> 4800 | H83: =G10*2*K7 -> 6240 | I83: =G11*2*K7 -> 7680
A84: Gross Profit | B84: =B82-B83 -> 17120 | C84: =C82-C83 -> 34240 | D84: =D82-D83 -> 45740 | E84: =E82-E83 -> 34240 | F84: =F82-F83 -> 55810 | G84: =G82-G83 -> 19200 | H84: =H82-H83 -> 41760 | I84: =I82-I83 -> 40320
A85: Gross Margin | B85: =B84/B82 -> 0.89166667 | C85: =C84/C82 -> 0.89166667 | D85: =D84/D82 -> 0.89335937 | E85: =E84/E82 -> 0.89166667 | F85: =F84/F82 -> 0.87203125 | G85: =G84/G82 -> 0.8 | H85: =H84/H82 -> 0.87 | I85: =I84/I82 -> 0.84

Sheet Registrations
A1: Registrations Input (Enter names here; Schedule auto-updates)
A3: Category | B3: Code | C3: Player 1 | D3: Player 2 | E3: Team ID | F3: UPI ID | G3: Player 1 DUPR | H3: Player 2 DUPR
A4: Open Men Singles | B4: MS01 | C4: Sanjay Gatti | E4: =IF(Registrations[[#This Row],[Player 2]]="",Registrations[[#This Row],[Player 1]],Registrations[[#This Row],[Player 1]]&" / "&Registrations[[#This Row],[Player 2]]) -> Sanjay Gatti | F4: 606469989512
A5: Open Men Singles | B5: MS02 | E5: =IF(Registrations[[#This Row],[Player 2]]="",Registrations[[#This Row],[Player 1]],Registrations[[#This Row],[Player 1]]&" / "&Registrations[[#This Row],[Player 2]]) -> 0
A6: Open Men Singles | B6: MS03 | E6: =IF(Registrations[[#This Row],[Player 2]]="",Registrations[[#This Row],[Player 1]],Registrations[[#This Row],[Player 1]]&" / "&Registrations[[#This Row],[Player 2]]) -> 0
A7: Open Men Singles | B7: MS04 | E7: =IF(Registrations[[#This Row],[Player 2]]="",Registrations[[#This Row],[Player 1]],Registrations[[#This Row],[Player 1]]&" / "&Registrations[[#This Row],[Player 2]]) -> 0
A8: Open Men Singles | B8: MS05 | E8: =IF(Registrations[[#This Row],[Player 2]]="",Registrations[[#This Row],[Player 1]],Registrations[[#This Row],[Player 1]]&" / "&Registrations[[#This Row],[Player 2]]) -> 0
A9: Open Men Singles | B9: MS06 | E9: =IF(Registrations[[#This Row],[Player 2]]="",Registrations[[#This Row],[Player 1]],Registrations[[#This Row],[Player 1]]&" / "&Registrations[[#This Row],[Player 2]]) -> 0
A10: Open Men Singles | B10: MS07 | E10: =IF(Registrations[[#This Row],[Player 2]]="",Registrations[[#This Row],[Player 1]],Registrations[[#This Row],[Player 1]]&" / "&Registrations[[#This Row],[Player 2]]) -> 0
A11: Open Men Singles | B11: MS08 | E11: =IF(Registrations[[#This Row],[Player 2]]="",Registrations[[#This Row],[Player 1]],Registrations[[#This Row],[Player 1]]&" / "&Registrations[[#This Row],[Player 2]]) -> 0
A12: Open Men Singles | B12: MS09 | E12: =IF(Registrations[[#This Row],[Player 2]]="",Registrations[[#This Row],[Player 1]],Registrations[[#This Row],[Player 1]]&" / "&Registrations[[#This Row],[Player 2]]) -> 0
A13: Open Men Singles | B13: MS10 | E13: =IF(Registrations[[#This Row],[Player 2]]="",Registrations[[#This Row],[Player 1]],Registrations[[#This Row],[Player 1]]&" / "&Registrations[[#This Row],[Player 2]]) -> 0
A14: Open Men Singles | B14: MS11 | E14: =IF(Registrations[[#This Row],[Player 2]]="",Registrations[[#This Row],[Player 1]],Registrations[[#This Row],[Player 1]]&" / "&Registrations[[#This Row],[Player 2]]) -> 0
A15: Open Men Singles | B15: MS12 | E15: =IF(Registrations[[#This Row],[Player 2]]="",Registrations[[#This Row],[Player 1]],Registrations[[#This Row],[Player 1]]&" / "&Registrations[[#This Row],[Player 2]]) -> 0
A16: Open Men Singles | B16: MS13 | E16: =IF(Registrations[[#This Row],[Player 2]]="",Registrations[[#This Row],[Player 1]],Registrations[[#This Row],[Player 1]]&" / "&Registrations[[#This Row],[Player 2]]) -> 0
... A119: Adv Men Doubles | B119: AMD24 | E119: =IF(Registrations[[#This Row],[Player 2]]="",Registrations[[#This Row],[Player 1]],Registrations[[#This Row],[Player 1]]&" / "&Registrations[[#This Row],[Player 2]]) -> 0
A120: 45+ Split Doubles | B120: SD4501 | C120: Rajib Sengupta | D120: Antriksh Gala | E120: =IF(Registrations[[#This Row],[Player 2]]="",Registrations[[#This Row],[Player 1]],Registrations[[#This Row],[Player 1]]&" / "&Registrations[[#This Row],[Player 2]]) -> Rajib Sengupta / Antriksh Gala | F120: 643027306079
A121: 45+ Split Doubles | B121: SD4502 | C121: Pratik Bhagat | D121: Godfrey Kattancherry | E121: =IF(Registrations[[#This Row],[Player 2]]="",Registrations[[#This Row],[Player 1]],Registrations[[#This Row],[Player 1]]&" / "&Registrations[[#This Row],[Player 2]]) -> Pratik Bhagat / Godfrey Kattancherry | F121: 119739308747
A122: 45+ Split Doubles | B122: SD4503 | E122: =IF(Registrations[[#This Row],[Player 2]]="",Registrations[[#This Row],[Player 1]],Registrations[[#This Row],[Player 1]]&" / "&Registrations[[#This Row],[Player 2]]) -> 0
A123: 45+ Split Doubles | B123: SD4504 | E123: =IF(Registrations[[#This Row],[Player 2]]="",Registrations[[#This Row],[Player 1]],Registrations[[#This Row],[Player 1]]&" / "&Registrations[[#This Row],[Player 2]]) -> 0
A124: 45+ Split Doubles | B124: SD4505 | E124: =IF(Registrations[[#This Row],[Player 2]]="",Registrations[[#This Row],[Player 1]],Registrations[[#This Row],[Player 1]]&" / "&Registrations[[#This Row],[Player 2]]) -> 0
A125: 45+ Split Doubles | B125: SD4506 | E125: =IF(Registrations[[#This Row],[Player 2]]="",Registrations[[#This Row],[Player 1]],Registrations[[#This Row],[Player 1]]&" / "&Registrations[[#This Row],[Player 2]]) -> 0
A126: 45+ Split Doubles | B126: SD4507 | E126: =IF(Registrations[[#This Row],[Player 2]]="",Registrations[[#This Row],[Player 1]],Registrations[[#This Row],[Player 1]]&" / "&Registrations[[#This Row],[Player 2]]) -> 0
A127: 45+ Split Doubles | B127: SD4508 | E127: =IF(Registrations[[#This Row],[Player 2]]="",Registrations[[#This Row],[Player 1]],Registrations[[#This Row],[Player 1]]&" / "&Registrations[[#This Row],[Player 2]]) -> 0
A128: 45+ Split Doubles | B128: SD4509 | E128: =IF(Registrations[[#This Row],[Player 2]]="",Registrations[[#This Row],[Player 1]],Registrations[[#This Row],[Player 1]]&" / "&Registrations[[#This Row],[Player 2]]) -> 0
A129: 45+ Split Doubles | B129: SD4510 | E129: =IF(Registrations[[#This Row],[Player 2]]="",Registrations[[#This Row],[Player 1]],Registrations[[#This Row],[Player 1]]&" / "&Registrations[[#This Row],[Player 2]]) -> 0
A130: 45+ Split Doubles | B130: SD4511 | E130: =IF(Registrations[[#This Row],[Player 2]]="",Registrations[[#This Row],[Player 1]],Registrations[[#This Row],[Player 1]]&" / "&Registrations[[#This Row],[Player 2]]) -> 0
A131: 45+ Split Doubles | B131: SD4512 | E131: =IF(Registrations[[#This Row],[Player 2]]="",Registrations[[#This Row],[Player 1]],Registrations[[#This Row],[Player 1]]&" / "&Registrations[[#This Row],[Player 2]]) -> 0
A132: 45+ Split Doubles | B132: SD4513 | E132: =IF(Registrations[[#This Row],[Player 2]]="",Registrations[[#This Row],[Player 1]],Registrations[[#This Row],[Player 1]]&" / "&Registrations[[#This Row],[Player 2]]) -> 0
A133: 45+ Split Doubles | B133: SD4514 | E133: =IF(Registrations[[#This Row],[Player 2]]="",Registrations[[#This Row],[Player 1]],Registrations[[#This Row],[Player 1]]&" / "&Registrations[[#This Row],[Player 2]]) -> 0
... A143: 45+ Split Doubles | B143: SD4524 | E143: =IF(Registrations[[#This Row],[Player 2]]="",Registrations[[#This Row],[Player 1]],Registrations[[#This Row],[Player 1]]&" / "&Registrations[[#This Row],[Player 2]]) -> 0
A144: Beginner Men's Doubles | B144: BMD01 | C144: Sanjay Gatti | D144: Prabhakar Ghadge | E144: =IF(Registrations[[#This Row],[Player 2]]="",Registrations[[#This Row],[Player 1]],Registrations[[#This Row],[Player 1]]&" / "&Registrations[[#This Row],[Player 2]]) -> Sanjay Gatti / Prabhakar Ghadge
A145: Beginner Men's Doubles | B145: BMD02 | C145: Yash Salvi | D145: Chaitanya Hirlekar | E145: =IF(Registrations[[#This Row],[Player 2]]="",Registrations[[#This Row],[Player 1]],Registrations[[#This Row],[Player 1]]&" / "&Registrations[[#This Row],[Player 2]]) -> Yash Salvi / Chaitanya Hirlekar | F145: 606706698051 | G145: ZDXQQW | H145: XKPMX7
A146: Beginner Men's Doubles | B146: BMD03 | E146: =IF(Registrations[[#This Row],[Player 2]]="",Registrations[[#This Row],[Player 1]],Registrations[[#This Row],[Player 1]]&" / "&Registrations[[#This Row],[Player 2]]) -> 0
A147: Beginner Men's Doubles | B147: BMD04 | E147: =IF(Registrations[[#This Row],[Player 2]]="",Registrations[[#This Row],[Player 1]],Registrations[[#This Row],[Player 1]]&" / "&Registrations[[#This Row],[Player 2]]) -> 0
A148: Beginner Men's Doubles | B148: BMD05 | E148: =IF(Registrations[[#This Row],[Player 2]]="",Registrations[[#This Row],[Player 1]],Registrations[[#This Row],[Player 1]]&" / "&Registrations[[#This Row],[Player 2]]) -> 0
A149: Beginner Men's Doubles | B149: BMD06 | E149: =IF(Registrations[[#This Row],[Player 2]]="",Registrations[[#This Row],[Player 1]],Registrations[[#This Row],[Player 1]]&" / "&Registrations[[#This Row],[Player 2]]) -> 0
A150: Beginner Men's Doubles | B150: BMD07 | E150: =IF(Registrations[[#This Row],[Player 2]]="",Registrations[[#This Row],[Player 1]],Registrations[[#This Row],[Player 1]]&" / "&Registrations[[#This Row],[Player 2]]) -> 0
A151: Beginner Men's Doubles | B151: BMD08 | E151: =IF(Registrations[[#This Row],[Player 2]]="",Registrations[[#This Row],[Player 1]],Registrations[[#This Row],[Player 1]]&" / "&Registrations[[#This Row],[Player 2]]) -> 0
A152: Beginner Men's Doubles | B152: BMD09 | E152: =IF(Registrations[[#This Row],[Player 2]]="",Registrations[[#This Row],[Player 1]],Registrations[[#This Row],[Player 1]]&" / "&Registrations[[#This Row],[Player 2]]) -> 0
A153: Beginner Men's Doubles | B153: BMD10 | E153: =IF(Registrations[[#This Row],[Player 2]]="",Registrations[[#This Row],[Player 1]],Registrations[[#This Row],[Player 1]]&" / "&Registrations[[#This Row],[Player 2]]) -> 0
A154: Beginner Men's Doubles | B154: BMD11 | E154: =IF(Registrations[[#This Row],[Player 2]]="",Registrations[[#This Row],[Player 1]],Registrations[[#This Row],[Player 1]]&" / "&Registrations[[#This Row],[Player 2]]) -> 0
A155: Beginner Men's Doubles | B155: BMD12 | E155: =IF(Registrations[[#This Row],[Player 2]]="",Registrations[[#This Row],[Player 1]],Registrations[[#This Row],[Player 1]]&" / "&Registrations[[#This Row],[Player 2]]) -> 0
A156: Beginner Men's Doubles | B156: BMD13 | E156: =IF(Registrations[[#This Row],[Player 2]]="",Registrations[[#This Row],[Player 1]],Registrations[[#This Row],[Player 1]]&" / "&Registrations[[#This Row],[Player 2]]) -> 0
A157: Beginner Men's Doubles | B157: BMD14 | E157: =IF(Registrations[[#This Row],[Player 2]]="",Registrations[[#This Row],[Player 1]],Registrations[[#This Row],[Player 1]]&" / "&Registrations[[#This Row],[Player 2]]) -> 0
... A175: Beginner Men's Doubles | B175: BMD32 | E175: =IF(Registrations[[#This Row],[Player 2]]="",Registrations[[#This Row],[Player 1]],Registrations[[#This Row],[Player 1]]&" / "&Registrations[[#This Row],[Player 2]]) -> 0
A176: Beginner Mx Doubles | B176: BMX01 | C176: Sachin Verma | D176: Hema Thakkar | E176: =IF(Registrations[[#This Row],[Player 2]]="",Registrations[[#This Row],[Player 1]],Registrations[[#This Row],[Player 1]]&" / "&Registrations[[#This Row],[Player 2]]) -> Sachin Verma / Hema Thakkar | F176: 606690035274
A177: Beginner Mx Doubles | B177: BMX02 | C177: Amandeep Saini | D177: Alisha Bhise | E177: =IF(Registrations[[#This Row],[Player 2]]="",Registrations[[#This Row],[Player 1]],Registrations[[#This Row],[Player 1]]&" / "&Registrations[[#This Row],[Player 2]]) -> Amandeep Saini / Alisha Bhise | F177: 606771993193 | G177: LVZE25 | H177: PZDOMQ
A178: Beginner Mx Doubles | B178: BMX03 | C178: Nachiket Gogia | D178: Purva Verma | E178: =IF(Registrations[[#This Row],[Player 2]]="",Registrations[[#This Row],[Player 1]],Registrations[[#This Row],[Player 1]]&" / "&Registrations[[#This Row],[Player 2]]) -> Nachiket Gogia / Purva Verma | F178: 643491390309 | G178: WN02OM | H178: 5E4V50
A179: Beginner Mx Doubles | B179: BMX04 | E179: =IF(Registrations[[#This Row],[Player 2]]="",Registrations[[#This Row],[Player 1]],Registrations[[#This Row],[Player 1]]&" / "&Registrations[[#This Row],[Player 2]]) -> 0
A180: Beginner Mx Doubles | B180: BMX05 | E180: =IF(Registrations[[#This Row],[Player 2]]="",Registrations[[#This Row],[Player 1]],Registrations[[#This Row],[Player 1]]&" / "&Registrations[[#This Row],[Player 2]]) -> 0
A181: Beginner Mx Doubles | B181: BMX06 | E181: =IF(Registrations[[#This Row],[Player 2]]="",Registrations[[#This Row],[Player 1]],Registrations[[#This Row],[Player 1]]&" / "&Registrations[[#This Row],[Player 2]]) -> 0
A182: Beginner Mx Doubles | B182: BMX07 | E182: =IF(Registrations[[#This Row],[Player 2]]="",Registrations[[#This Row],[Player 1]],Registrations[[#This Row],[Player 1]]&" / "&Registrations[[#This Row],[Player 2]]) -> 0
A183: Beginner Mx Doubles | B183: BMX08 | E183: =IF(Registrations[[#This Row],[Player 2]]="",Registrations[[#This Row],[Player 1]],Registrations[[#This Row],[Player 1]]&" / "&Registrations[[#This Row],[Player 2]]) -> 0
A184: Beginner Mx Doubles | B184: BMX09 | E184: =IF(Registrations[[#This Row],[Player 2]]="",Registrations[[#This Row],[Player 1]],Registrations[[#This Row],[Player 1]]&" / "&Registrations[[#This Row],[Player 2]]) -> 0
A185: Beginner Mx Doubles | B185: BMX10 | E185: =IF(Registrations[[#This Row],[Player 2]]="",Registrations[[#This Row],[Player 1]],Registrations[[#This Row],[Player 1]]&" / "&Registrations[[#This Row],[Player 2]]) -> 0
A186: Beginner Mx Doubles | B186: BMX11 | E186: =IF(Registrations[[#This Row],[Player 2]]="",Registrations[[#This Row],[Player 1]],Registrations[[#This Row],[Player 1]]&" / "&Registrations[[#This Row],[Player 2]]) -> 0
A187: Beginner Mx Doubles | B187: BMX12 | E187: =IF(Registrations[[#This Row],[Player 2]]="",Registrations[[#This Row],[Player 1]],Registrations[[#This Row],[Player 1]]&" / "&Registrations[[#This Row],[Player 2]]) -> 0
A188: Beginner Mx Doubles | B188: BMX13 | E188: =IF(Registrations[[#This Row],[Player 2]]="",Registrations[[#This Row],[Player 1]],Registrations[[#This Row],[Player 1]]&" / "&Registrations[[#This Row],[Player 2]]) -> 0
A189: Beginner Mx Doubles | B189: BMX14 | E189: =IF(Registrations[[#This Row],[Player 2]]="",Registrations[[#This Row],[Player 1]],Registrations[[#This Row],[Player 1]]&" / "&Registrations[[#This Row],[Player 2]]) -> 0
A190: Beginner Mx Doubles | B190: BMX15 | E190: =IF(Registrations[[#This Row],[Player 2]]="",Registrations[[#This Row],[Player 1]],Registrations[[#This Row],[Player 1]]&" / "&Registrations[[#This Row],[Player 2]]) -> 0
... A211: Open Women's Doubles | B211: OMD12 | E211: =IF(Registrations[[#This Row],[Player 2]]="",Registrations[[#This Row],[Player 1]],Registrations[[#This Row],[Player 1]]&" / "&Registrations[[#This Row],[Player 2]]) -> 0

Sheet Groups
A1: Category | B1: Pool 1 | C1: ="Pool " & VALUE(RIGHT(B1, LEN(B1)-5))+1 -> Pool 2 | D1: ="Pool " & VALUE(RIGHT(C1, LEN(C1)-5))+1 -> Pool 3 | E1: ="Pool " & VALUE(RIGHT(D1, LEN(D1)-5))+1 -> Pool 4 | F1: ="Pool " & VALUE(RIGHT(E1, LEN(E1)-5))+1 -> Pool 5 | G1: ="Pool " & VALUE(RIGHT(F1, LEN(F1)-5))+1 -> Pool 6 | H1: ="Pool " & VALUE(RIGHT(G1, LEN(G1)-5))+1 -> Pool 7 | I1: ="Pool " & VALUE(RIGHT(H1, LEN(H1)-5))+1 -> Pool 8
A2: Open Men Singles | B2: ='Registrations'!E4 -> Sanjay Gatti | C2: ='Registrations'!E8 -> 0 | D2: ='Registrations'!E12 -> 0 | E2: ='Registrations'!E16 -> 0 | F2: ='Registrations'!E20 -> 0 | G2: ='Registrations'!E24 -> 0
B3: ='Registrations'!E5 -> 0 | C3: ='Registrations'!E9 -> 0 | D3: ='Registrations'!E13 -> 0 | E3: ='Registrations'!E17 -> 0 | F3: ='Registrations'!E21 -> 0 | G3: ='Registrations'!E25 -> 0
B4: ='Registrations'!E6 -> 0 | C4: ='Registrations'!E10 -> 0 | D4: ='Registrations'!E14 -> 0 | E4: ='Registrations'!E18 -> 0 | F4: ='Registrations'!E22 -> 0 | G4: ='Registrations'!E26 -> 0
B5: ='Registrations'!E7 -> 0 | C5: ='Registrations'!E11 -> 0 | D5: ='Registrations'!E15 -> 0 | E5: ='Registrations'!E19 -> 0 | F5: ='Registrations'!E23 -> 0 | G5: ='Registrations'!E27 -> 0
A7: Intermediate 35+ Split Doubles | B7: ='Registrations'!E28 -> 0 | C7: ='Registrations'!E32 -> 0 | D7: ='Registrations'!E36 -> 0
B8: ='Registrations'!E29 -> 0 | C8: ='Registrations'!E33 -> 0 | D8: ='Registrations'!E37 -> 0
B9: ='Registrations'!E30 -> 0 | C9: ='Registrations'!E34 -> 0 | D9: ='Registrations'!E38 -> 0
B10: ='Registrations'!E31 -> 0 | C10: ='Registrations'!E35 -> 0 | D10: ='Registrations'!E39 -> 0
A12: Int Men Doubles | B12: ='Registrations'!E40 -> 0 | C12: ='Registrations'!E44 -> 0 | D12: ='Registrations'!E48 -> 0 | E12: ='Registrations'!E52 -> 0 | F12: ='Registrations'!E56 -> 0 | G12: ='Registrations'!E60 -> 0 | H12: ='Registrations'!E64 -> 0 | I12: ='Registrations'!E68 -> 0
B13: ='Registrations'!E41 -> 0 | C13: ='Registrations'!E45 -> 0 | D13: ='Registrations'!E49 -> 0 | E13: ='Registrations'!E53 -> 0 | F13: ='Registrations'!E57 -> 0 | G13: ='Registrations'!E61 -> 0 | H13: ='Registrations'!E65 -> 0 | I13: ='Registrations'!E69 -> 0
B14: ='Registrations'!E42 -> 0 | C14: ='Registrations'!E46 -> 0 | D14: ='Registrations'!E50 -> 0 | E14: ='Registrations'!E54 -> 0 | F14: ='Registrations'!E58 -> 0 | G14: ='Registrations'!E62 -> 0 | H14: ='Registrations'!E66 -> 0 | I14: ='Registrations'!E70 -> 0
B15: ='Registrations'!E43 -> 0 | C15: ='Registrations'!E47 -> 0 | D15: ='Registrations'!E51 -> 0 | E15: ='Registrations'!E55 -> 0 | F15: ='Registrations'!E59 -> 0 | G15: ='Registrations'!E63 -> 0 | H15: ='Registrations'!E67 -> 0 | I15: ='Registrations'!E71 -> 0
A17: Open Mixed Doubles | B17: ='Registrations'!E72 -> 0 | C17: ='Registrations'!E76 -> 0 | D17: ='Registrations'!E80 -> 0 | E17: ='Registrations'!E84 -> 0 | F17: ='Registrations'!E88 -> 0 | G17: ='Registrations'!E92 -> 0
B18: ='Registrations'!E73 -> 0 | C18: ='Registrations'!E77 -> 0 | D18: ='Registrations'!E81 -> 0 | E18: ='Registrations'!E85 -> 0 | F18: ='Registrations'!E89 -> 0 | G18: ='Registrations'!E93 -> 0
B19: ='Registrations'!E74 -> 0 | C19: ='Registrations'!E78 -> 0 | D19: ='Registrations'!E82 -> 0 | E19: ='Registrations'!E86 -> 0 | F19: ='Registrations'!E90 -> 0 | G19: ='Registrations'!E94 -> 0
B20: ='Registrations'!E75 -> 0 | C20: ='Registrations'!E79 -> 0 | D20: ='Registrations'!E83 -> 0 | E20: ='Registrations'!E87 -> 0 | F20: ='Registrations'!E91 -> 0 | G20: ='Registrations'!E95 -> 0
A22: Adv Men Doubles | B22: ='Registrations'!E96 -> 0 | C22: ='Registrations'!E100 -> 0 | D22: ='Registrations'!E104 -> 0 | E22: ='Registrations'!E108 -> 0 | F22: ='Registrations'!E112 -> 0 | G22: ='Registrations'!E116 -> 0
B23: ='Registrations'!E97 -> 0 | C23: ='Registrations'!E101 -> 0 | D23: ='Registrations'!E105 -> 0 | E23: ='Registrations'!E109 -> 0 | F23: ='Registrations'!E113 -> 0 | G23: ='Registrations'!E117 -> 0
B24: ='Registrations'!E98 -> 0 | C24: ='Registrations'!E102 -> 0 | D24: ='Registrations'!E106 -> 0 | E24: ='Registrations'!E110 -> 0 | F24: ='Registrations'!E114 -> 0 | G24: ='Registrations'!E118 -> 0
B25: ='Registrations'!E99 -> 0 | C25: ='Registrations'!E103 -> 0 | D25: ='Registrations'!E107 -> 0 | E25: ='Registrations'!E111 -> 0 | F25: ='Registrations'!E115 -> 0 | G25: ='Registrations'!E119 -> 0
A27: Open Women's Doubles | B27: ='Registrations'!E200 -> 0 | C27: ='Registrations'!E204 -> 0 | D27: ='Registrations'!E208 -> 0
B28: ='Registrations'!E201 -> 0 | C28: ='Registrations'!E205 -> 0 | D28: ='Registrations'!E209 -> 0
B29: ='Registrations'!E202 -> 0 | C29: ='Registrations'!E206 -> 0 | D29: ='Registrations'!E210 -> 0
B30: ='Registrations'!E203 -> 0 | C30: ='Registrations'!E207 -> 0 | D30: ='Registrations'!E211 -> 0
A32: 45+ Split Doubles | B32: ='Registrations'!E120 -> Rajib Sengupta / Antriksh Gala | C32: ='Registrations'!E124 -> 0 | D32: ='Registrations'!E128 -> 0 | E32: ='Registrations'!E132 -> 0 | F32: ='Registrations'!E136 -> 0 | G32: ='Registrations'!E140 -> 0
B33: ='Registrations'!E121 -> Pratik Bhagat / Godfrey Kattancherry | C33: ='Registrations'!E125 -> 0 | D33: ='Registrations'!E129 -> 0 | E33: ='Registrations'!E133 -> 0 | F33: ='Registrations'!E137 -> 0 | G33: ='Registrations'!E141 -> 0
B34: ='Registrations'!E122 -> 0 | C34: ='Registrations'!E126 -> 0 | D34: ='Registrations'!E130 -> 0 | E34: ='Registrations'!E134 -> 0 | F34: ='Registrations'!E138 -> 0 | G34: ='Registrations'!E142 -> 0
B35: ='Registrations'!E123 -> 0 | C35: ='Registrations'!E127 -> 0 | D35: ='Registrations'!E131 -> 0 | E35: ='Registrations'!E135 -> 0 | F35: ='Registrations'!E139 -> 0 | G35: ='Registrations'!E143 -> 0
A37: Beginner Men's Doubles | B37: ='Registrations'!E144 -> Sanjay Gatti / Prabhakar Ghadge | C37: ='Registrations'!E148 -> 0 | D37: ='Registrations'!E152 -> 0 | E37: ='Registrations'!E156 -> 0 | F37: ='Registrations'!E160 -> 0 | G37: ='Registrations'!E164 -> 0 | H37: ='Registrations'!E168 -> 0 | I37: ='Registrations'!E172 -> 0
B38: ='Registrations'!E145 -> Yash Salvi / Chaitanya Hirlekar | C38: ='Registrations'!E149 -> 0 | D38: ='Registrations'!E153 -> 0 | E38: ='Registrations'!E157 -> 0 | F38: ='Registrations'!E161 -> 0 | G38: ='Registrations'!E165 -> 0 | H38: ='Registrations'!E169 -> 0 | I38: ='Registrations'!E173 -> 0
B39: ='Registrations'!E146 -> 0 | C39: ='Registrations'!E150 -> 0 | D39: ='Registrations'!E154 -> 0 | E39: ='Registrations'!E158 -> 0 | F39: ='Registrations'!E162 -> 0 | G39: ='Registrations'!E166 -> 0 | H39: ='Registrations'!E170 -> 0 | I39: ='Registrations'!E174 -> 0
B40: ='Registrations'!E147 -> 0 | C40: ='Registrations'!E151 -> 0 | D40: ='Registrations'!E155 -> 0 | E40: ='Registrations'!E159 -> 0 | F40: ='Registrations'!E163 -> 0 | G40: ='Registrations'!E167 -> 0 | H40: ='Registrations'!E171 -> 0 | I40: ='Registrations'!E175 -> 0
A42: Beginner Mx Doubles | B42: ='Registrations'!E176 -> Sachin Verma / Hema Thakkar | C42: ='Registrations'!E180 -> 0 | D42: ='Registrations'!E184 -> 0 | E42: ='Registrations'!E188 -> 0 | F42: ='Registrations'!E192 -> 0 | G42: ='Registrations'!E196 -> 0
B43: ='Registrations'!E177 -> Amandeep Saini / Alisha Bhise | C43: ='Registrations'!E181 -> 0 | D43: ='Registrations'!E185 -> 0 | E43: ='Registrations'!E189 -> 0 | F43: ='Registrations'!E193 -> 0 | G43: ='Registrations'!E197 -> 0
B44: ='Registrations'!E178 -> Nachiket Gogia / Purva Verma | C44: ='Registrations'!E182 -> 0 | D44: ='Registrations'!E186 -> 0 | E44: ='Registrations'!E190 -> 0 | F44: ='Registrations'!E194 -> 0 | G44: ='Registrations'!E198 -> 0
B45: ='Registrations'!E179 -> 0 | C45: ='Registrations'!E183 -> 0 | D45: ='Registrations'!E187 -> 0 | E45: ='Registrations'!E191 -> 0 | F45: ='Registrations'!E195 -> 0 | G45: ='Registrations'!E199 -> 0

Sheet Input
A1: Open Men's Singles
A2: Group Stage | H2: Pre-Quarters | L2: Quarters | P2: Semis | T2: Finals
A3: Pool 1 | B3: {=TRANSPOSE(Groups!B2:B5)} -> Sanjay Gatti | C3: 0 | D3: 0 | E3: 0 | G3: Pool 1 vs 2 | H3: =B3 -> Sanjay Gatti | I3: =D4 -> 0 | K3: Pool 1 vs 6 | L3: =H3 -> Sanjay Gatti | M3: =H8 -> 0 | O3: Pool 1 vs 3 | P3: =L3 -> Sanjay Gatti | Q3: =L5 -> 0 | T3: =P3 -> Sanjay Gatti | U3: =P4 -> 0
A4: ="Pool " & VALUE(RIGHT(A3, LEN(A3)-5))+1 -> Pool 2 | B4: {=TRANSPOSE(Groups!C2:C5)} -> 0 | C4: 0 | D4: 0 | E4: 0 | G4: =G3 -> Pool 1 vs 2 | H4: =D3 -> 0 | I4: =B4 -> 0 | K4: Pool 2 vs 5 | L4: =H4 -> 0 | M4: =H7 -> 0 | O4: Pool 2 vs WC | P4: =L4 -> 0 | Q4: WC 01
A5: ="Pool " & VALUE(RIGHT(A4, LEN(A4)-5))+1 -> Pool 3 | B5: {=TRANSPOSE(Groups!D2:D5)} -> 0 | C5: 0 | D5: 0 | E5: 0 | G5: Pool 3 vs 4 | H5: =B5 -> 0 | I5: =D6 -> 0 | K5: Pool 3 vs 4 | L5: =H5 -> 0 | M5: =H6 -> 0
A6: ="Pool " & VALUE(RIGHT(A5, LEN(A5)-5))+1 -> Pool 4 | B6: {=TRANSPOSE(Groups!E2:E5)} -> 0 | C6: 0 | D6: 0 | E6: 0 | G6: =G5 -> Pool 3 vs 4 | H6: =D5 -> 0 | I6: =B6 -> 0
A7: ="Pool " & VALUE(RIGHT(A6, LEN(A6)-5))+1 -> Pool 5 | B7: {=TRANSPOSE(Groups!F2:F5)} -> 0 | C7: 0 | D7: 0 | E7: 0 | G7: Pool 5 vs 6 | H7: =B7 -> 0 | I7: =D8 -> 0
A8: ="Pool " & VALUE(RIGHT(A7, LEN(A7)-5))+1 -> Pool 6 | B8: {=TRANSPOSE(Groups!G2:G5)} -> 0 | C8: 0 | D8: 0 | E8: 0 | G8: =G7 -> Pool 5 vs 6 | H8: =D7 -> 0 | I8: =B8 -> 0
A9: ="Pool " & VALUE(RIGHT(A8, LEN(A8)-5))+1 -> Pool 7
A10: ="Pool " & VALUE(RIGHT(A9, LEN(A9)-5))+1 -> Pool 8
A12: Intermediate 35+ Split Doubles
A13: =A2 -> Group Stage | H13: Quarters | L13: Semis | P13: Finals
A14: =A3 -> Pool 1 | B14: {=TRANSPOSE(Groups!B7:B10)} -> 0 | C14: 0 | D14: 0 | E14: 0 | G14: Pool 1 vs 3 | H14: =B14 -> 0 | I14: =D16 -> 0 | K14: Pool 1 vs 2 | L14: =H14 -> 0 | M14: =H15 -> 0 | P14: =L14 -> 0 | Q14: =L15 -> 0
A15: =A4 -> Pool 2 | B15: {=TRANSPOSE(Groups!C7:C10)} -> 0 | C15: 0 | D15: 0 | E15: 0 | G15: Pool 2 vs 1 | H15: =B15 -> 0 | I15: =D14 -> 0 | K15: Pool 3 vs 4 | L15: =H16 -> 0 | M15: WC 1
A16: =A5 -> Pool 3 | B16: {=TRANSPOSE(Groups!D7:D10)} -> 0 | C16: 0 | D16: 0 | E16: 0 | G16: Pool 3 vs 2 | H16: =B16 -> 0 | I16: =D15 -> 0
A17: =A6 -> Pool 4
A18: =A7 -> Pool 5
A19: =A8 -> Pool 6
A20: =A9 -> Pool 7
A21: =A10 -> Pool 8
A23: Intermediate Men's Doubles
A24: =A13 -> Group Stage | H24: Pre-Quarters | L24: Quarters | P24: Semis | T24: Finals
A25: =A14 -> Pool 1 | B25: {=TRANSPOSE(Groups!B12:B15)} -> 0 | C25: 0 | D25: 0 | E25: 0 | G25: Pool 1 vs 2 | H25: =B25 -> 0 | I25: =D26 -> 0 | K25: Pool 1 vs 8 | L25: =H25 -> 0 | M25: =H32 -> 0 | O25: 1 vs 4 | P25: =L25 -> 0 | Q25: =L28 -> 0 | S25: 1 vs 2 | T25: =P25 -> 0 | U25: =P26 -> 0
A26: =A15 -> Pool 2 | B26: {=TRANSPOSE(Groups!C12:C15)} -> 0 | C26: 0 | D26: 0 | E26: 0 | G26: =G25 -> Pool 1 vs 2 | H26: =D25 -> 0 | I26: =B26 -> 0 | K26: Pool 2 vs 7 | L26: =H26 -> 0 | M26: =H31 -> 0 | O26: 2 vs 3 | P26: =L26 -> 0 | Q26: =L27 -> 0
A27: =A16 -> Pool 3 | B27: {=TRANSPOSE(Groups!D12:D15)} -> 0 | C27: 0 | D27: 0 | E27: 0 | G27: Pool 3 vs 4 | H27: =B27 -> 0 | I27: =D28 -> 0 | K27: Pool 3 vs 6 | L27: =H27 -> 0 | M27: =H30 -> 0
A28: =A17 -> Pool 4 | B28: {=TRANSPOSE(Groups!E12:E15)} -> 0 | C28: 0 | D28: 0 | E28: 0 | G28: =G27 -> Pool 3 vs 4 | H28: =D27 -> 0 | I28: =B28 -> 0 | K28: Pool 4 vs 5 | L28: =H28 -> 0 | M28: =H29 -> 0
A29: =A18 -> Pool 5 | B29: {=TRANSPOSE(Groups!F12:F15)} -> 0 | C29: 0 | D29: 0 | E29: 0 | G29: Pool 5 vs 6 | H29: =B29 -> 0 | I29: =D30 -> 0
A30: =A19 -> Pool 6 | B30: {=TRANSPOSE(Groups!G12:G15)} -> 0 | C30: 0 | D30: 0 | E30: 0 | G30: =G29 -> Pool 5 vs 6 | H30: =D29 -> 0 | I30: =B30 -> 0
A31: =A20 -> Pool 7 | B31: {=TRANSPOSE(Groups!H12:H15)} -> 0 | C31: 0 | D31: 0 | E31: 0 | G31: Pool 7 vs 8 | H31: =B31 -> 0 | I31: =D32 -> 0
A32: =A21 -> Pool 8 | B32: {=TRANSPOSE(Groups!I12:I15)} -> 0 | C32: 0 | D32: 0 | E32: 0 | G32: =G31 -> Pool 7 vs 8 | H32: =D31 -> 0 | I32: =B32 -> 0
A34: Open Mixed Doubles
A35: =A24 -> Group Stage | H35: Pre-Quarters | L35: Quarters | P35: Semis | T35: Finals
A36: =A25 -> Pool 1 | B36: {=TRANSPOSE(Groups!B17:B20)} -> 0 | C36: 0 | D36: 0 | E36: 0 | G36: Pool 1 vs 2 | H36: =B36 -> 0 | I36: =D37 -> 0 | K36: Pool 1 vs 6 | L36: =H36 -> 0 | M36: =H41 -> 0 | O36: 1 vs 4 | P36: =L36 -> 0 | Q36: =L38 -> 0 | S36: 1 vs 2 | T36: =P36 -> 0 | U36: =P37 -> 0
A37: =A26 -> Pool 2 | B37: {=TRANSPOSE(Groups!C17:C20)} -> 0 | C37: 0 | D37: 0 | E37: 0 | G37: =G36 -> Pool 1 vs 2 | H37: =D36 -> 0 | I37: =B37 -> 0 | K37: Pool 2 vs 5 | L37: =H37 -> 0 | M37: =H40 -> 0 | O37: 2 vs 3 | P37: =L37 -> 0 | Q37: WC 1
A38: =A27 -> Pool 3 | B38: {=TRANSPOSE(Groups!D17:D20)} -> 0 | C38: 0 | D38: 0 | E38: 0 | G38: Pool 3 vs 4 | H38: =B38 -> 0 | I38: =D39 -> 0 | K38: Pool 3 vs 4 | L38: =H38 -> 0 | M38: =H39 -> 0
A39: =A28 -> Pool 4 | B39: {=TRANSPOSE(Groups!E17:E20)} -> 0 | C39: 0 | D39: 0 | E39: 0 | G39: =G38 -> Pool 3 vs 4 | H39: =D38 -> 0 | I39: =B39 -> 0
A40: =A29 -> Pool 5 | B40: {=TRANSPOSE(Groups!F17:F20)} -> 0 | C40: 0 | D40: 0 | E40: 0 | G40: Pool 5 vs 6 | H40: =B40 -> 0 | I40: =D41 -> 0
A41: =A30 -> Pool 6 | B41: {=TRANSPOSE(Groups!G17:G20)} -> 0 | C41: 0 | D41: 0 | E41: 0 | G41: =G40 -> Pool 5 vs 6 | H41: =D40 -> 0 | I41: =B41 -> 0
A42: =A31 -> Pool 7
A43: =A32 -> Pool 8
A45: Advanced Men's Doubles
A46: =A35 -> Group Stage | H46: Pre-Quarters | L46: Quarters | P46: Semis | T46: Finals
A47: =A36 -> Pool 1 | B47: {=TRANSPOSE(Groups!B22:B25)} -> 0 | C47: 0 | D47: 0 | E47: 0 | G47: Pool 1 vs 2 | H47: =B47 -> 0 | I47: =D48 -> 0 | K47: Pool 1 vs 6 | L47: =H47 -> 0 | M47: =H52 -> 0 | O47: 1 vs 4 | P47: =L47 -> 0 | Q47: =L49 -> 0 | S47: 1 vs 2 | T47: =P47 -> 0 | U47: =P48 -> 0
A48: =A37 -> Pool 2 | B48: {=TRANSPOSE(Groups!C22:C25)} -> 0 | C48: 0 | D48: 0 | E48: 0 | G48: =G47 -> Pool 1 vs 2 | H48: =D47 -> 0 | I48: =B48 -> 0 | K48: Pool 2 vs 5 | L48: =H48 -> 0 | M48: =H51 -> 0 | O48: 2 vs 3 | P48: =L48 -> 0 | Q48: WC 1
A49: =A38 -> Pool 3 | B49: {=TRANSPOSE(Groups!D22:D25)} -> 0 | C49: 0 | D49: 0 | E49: 0 | G49: Pool 3 vs 4 | H49: =B49 -> 0 | I49: =D50 -> 0 | K49: Pool 3 vs 4 | L49: =H49 -> 0 | M49: =H50 -> 0
A50: =A39 -> Pool 4 | B50: {=TRANSPOSE(Groups!E22:E25)} -> 0 | C50: 0 | D50: 0 | E50: 0 | G50: =G49 -> Pool 3 vs 4 | H50: =D49 -> 0 | I50: =B50 -> 0
A51: =A40 -> Pool 5 | B51: {=TRANSPOSE(Groups!F22:F25)} -> 0 | C51: 0 | D51: 0 | E51: 0 | G51: Pool 5 vs 6 | H51: =B51 -> 0 | I51: =D52 -> 0
A52: =A41 -> Pool 6 | B52: {=TRANSPOSE(Groups!G22:G25)} -> 0 | C52: 0 | D52: 0 | E52: 0 | G52: =G51 -> Pool 5 vs 6 | H52: =D51 -> 0 | I52: =B52 -> 0
A53: =A42 -> Pool 7
A54: =A43 -> Pool 8
A56: Open Women's Doubles
A57: =A46 -> Group Stage | H57: Quarters | L57: Semis | P57: Finals
A58: =A47 -> Pool 1 | B58: {=TRANSPOSE(Groups!B27:B30)} -> 0 | C58: 0 | D58: 0 | E58: 0 | G58: Pool 1 vs 3 | H58: =B58 -> 0 | I58: =D60 -> 0 | K58: Pool 1 vs 2 | L58: =H58 -> 0 | M58: =H59 -> 0 | O58: Pool 1 vs 2 | P58: =L58 -> 0 | Q58: =L59 -> 0
A59: =A48 -> Pool 2 | B59: {=TRANSPOSE(Groups!C27:C30)} -> 0 | C59: 0 | D59: 0 | E59: 0 | G59: Pool 2 vs 1 | H59: =B59 -> 0 | I59: =D58 -> 0 | K59: Pool 3 vs 4 | L59: =H60 -> 0 | M59: WC 1
A60: =A49 -> Pool 3 | B60: {=TRANSPOSE(Groups!D27:D30)} -> 0 | C60: 0 | D60: 0 | E60: 0 | G60: Pool 3 vs 2 | H60: =B60 -> 0 | I60: =D59 -> 0
A61: =A50 -> Pool 4
A62: =A51 -> Pool 5
A63: =A52 -> Pool 6
A64: =A53 -> Pool 7
A65: =A54 -> Pool 8
A67: 45+ Split Doubles
A68: =A13 -> Group Stage | H68: Pre-Quarters | L68: Quarters | P68: Semis | T68: Finals
A69: =A14 -> Pool 1 | B69: {=TRANSPOSE(Groups!B32:B35)} -> Rajib Sengupta / Antriksh Gala | C69: Pratik Bhagat / Godfrey Kattancherry | D69: 0 | E69: 0 | G69: Pool 1 vs 2 | H69: =B69 -> Rajib Sengupta / Antriksh Gala | I69: =D70 -> 0 | K69: Pool 1 vs 6 | L69: =H69 -> Rajib Sengupta / Antriksh Gala | M69: =H74 -> 0 | O69: 1 vs 4 | P69: =L69 -> Rajib Sengupta / Antriksh Gala | Q69: =L71 -> 0 | S69: 1 vs 2 | T69: =P69 -> Rajib Sengupta / Antriksh Gala | U69: =P70 -> 0
A70: =A15 -> Pool 2 | B70: {=TRANSPOSE(Groups!C32:C35)} -> 0 | C70: 0 | D70: 0 | E70: 0 | G70: Pool 1 vs 2 | H70: =B70 -> 0 | I70: =D69 -> 0 | K70: Pool 2 vs 5 | L70: =H70 -> 0 | M70: =H73 -> 0 | O70: 2 vs 3 | P70: =L70 -> 0 | Q70: WC 1
A71: =A16 -> Pool 3 | B71: {=TRANSPOSE(Groups!D32:D35)} -> 0 | C71: 0 | D71: 0 | E71: 0 | G71: Pool 3 vs 4 | H71: =B71 -> 0 | I71: =D72 -> 0 | K71: Pool 3 vs 4 | L71: =H71 -> 0 | M71: =H72 -> 0
A72: =A17 -> Pool 4 | B72: {=TRANSPOSE(Groups!E32:E35)} -> 0 | C72: 0 | D72: 0 | E72: 0 | G72: Pool 3 vs 4 | H72: =B72 -> 0 | I72: =D71 -> 0
A73: =A18 -> Pool 5 | B73: {=TRANSPOSE(Groups!F32:F35)} -> 0 | C73: 0 | D73: 0 | E73: 0 | G73: Pool 5 vs 6 | H73: =B73 -> 0 | I73: =D74 -> 0
A74: =A19 -> Pool 6 | B74: {=TRANSPOSE(Groups!G32:G35)} -> 0 | C74: 0 | D74: 0 | E74: 0 | G74: Pool 5 vs 6 | H74: =B74 -> 0 | I74: =D73 -> 0
A75: =A20 -> Pool 7
A76: =A21 -> Pool 8
A78: Beginner Men's Doubles
A79: =A22 -> 0 | H79: Pre-Quarters | L79: Quarters | P79: Semis | T79: Finals
A80: =A69 -> Pool 1 | B80: {=TRANSPOSE(Groups!B37:B40)} -> Sanjay Gatti / Prabhakar Ghadge | C80: Yash Salvi / Chaitanya Hirlekar | D80: 0 | E80: 0 | G80: Pool 1 vs 2 | H80: =B80 -> Sanjay Gatti / Prabhakar Ghadge | I80: =D81 -> 0 | K80: Pool 1 vs 8 | L80: =H80 -> Sanjay Gatti / Prabhakar Ghadge | M80: =H87 -> 0 | O80: 1 vs 4 | P80: =L80 -> Sanjay Gatti / Prabhakar Ghadge | Q80: =L83 -> 0 | S80: 1 vs 2 | T80: =P80 -> Sanjay Gatti / Prabhakar Ghadge | U80: =P81 -> 0
A81: =A70 -> Pool 2 | B81: {=TRANSPOSE(Groups!C37:C40)} -> 0 | C81: 0 | D81: 0 | E81: 0 | G81: =G80 -> Pool 1 vs 2 | H81: =D80 -> 0 | I81: =B81 -> 0 | K81: Pool 2 vs 7 | L81: =H81 -> 0 | M81: =H86 -> 0 | O81: 2 vs 3 | P81: =L81 -> 0 | Q81: =L82 -> 0
A82: =A71 -> Pool 3 | B82: {=TRANSPOSE(Groups!D37:D40)} -> 0 | C82: 0 | D82: 0 | E82: 0 | G82: Pool 3 vs 4 | H82: =B82 -> 0 | I82: =D83 -> 0 | K82: Pool 3 vs 6 | L82: =H82 -> 0 | M82: =H85 -> 0
A83: =A72 -> Pool 4 | B83: {=TRANSPOSE(Groups!E37:E40)} -> 0 | C83: 0 | D83: 0 | E83: 0 | G83: =G82 -> Pool 3 vs 4 | H83: =D82 -> 0 | I83: =B83 -> 0 | K83: Pool 4 vs 5 | L83: =H83 -> 0 | M83: =H84 -> 0
A84: =A73 -> Pool 5 | B84: {=TRANSPOSE(Groups!F37:F40)} -> 0 | C84: 0 | D84: 0 | E84: 0 | G84: Pool 5 vs 6 | H84: =B84 -> 0 | I84: =D85 -> 0
A85: =A74 -> Pool 6 | B85: {=TRANSPOSE(Groups!G37:G40)} -> 0 | C85: 0 | D85: 0 | E85: 0 | G85: =G84 -> Pool 5 vs 6 | H85: =D84 -> 0 | I85: =B85 -> 0
A86: =A75 -> Pool 7 | B86: {=TRANSPOSE(Groups!H37:H40)} -> 0 | C86: 0 | D86: 0 | E86: 0 | G86: Pool 7 vs 8 | H86: =B86 -> 0 | I86: =D87 -> 0
A87: =A76 -> Pool 8 | B87: {=TRANSPOSE(Groups!I37:I40)} -> 0 | C87: 0 | D87: 0 | E87: 0 | G87: =G86 -> Pool 7 vs 8 | H87: =D86 -> 0 | I87: =B87 -> 0
A89: Beginner Mixed Doubles
A90: =A33 -> 0 | H90: Pre-Quarters | L90: Quarters | P90: Semis | T90: Finals
A91: =A80 -> Pool 1 | B91: {=TRANSPOSE(Groups!B42:B45)} -> Sachin Verma / Hema Thakkar | C91: Amandeep Saini / Alisha Bhise | D91: Nachiket Gogia / Purva Verma | E91: 0 | G91: Pool 1 vs 2 | H91: =B91 -> Sachin Verma / Hema Thakkar | I91: =D92 -> 0 | K91: Pool 1 vs 6 | L91: =H91 -> Sachin Verma / Hema Thakkar | M91: =H96 -> 0 | O91: 1 vs 4 | P91: =L91 -> Sachin Verma / Hema Thakkar | Q91: =L93 -> 0 | S91: 1 vs 2 | T91: =P91 -> Sachin Verma / Hema Thakkar | U91: =P92 -> Nachiket Gogia / Purva Verma
A92: =A81 -> Pool 2 | B92: {=TRANSPOSE(Groups!C42:C45)} -> 0 | C92: 0 | D92: 0 | E92: 0 | G92: =G91 -> Pool 1 vs 2 | H92: =D91 -> Nachiket Gogia / Purva Verma | I92: =B92 -> 0 | K92: Pool 2 vs 5 | L92: =H92 -> Nachiket Gogia / Purva Verma | M92: =H95 -> 0 | O92: 2 vs 3 | P92: =L92 -> Nachiket Gogia / Purva Verma | Q92: WC 1
A93: =A82 -> Pool 3 | B93: {=TRANSPOSE(Groups!D42:D45)} -> 0 | C93: 0 | D93: 0 | E93: 0 | G93: Pool 3 vs 4 | H93: =B93 -> 0 | I93: =D94 -> 0 | K93: Pool 3 vs 4 | L93: =H93 -> 0 | M93: =H94 -> 0
A94: =A83 -> Pool 4 | B94: {=TRANSPOSE(Groups!E42:E45)} -> 0 | C94: 0 | D94: 0 | E94: 0 | G94: =G93 -> Pool 3 vs 4 | H94: =D93 -> 0 | I94: =B94 -> 0
A95: =A84 -> Pool 5 | B95: {=TRANSPOSE(Groups!F42:F45)} -> 0 | C95: 0 | D95: 0 | E95: 0 | G95: Pool 5 vs 6 | H95: =B95 -> 0 | I95: =D96 -> 0
A96: =A85 -> Pool 6 | B96: {=TRANSPOSE(Groups!G42:G45)} -> 0 | C96: 0 | D96: 0 | E96: 0 | G96: =G95 -> Pool 5 vs 6 | H96: =D95 -> 0 | I96: =B96 -> 0
A97: =A86 -> Pool 7
A98: =A87 -> Pool 8

Sheet Schedule
A1: Category | B1: Venue | C1: Start Time | D1: End Time | E1: Round Name | F1: Court No | G1: Pool No | H1: Match Details | I1: Player 1 | J1: Player 2 | K1: Team 1 Name | L1: Team 1 Score | M1: Team 1 Outcome | N1: Player 3 | O1: Player 4 | P1: Team 2 Name | Q1: Team 2 Score | R1: Team 2 Outcome | S1: TeamA_Code | T1: TeamB_Code | U1: Colour Legend
A2: Open Men Singles | B2: Adda | C2: 46117.292 | D2: =C2+TIME(0,7,0) -> 46117.297 | E2: Group | F2: 1 | G2: 1 | H2: =IF(OR(S2="",T2=""),"",IFERROR(_xludf.XLOOKUP(S2,'Registrations'!#REF!,'Registrations'!#REF!,_xludf.XLOOKUP(S2,'Registrations'!$B$4:$B$211,'Registrations'!$E$4:$E$211,S2)),S2) & " vs " & IFERROR(_xludf.XLOOKUP(T2,'Registrations'!#REF!,'Registrations'!#REF!,_xludf.XLOOKUP(T2,'Registrations'!$B$4:$B$211,'Registrations'!$E$4:$E$211,T2)),T2)) -> Sanjay Gatti vs 0 | I2: =_xlfn.TEXTBEFORE(H2," vs ") -> Sanjay Gatti | J2: =_xlfn.TEXTAFTER(H2," vs ") -> 0 | K2: =Schedules[[#This Row],[Player 1]] -> Sanjay Gatti | L2: 15 | M2: =IF(L2=15,"WIN","LOST") -> WIN | P2: =Schedules[[#This Row],[Player 2]] -> 0 | Q2: 10 | R2: =IF(Q2=15,"WIN","LOST") -> LOST | S2: =Input!B3 -> Sanjay Gatti | T2: =Input!C3 -> 0 | U2: Group
A3: Open Men Singles | B3: =B2 -> Adda | C3: =C2 -> 46117.292 | D3: =D2 -> 46117.297 | E3: =E2 -> Group | F3: 2 | G3: 2 | H3: =IF(OR(S3="",T3=""),"",IFERROR(_xludf.XLOOKUP(S3,'Registrations'!#REF!,'Registrations'!#REF!,_xludf.XLOOKUP(S3,'Registrations'!$B$4:$B$211,'Registrations'!$E$4:$E$211,S3)),S3) & " vs " & IFERROR(_xludf.XLOOKUP(T3,'Registrations'!#REF!,'Registrations'!#REF!,_xludf.XLOOKUP(T3,'Registrations'!$B$4:$B$211,'Registrations'!$E$4:$E$211,T3)),T3)) -> 0 vs 0 | I3: =_xlfn.TEXTBEFORE(H3," vs ") -> 0 | J3: =_xlfn.TEXTAFTER(H3," vs ") -> 0 | K3: =Schedules[[#This Row],[Player 1]] -> 0 | L3: 15 | M3: =IF(L3=15,"WIN","LOST") -> WIN | P3: =Schedules[[#This Row],[Player 2]] -> 0 | Q3: 10 | R3: =IF(Q3=15,"WIN","LOST") -> LOST | S3: =Input!B4 -> 0 | T3: =Input!C4 -> 0 | U3: Pre-Quarters
A4: Open Men Singles | B4: =B3 -> Adda | C4: =D3+TIME(0,3,0) -> 46117.299 | D4: =C4+TIME(0,7,0) -> 46117.303 | E4: =E3 -> Group | F4: =F2 -> 1 | G4: =G2 -> 1 | H4: =IF(OR(S4="",T4=""),"",IFERROR(_xludf.XLOOKUP(S4,'Registrations'!#REF!,'Registrations'!#REF!,_xludf.XLOOKUP(S4,'Registrations'!$B$4:$B$211,'Registrations'!$E$4:$E$211,S4)),S4) & " vs " & IFERROR(_xludf.XLOOKUP(T4,'Registrations'!#REF!,'Registrations'!#REF!,_xludf.XLOOKUP(T4,'Registrations'!$B$4:$B$211,'Registrations'!$E$4:$E$211,T4)),T4)) -> 0 vs 0 | I4: =_xlfn.TEXTBEFORE(H4," vs ") -> 0 | J4: =_xlfn.TEXTAFTER(H4," vs ") -> 0 | K4: =Schedules[[#This Row],[Player 1]] -> 0 | L4: 15 | M4: =IF(L4=15,"WIN","LOST") -> WIN | P4: =Schedules[[#This Row],[Player 2]] -> 0 | Q4: 10 | R4: =IF(Q4=15,"WIN","LOST") -> LOST | S4: =Input!D3 -> 0 | T4: =Input!E3 -> 0 | U4: Quarters
A5: Open Men Singles | B5: =B4 -> Adda | C5: =C4 -> 46117.299 | D5: =D4 -> 46117.303 | E5: =E4 -> Group | F5: =F3 -> 2 | G5: =G3 -> 2 | H5: =IF(OR(S4="",T4=""),"",IFERROR(_xludf.XLOOKUP(S4,'Registrations'!#REF!,'Registrations'!#REF!,_xludf.XLOOKUP(S4,'Registrations'!$B$4:$B$211,'Registrations'!$E$4:$E$211,S4)),S4) & " vs " & IFERROR(_xludf.XLOOKUP(T4,'Registrations'!#REF!,'Registrations'!#REF!,_xludf.XLOOKUP(T4,'Registrations'!$B$4:$B$211,'Registrations'!$E$4:$E$211,T4)),T4)) -> 0 vs 0 | I5: =_xlfn.TEXTBEFORE(H5," vs ") -> 0 | J5: =_xlfn.TEXTAFTER(H5," vs ") -> 0 | K5: =Schedules[[#This Row],[Player 1]] -> 0 | L5: 15 | M5: =IF(L5=15,"WIN","LOST") -> WIN | P5: =Schedules[[#This Row],[Player 2]] -> 0 | Q5: 10 | R5: =IF(Q5=15,"WIN","LOST") -> LOST | S5: =Input!D4 -> 0 | T5: =Input!E4 -> 0 | U5: Semis
A6: Open Men Singles | B6: =B5 -> Adda | C6: =D5+TIME(0,3,0) -> 46117.306 | D6: =C6+TIME(0,7,0) -> 46117.31 | E6: =E5 -> Group | F6: =F4 -> 1 | G6: =G4 -> 1 | H6: =IF(OR(S5="",T5=""),"",IFERROR(_xludf.XLOOKUP(S5,'Registrations'!#REF!,'Registrations'!#REF!,_xludf.XLOOKUP(S5,'Registrations'!$B$4:$B$211,'Registrations'!$E$4:$E$211,S5)),S5) & " vs " & IFERROR(_xludf.XLOOKUP(T5,'Registrations'!#REF!,'Registrations'!#REF!,_xludf.XLOOKUP(T5,'Registrations'!$B$4:$B$211,'Registrations'!$E$4:$E$211,T5)),T5)) -> 0 vs 0 | I6: =_xlfn.TEXTBEFORE(H6," vs ") -> 0 | J6: =_xlfn.TEXTAFTER(H6," vs ") -> 0 | K6: =Schedules[[#This Row],[Player 1]] -> 0 | L6: 15 | M6: =IF(L6=15,"WIN","LOST") -> WIN | P6: =Schedules[[#This Row],[Player 2]] -> 0 | Q6: 10 | R6: =IF(Q6=15,"WIN","LOST") -> LOST | S6: =Input!B3 -> Sanjay Gatti | T6: =Input!D3 -> 0 | U6: Finals
A7: Open Men Singles | B7: =B6 -> Adda | C7: =C6 -> 46117.306 | D7: =D6 -> 46117.31 | E7: =E6 -> Group | F7: =F5 -> 2 | G7: =G5 -> 2 | H7: =IF(OR(S7="",T7=""),"",IFERROR(_xludf.XLOOKUP(S7,'Registrations'!#REF!,'Registrations'!#REF!,_xludf.XLOOKUP(S7,'Registrations'!$B$4:$B$211,'Registrations'!$E$4:$E$211,S7)),S7) & " vs " & IFERROR(_xludf.XLOOKUP(T7,'Registrations'!#REF!,'Registrations'!#REF!,_xludf.XLOOKUP(T7,'Registrations'!$B$4:$B$211,'Registrations'!$E$4:$E$211,T7)),T7)) -> 0 vs 0 | I7: =_xlfn.TEXTBEFORE(H7," vs ") -> 0 | J7: =_xlfn.TEXTAFTER(H7," vs ") -> 0 | K7: =Schedules[[#This Row],[Player 1]] -> 0 | L7: 15 | M7: =IF(L7=15,"WIN","LOST") -> WIN | P7: =Schedules[[#This Row],[Player 2]] -> 0 | Q7: 10 | R7: =IF(Q7=15,"WIN","LOST") -> LOST | S7: =Input!B4 -> 0 | T7: =Input!D4 -> 0 | U7: Warm-up
A8: Open Men Singles | B8: =B7 -> Adda | C8: =D7+TIME(0,3,0) -> 46117.312 | D8: =C8+TIME(0,7,0) -> 46117.317 | E8: =E7 -> Group | F8: =F6 -> 1 | G8: =G6 -> 1 | H8: =IF(OR(S8="",T8=""),"",IFERROR(_xludf.XLOOKUP(S8,'Registrations'!#REF!,'Registrations'!#REF!,_xludf.XLOOKUP(S8,'Registrations'!$B$4:$B$211,'Registrations'!$E$4:$E$211,S8)),S8) & " vs " & IFERROR(_xludf.XLOOKUP(T8,'Registrations'!#REF!,'Registrations'!#REF!,_xludf.XLOOKUP(T8,'Registrations'!$B$4:$B$211,'Registrations'!$E$4:$E$211,T8)),T8)) -> 0 vs 0 | I8: =_xlfn.TEXTBEFORE(H8," vs ") -> 0 | J8: =_xlfn.TEXTAFTER(H8," vs ") -> 0 | K8: =Schedules[[#This Row],[Player 1]] -> 0 | L8: 15 | M8: =IF(L8=15,"WIN","LOST") -> WIN | P8: =Schedules[[#This Row],[Player 2]] -> 0 | Q8: 10 | R8: =IF(Q8=15,"WIN","LOST") -> LOST | S8: =Input!C3 -> 0 | T8: =Input!E3 -> 0
A9: Open Men Singles | B9: =B8 -> Adda | C9: =C8 -> 46117.312 | D9: =D8 -> 46117.317 | E9: =E8 -> Group | F9: =F7 -> 2 | G9: =G7 -> 2 | H9: =IF(OR(S9="",T9=""),"",IFERROR(_xludf.XLOOKUP(S9,'Registrations'!#REF!,'Registrations'!#REF!,_xludf.XLOOKUP(S9,'Registrations'!$B$4:$B$211,'Registrations'!$E$4:$E$211,S9)),S9) & " vs " & IFERROR(_xludf.XLOOKUP(T9,'Registrations'!#REF!,'Registrations'!#REF!,_xludf.XLOOKUP(T9,'Registrations'!$B$4:$B$211,'Registrations'!$E$4:$E$211,T9)),T9)) -> 0 vs 0 | I9: =_xlfn.TEXTBEFORE(H9," vs ") -> 0 | J9: =_xlfn.TEXTAFTER(H9," vs ") -> 0 | K9: =Schedules[[#This Row],[Player 1]] -> 0 | L9: 15 | M9: =IF(L9=15,"WIN","LOST") -> WIN | P9: =Schedules[[#This Row],[Player 2]] -> 0 | Q9: 10 | R9: =IF(Q9=15,"WIN","LOST") -> LOST | S9: =Input!C4 -> 0 | T9: =Input!E4 -> 0
A10: Open Men Singles | B10: =B9 -> Adda | C10: =D9+TIME(0,3,0) -> 46117.319 | D10: =C10+TIME(0,7,0) -> 46117.324 | E10: =E9 -> Group | F10: =F8 -> 1 | G10: =G8 -> 1 | H10: =IF(OR(S10="",T10=""),"",IFERROR(_xludf.XLOOKUP(S10,'Registrations'!#REF!,'Registrations'!#REF!,_xludf.XLOOKUP(S10,'Registrations'!$B$4:$B$211,'Registrations'!$E$4:$E$211,S10)),S10) & " vs " & IFERROR(_xludf.XLOOKUP(T10,'Registrations'!#REF!,'Registrations'!#REF!,_xludf.XLOOKUP(T10,'Registrations'!$B$4:$B$211,'Registrations'!$E$4:$E$211,T10)),T10)) -> Sanjay Gatti vs 0 | I10: =_xlfn.TEXTBEFORE(H10," vs ") -> Sanjay Gatti | J10: =_xlfn.TEXTAFTER(H10," vs ") -> 0 | K10: =Schedules[[#This Row],[Player 1]] -> Sanjay Gatti | L10: 15 | M10: =IF(L10=15,"WIN","LOST") -> WIN | P10: =Schedules[[#This Row],[Player 2]] -> 0 | Q10: 10 | R10: =IF(Q10=15,"WIN","LOST") -> LOST | S10: =Input!B3 -> Sanjay Gatti | T10: =Input!E3 -> 0
A11: Open Men Singles | B11: =B10 -> Adda | C11: =C10 -> 46117.319 | D11: =D10 -> 46117.324 | E11: =E10 -> Group | F11: =F9 -> 2 | G11: =G9 -> 2 | H11: =IF(OR(S11="",T11=""),"",IFERROR(_xludf.XLOOKUP(S11,'Registrations'!#REF!,'Registrations'!#REF!,_xludf.XLOOKUP(S11,'Registrations'!$B$4:$B$211,'Registrations'!$E$4:$E$211,S11)),S11) & " vs " & IFERROR(_xludf.XLOOKUP(T11,'Registrations'!#REF!,'Registrations'!#REF!,_xludf.XLOOKUP(T11,'Registrations'!$B$4:$B$211,'Registrations'!$E$4:$E$211,T11)),T11)) -> 0 vs 0 | I11: =_xlfn.TEXTBEFORE(H11," vs ") -> 0 | J11: =_xlfn.TEXTAFTER(H11," vs ") -> 0 | K11: =Schedules[[#This Row],[Player 1]] -> 0 | L11: 15 | M11: =IF(L11=15,"WIN","LOST") -> WIN | P11: =Schedules[[#This Row],[Player 2]] -> 0 | Q11: 10 | R11: =IF(Q11=15,"WIN","LOST") -> LOST | S11: =Input!B4 -> 0 | T11: =Input!E4 -> 0
A12: Open Men Singles | B12: =B11 -> Adda | C12: =D11+TIME(0,3,0) -> 46117.326 | D12: =C12+TIME(0,7,0) -> 46117.331 | E12: =E11 -> Group | F12: =F10 -> 1 | G12: =G10 -> 1 | H12: =IF(OR(S12="",T12=""),"",IFERROR(_xludf.XLOOKUP(S12,'Registrations'!#REF!,'Registrations'!#REF!,_xludf.XLOOKUP(S12,'Registrations'!$B$4:$B$211,'Registrations'!$E$4:$E$211,S12)),S12) & " vs " & IFERROR(_xludf.XLOOKUP(T12,'Registrations'!#REF!,'Registrations'!#REF!,_xludf.XLOOKUP(T12,'Registrations'!$B$4:$B$211,'Registrations'!$E$4:$E$211,T12)),T12)) -> 0 vs 0 | I12: =_xlfn.TEXTBEFORE(H12," vs ") -> 0 | J12: =_xlfn.TEXTAFTER(H12," vs ") -> 0 | K12: =Schedules[[#This Row],[Player 1]] -> 0 | L12: 15 | M12: =IF(L12=15,"WIN","LOST") -> WIN | P12: =Schedules[[#This Row],[Player 2]] -> 0 | Q12: 10 | R12: =IF(Q12=15,"WIN","LOST") -> LOST | S12: =Input!C3 -> 0 | T12: =Input!D3 -> 0
A13: Open Men Singles | B13: =B12 -> Adda | C13: =C12 -> 46117.326 | D13: =D12 -> 46117.331 | E13: =E12 -> Group | F13: =F11 -> 2 | G13: =G11 -> 2 | H13: =IF(OR(S13="",T13=""),"",IFERROR(_xludf.XLOOKUP(S13,'Registrations'!#REF!,'Registrations'!#REF!,_xludf.XLOOKUP(S13,'Registrations'!$B$4:$B$211,'Registrations'!$E$4:$E$211,S13)),S13) & " vs " & IFERROR(_xludf.XLOOKUP(T13,'Registrations'!#REF!,'Registrations'!#REF!,_xludf.XLOOKUP(T13,'Registrations'!$B$4:$B$211,'Registrations'!$E$4:$E$211,T13)),T13)) -> 0 vs 0 | I13: =_xlfn.TEXTBEFORE(H13," vs ") -> 0 | J13: =_xlfn.TEXTAFTER(H13," vs ") -> 0 | K13: =Schedules[[#This Row],[Player 1]] -> 0 | L13: 15 | M13: =IF(L13=15,"WIN","LOST") -> WIN | P13: =Schedules[[#This Row],[Player 2]] -> 0 | Q13: 10 | R13: =IF(Q13=15,"WIN","LOST") -> LOST | S13: =Input!C4 -> 0 | T13: =Input!D4 -> 0
A14: Open Men Singles | B14: =B13 -> Adda | C14: =D13+TIME(0,3,0) -> 46117.333 | D14: =C14+TIME(0,7,0) -> 46117.338 | E14: Pre-Q | F14: =F12 -> 1 | G14: 1 vs 2 | H14: =IF(OR(S14="",T14=""),"",IFERROR(_xludf.XLOOKUP(S14,'Registrations'!#REF!,'Registrations'!#REF!,_xludf.XLOOKUP(S14,'Registrations'!$B$4:$B$211,'Registrations'!$E$4:$E$211,S14)),S14) & " vs " & IFERROR(_xludf.XLOOKUP(T14,'Registrations'!#REF!,'Registrations'!#REF!,_xludf.XLOOKUP(T14,'Registrations'!$B$4:$B$211,'Registrations'!$E$4:$E$211,T14)),T14)) -> Sanjay Gatti vs 0 | I14: =_xlfn.TEXTBEFORE(H14," vs ") -> Sanjay Gatti | J14: =_xlfn.TEXTAFTER(H14," vs ") -> 0 | K14: =Schedules[[#This Row],[Player 1]] -> Sanjay Gatti | L14: 15 | M14: =IF(L14=15,"WIN","LOST") -> WIN | P14: =Schedules[[#This Row],[Player 2]] -> 0 | Q14: 10 | R14: =IF(Q14=15,"WIN","LOST") -> LOST | S14: =Input!H3 -> Sanjay Gatti | T14: =Input!I3 -> 0
A15: Open Men Singles | B15: =B14 -> Adda | C15: =C14 -> 46117.333 | D15: =D14 -> 46117.338 | E15: =E14 -> Pre-Q | F15: =F13 -> 2 | G15: 1 vs 2 | H15: =IF(OR(S15="",T15=""),"",IFERROR(_xludf.XLOOKUP(S15,'Registrations'!#REF!,'Registrations'!#REF!,_xludf.XLOOKUP(S15,'Registrations'!$B$4:$B$211,'Registrations'!$E$4:$E$211,S15)),S15) & " vs " & IFERROR(_xludf.XLOOKUP(T15,'Registrations'!#REF!,'Registrations'!#REF!,_xludf.XLOOKUP(T15,'Registrations'!$B$4:$B$211,'Registrations'!$E$4:$E$211,T15)),T15)) -> 0 vs 0 | I15: =_xlfn.TEXTBEFORE(H15," vs ") -> 0 | J15: =_xlfn.TEXTAFTER(H15," vs ") -> 0 | K15: =Schedules[[#This Row],[Player 1]] -> 0 | L15: 15 | M15: =IF(L15=15,"WIN","LOST") -> WIN | P15: =Schedules[[#This Row],[Player 2]] -> 0 | Q15: 10 | R15: =IF(Q15=15,"WIN","LOST") -> LOST | S15: =Input!H4 -> 0 | T15: =Input!I4 -> 0
A16: Open Men Singles | B16: =B15 -> Adda | C16: =D15+TIME(0,3,0) -> 46117.34 | D16: =C16+TIME(0,7,0) -> 46117.345 | E16: Group | F16: =F14 -> 1 | G16: 3 | H16: =IF(OR(S16="",T16=""),"",IFERROR(_xludf.XLOOKUP(S16,'Registrations'!#REF!,'Registrations'!#REF!,_xludf.XLOOKUP(S16,'Registrations'!$B$4:$B$211,'Registrations'!$E$4:$E$211,S16)),S16) & " vs " & IFERROR(_xludf.XLOOKUP(T16,'Registrations'!#REF!,'Registrations'!#REF!,_xludf.XLOOKUP(T16,'Registrations'!$B$4:$B$211,'Registrations'!$E$4:$E$211,T16)),T16)) -> 0 vs 0 | I16: =_xlfn.TEXTBEFORE(H16," vs ") -> 0 | J16: =_xlfn.TEXTAFTER(H16," vs ") -> 0 | K16: =Schedules[[#This Row],[Player 1]] -> 0 | L16: 15 | M16: =IF(L16=15,"WIN","LOST") -> WIN | P16: =Schedules[[#This Row],[Player 2]] -> 0 | Q16: 10 | R16: =IF(Q16=15,"WIN","LOST") -> LOST | S16: =Input!B5 -> 0 | T16: =Input!C5 -> 0
A17: Open Men Singles | B17: =B16 -> Adda | C17: =C16 -> 46117.34 | D17: =D16 -> 46117.345 | E17: =E16 -> Group | F17: =F15 -> 2 | G17: 4 | H17: =IF(OR(S17="",T17=""),"",IFERROR(_xludf.XLOOKUP(S17,'Registrations'!#REF!,'Registrations'!#REF!,_xludf.XLOOKUP(S17,'Registrations'!$B$4:$B$211,'Registrations'!$E$4:$E$211,S17)),S17) & " vs " & IFERROR(_xludf.XLOOKUP(T17,'Registrations'!#REF!,'Registrations'!#REF!,_xludf.XLOOKUP(T17,'Registrations'!$B$4:$B$211,'Registrations'!$E$4:$E$211,T17)),T17)) -> 0 vs 0 | I17: =_xlfn.TEXTBEFORE(H17," vs ") -> 0 | J17: =_xlfn.TEXTAFTER(H17," vs ") -> 0 | K17: =Schedules[[#This Row],[Player 1]] -> 0 | L17: 15 | M17: =IF(L17=15,"WIN","LOST") -> WIN | P17: =Schedules[[#This Row],[Player 2]] -> 0 | Q17: 10 | R17: =IF(Q17=15,"WIN","LOST") -> LOST | S17: =Input!B6 -> 0 | T17: =Input!C6 -> 0
A18: Open Men Singles | B18: =B17 -> Adda | C18: =D17+TIME(0,3,0) -> 46117.347 | D18: =C18+TIME(0,7,0) -> 46117.352 | E18: =E17 -> Group | F18: =F16 -> 1 | G18: =G16 -> 3 | H18: =IF(OR(S18="",T18=""),"",IFERROR(_xludf.XLOOKUP(S18,'Registrations'!#REF!,'Registrations'!#REF!,_xludf.XLOOKUP(S18,'Registrations'!$B$4:$B$211,'Registrations'!$E$4:$E$211,S18)),S18) & " vs " & IFERROR(_xludf.XLOOKUP(T18,'Registrations'!#REF!,'Registrations'!#REF!,_xludf.XLOOKUP(T18,'Registrations'!$B$4:$B$211,'Registrations'!$E$4:$E$211,T18)),T18)) -> 0 vs 0 | I18: =_xlfn.TEXTBEFORE(H18," vs ") -> 0 | J18: =_xlfn.TEXTAFTER(H18," vs ") -> 0 | K18: =Schedules[[#This Row],[Player 1]] -> 0 | L18: 15 | M18: =IF(L18=15,"WIN","LOST") -> WIN | P18: =Schedules[[#This Row],[Player 2]] -> 0 | Q18: 10 | R18: =IF(Q18=15,"WIN","LOST") -> LOST | S18: =Input!D5 -> 0 | T18: =Input!E5 -> 0
A19: Open Men Singles | B19: =B18 -> Adda | C19: =C18 -> 46117.347 | D19: =D18 -> 46117.352 | E19: =E18 -> Group | F19: =F17 -> 2 | G19: =G17 -> 4 | H19: =IF(OR(S19="",T19=""),"",IFERROR(_xludf.XLOOKUP(S19,'Registrations'!#REF!,'Registrations'!#REF!,_xludf.XLOOKUP(S19,'Registrations'!$B$4:$B$211,'Registrations'!$E$4:$E$211,S19)),S19) & " vs " & IFERROR(_xludf.XLOOKUP(T19,'Registrations'!#REF!,'Registrations'!#REF!,_xludf.XLOOKUP(T19,'Registrations'!$B$4:$B$211,'Registrations'!$E$4:$E$211,T19)),T19)) -> 0 vs 0 | I19: =_xlfn.TEXTBEFORE(H19," vs ") -> 0 | J19: =_xlfn.TEXTAFTER(H19," vs ") -> 0 | K19: =Schedules[[#This Row],[Player 1]] -> 0 | L19: 15 | M19: =IF(L19=15,"WIN","LOST") -> WIN | P19: =Schedules[[#This Row],[Player 2]] -> 0 | Q19: 10 | R19: =IF(Q19=15,"WIN","LOST") -> LOST | S19: =Input!D6 -> 0 | T19: =Input!E6 -> 0
A20: Open Men Singles | B20: =B19 -> Adda | C20: =D19+TIME(0,3,0) -> 46117.354 | D20: =C20+TIME(0,7,0) -> 46117.359 | E20: =E19 -> Group | F20: =F18 -> 1 | G20: =G18 -> 3 | H20: =IF(OR(S20="",T20=""),"",IFERROR(_xludf.XLOOKUP(S20,'Registrations'!#REF!,'Registrations'!#REF!,_xludf.XLOOKUP(S20,'Registrations'!$B$4:$B$211,'Registrations'!$E$4:$E$211,S20)),S20) & " vs " & IFERROR(_xludf.XLOOKUP(T20,'Registrations'!#REF!,'Registrations'!#REF!,_xludf.XLOOKUP(T20,'Registrations'!$B$4:$B$211,'Registrations'!$E$4:$E$211,T20)),T20)) -> 0 vs 0 | I20: =_xlfn.TEXTBEFORE(H20," vs ") -> 0 | J20: =_xlfn.TEXTAFTER(H20," vs ") -> 0 | K20: =Schedules[[#This Row],[Player 1]] -> 0 | L20: 15 | M20: =IF(L20=15,"WIN","LOST") -> WIN | P20: =Schedules[[#This Row],[Player 2]] -> 0 | Q20: 10 | R20: =IF(Q20=15,"WIN","LOST") -> LOST | S20: =Input!B5 -> 0 | T20: =Input!D5 -> 0
A21: Open Men Singles | B21: =B20 -> Adda | C21: =C20 -> 46117.354 | D21: =D20 -> 46117.359 | E21: Group | F21: =F19 -> 2 | G21: =G19 -> 4 | H21: =IF(OR(S21="",T21=""),"",IFERROR(_xludf.XLOOKUP(S21,'Registrations'!#REF!,'Registrations'!#REF!,_xludf.XLOOKUP(S21,'Registrations'!$B$4:$B$211,'Registrations'!$E$4:$E$211,S21)),S21) & " vs " & IFERROR(_xludf.XLOOKUP(T21,'Registrations'!#REF!,'Registrations'!#REF!,_xludf.XLOOKUP(T21,'Registrations'!$B$4:$B$211,'Registrations'!$E$4:$E$211,T21)),T21)) -> 0 vs 0 | I21: =_xlfn.TEXTBEFORE(H21," vs ") -> 0 | J21: =_xlfn.TEXTAFTER(H21," vs ") -> 0 | K21: =Schedules[[#This Row],[Player 1]] -> 0 | L21: 15 | M21: =IF(L21=15,"WIN","LOST") -> WIN | P21: =Schedules[[#This Row],[Player 2]] -> 0 | Q21: 10 | R21: =IF(Q21=15,"WIN","LOST") -> LOST | S21: =Input!B6 -> 0 | T21: =Input!D6 -> 0
A22: Open Men Singles | B22: =B21 -> Adda | C22: =D21+TIME(0,3,0) -> 46117.361 | D22: =C22+TIME(0,7,0) -> 46117.366 | E22: =E21 -> Group | F22: =F20 -> 1 | G22: =G20 -> 3 | H22: =IF(OR(S22="",T22=""),"",IFERROR(_xludf.XLOOKUP(S22,'Registrations'!#REF!,'Registrations'!#REF!,_xludf.XLOOKUP(S22,'Registrations'!$B$4:$B$211,'Registrations'!$E$4:$E$211,S22)),S22) & " vs " & IFERROR(_xludf.XLOOKUP(T22,'Registrations'!#REF!,'Registrations'!#REF!,_xludf.XLOOKUP(T22,'Registrations'!$B$4:$B$211,'Registrations'!$E$4:$E$211,T22)),T22)) -> 0 vs 0 | I22: =_xlfn.TEXTBEFORE(H22," vs ") -> 0 | J22: =_xlfn.TEXTAFTER(H22," vs ") -> 0 | K22: =Schedules[[#This Row],[Player 1]] -> 0 | L22: 15 | M22: =IF(L22=15,"WIN","LOST") -> WIN | P22: =Schedules[[#This Row],[Player 2]] -> 0 | Q22: 10 | R22: =IF(Q22=15,"WIN","LOST") -> LOST | S22: =Input!C5 -> 0 | T22: =Input!E5 -> 0
A23: Open Men Singles | B23: =B22 -> Adda | C23: =C22 -> 46117.361 | D23: =D22 -> 46117.366 | E23: =E22 -> Group | F23: =F21 -> 2 | G23: =G21 -> 4 | H23: =IF(OR(S23="",T23=""),"",IFERROR(_xludf.XLOOKUP(S23,'Registrations'!#REF!,'Registrations'!#REF!,_xludf.XLOOKUP(S23,'Registrations'!$B$4:$B$211,'Registrations'!$E$4:$E$211,S23)),S23) & " vs " & IFERROR(_xludf.XLOOKUP(T23,'Registrations'!#REF!,'Registrations'!#REF!,_xludf.XLOOKUP(T23,'Registrations'!$B$4:$B$211,'Registrations'!$E$4:$E$211,T23)),T23)) -> 0 vs 0 | I23: =_xlfn.TEXTBEFORE(H23," vs ") -> 0 | J23: =_xlfn.TEXTAFTER(H23," vs ") -> 0 | K23: =Schedules[[#This Row],[Player 1]] -> 0 | L23: 15 | M23: =IF(L23=15,"WIN","LOST") -> WIN | P23: =Schedules[[#This Row],[Player 2]] -> 0 | Q23: 10 | R23: =IF(Q23=15,"WIN","LOST") -> LOST | S23: =Input!C6 -> 0 | T23: =Input!E6 -> 0
A24: Open Men Singles | B24: =B23 -> Adda | C24: =D23+TIME(0,3,0) -> 46117.368 | D24: =C24+TIME(0,7,0) -> 46117.373 | E24: Group | F24: =F22 -> 1 | G24: =G22 -> 3 | H24: =IF(OR(S24="",T24=""),"",IFERROR(_xludf.XLOOKUP(S24,'Registrations'!#REF!,'Registrations'!#REF!,_xludf.XLOOKUP(S24,'Registrations'!$B$4:$B$211,'Registrations'!$E$4:$E$211,S24)),S24) & " vs " & IFERROR(_xludf.XLOOKUP(T24,'Registrations'!#REF!,'Registrations'!#REF!,_xludf.XLOOKUP(T24,'Registrations'!$B$4:$B$211,'Registrations'!$E$4:$E$211,T24)),T24)) -> 0 vs 0 | I24: =_xlfn.TEXTBEFORE(H24," vs ") -> 0 | J24: =_xlfn.TEXTAFTER(H24," vs ") -> 0 | K24: =Schedules[[#This Row],[Player 1]] -> 0 | L24: 15 | M24: =IF(L24=15,"WIN","LOST") -> WIN | P24: =Schedules[[#This Row],[Player 2]] -> 0 | Q24: 10 | R24: =IF(Q24=15,"WIN","LOST") -> LOST | S24: =Input!B5 -> 0 | T24: =Input!E5 -> 0
A25: Open Men Singles | B25: =B24 -> Adda | C25: =C24 -> 46117.368 | D25: =D24 -> 46117.373 | E25: =E24 -> Group | F25: =F23 -> 2 | G25: =G23 -> 4 | H25: =IF(OR(S25="",T25=""),"",IFERROR(_xludf.XLOOKUP(S25,'Registrations'!#REF!,'Registrations'!#REF!,_xludf.XLOOKUP(S25,'Registrations'!$B$4:$B$211,'Registrations'!$E$4:$E$211,S25)),S25) & " vs " & IFERROR(_xludf.XLOOKUP(T25,'Registrations'!#REF!,'Registrations'!#REF!,_xludf.XLOOKUP(T25,'Registrations'!$B$4:$B$211,'Registrations'!$E$4:$E$211,T25)),T25)) -> 0 vs 0 | I25: =_xlfn.TEXTBEFORE(H25," vs ") -> 0 | J25: =_xlfn.TEXTAFTER(H25," vs ") -> 0 | K25: =Schedules[[#This Row],[Player 1]] -> 0 | L25: 15 | M25: =IF(L25=15,"WIN","LOST") -> WIN | P25: =Schedules[[#This Row],[Player 2]] -> 0 | Q25: 10 | R25: =IF(Q25=15,"WIN","LOST") -> LOST | S25: =Input!B6 -> 0 | T25: =Input!E6 -> 0
A26: Open Men Singles | B26: =B25 -> Adda | C26: =D25+TIME(0,3,0) -> 46117.375 | D26: =C26+TIME(0,7,0) -> 46117.38 | E26: =E25 -> Group | F26: =F24 -> 1 | G26: =G24 -> 3 | H26: =IF(OR(S26="",T26=""),"",IFERROR(_xludf.XLOOKUP(S26,'Registrations'!#REF!,'Registrations'!#REF!,_xludf.XLOOKUP(S26,'Registrations'!$B$4:$B$211,'Registrations'!$E$4:$E$211,S26)),S26) & " vs " & IFERROR(_xludf.XLOOKUP(T26,'Registrations'!#REF!,'Registrations'!#REF!,_xludf.XLOOKUP(T26,'Registrations'!$B$4:$B$211,'Registrations'!$E$4:$E$211,T26)),T26)) -> 0 vs 0 | I26: =_xlfn.TEXTBEFORE(H26," vs ") -> 0 | J26: =_xlfn.TEXTAFTER(H26," vs ") -> 0 | K26: =Schedules[[#This Row],[Player 1]] -> 0 | L26: 15 | M26: =IF(L26=15,"WIN","LOST") -> WIN | P26: =Schedules[[#This Row],[Player 2]] -> 0 | Q26: 10 | R26: =IF(Q26=15,"WIN","LOST") -> LOST | S26: =Input!C5 -> 0 | T26: =Input!D5 -> 0
A27: Open Men Singles | B27: =B26 -> Adda | C27: =C26 -> 46117.375 | D27: =D26 -> 46117.38 | E27: =E26 -> Group | F27: =F25 -> 2 | G27: =G25 -> 4 | H27: =IF(OR(S27="",T27=""),"",IFERROR(_xludf.XLOOKUP(S27,'Registrations'!#REF!,'Registrations'!#REF!,_xludf.XLOOKUP(S27,'Registrations'!$B$4:$B$211,'Registrations'!$E$4:$E$211,S27)),S27) & " vs " & IFERROR(_xludf.XLOOKUP(T27,'Registrations'!#REF!,'Registrations'!#REF!,_xludf.XLOOKUP(T27,'Registrations'!$B$4:$B$211,'Registrations'!$E$4:$E$211,T27)),T27)) -> 0 vs 0 | I27: =_xlfn.TEXTBEFORE(H27," vs ") -> 0 | J27: =_xlfn.TEXTAFTER(H27," vs ") -> 0 | K27: =Schedules[[#This Row],[Player 1]] -> 0 | L27: 15 | M27: =IF(L27=15,"WIN","LOST") -> WIN | P27: =Schedules[[#This Row],[Player 2]] -> 0 | Q27: 10 | R27: =IF(Q27=15,"WIN","LOST") -> LOST | S27: =Input!C6 -> 0 | T27: =Input!D6 -> 0
A28: Open Men Singles | B28: =B27 -> Adda | C28: =D27+TIME(0,3,0) -> 46117.382 | D28: =C28+TIME(0,7,0) -> 46117.387 | E28: Pre-Q | F28: =F26 -> 1 | G28: 3 vs 4 | H28: =IF(OR(S28="",T28=""),"",IFERROR(_xludf.XLOOKUP(S28,'Registrations'!#REF!,'Registrations'!#REF!,_xludf.XLOOKUP(S28,'Registrations'!$B$4:$B$211,'Registrations'!$E$4:$E$211,S28)),S28) & " vs " & IFERROR(_xludf.XLOOKUP(T28,'Registrations'!#REF!,'Registrations'!#REF!,_xludf.XLOOKUP(T28,'Registrations'!$B$4:$B$211,'Registrations'!$E$4:$E$211,T28)),T28)) -> 0 vs 0 | I28: =_xlfn.TEXTBEFORE(H28," vs ") -> 0 | J28: =_xlfn.TEXTAFTER(H28," vs ") -> 0 | K28: =Schedules[[#This Row],[Player 1]] -> 0 | L28: 15 | M28: =IF(L28=15,"WIN","LOST") -> WIN | P28: =Schedules[[#This Row],[Player 2]] -> 0 | Q28: 10 | R28: =IF(Q28=15,"WIN","LOST") -> LOST | S28: =Input!H5 -> 0 | T28: =Input!I5 -> 0
A29: Open Men Singles | B29: =B28 -> Adda | C29: =C28 -> 46117.382 | D29: =D28 -> 46117.387 | E29: =E28 -> Pre-Q | F29: =F27 -> 2 | G29: 3 vs 4 | H29: =IF(OR(S29="",T29=""),"",IFERROR(_xludf.XLOOKUP(S29,'Registrations'!#REF!,'Registrations'!#REF!,_xludf.XLOOKUP(S29,'Registrations'!$B$4:$B$211,'Registrations'!$E$4:$E$211,S29)),S29) & " vs " & IFERROR(_xludf.XLOOKUP(T29,'Registrations'!#REF!,'Registrations'!#REF!,_xludf.XLOOKUP(T29,'Registrations'!$B$4:$B$211,'Registrations'!$E$4:$E$211,T29)),T29)) -> 0 vs 0 | I29: =_xlfn.TEXTBEFORE(H29," vs ") -> 0 | J29: =_xlfn.TEXTAFTER(H29," vs ") -> 0 | K29: =Schedules[[#This Row],[Player 1]] -> 0 | L29: 15 | M29: =IF(L29=15,"WIN","LOST") -> WIN | P29: =Schedules[[#This Row],[Player 2]] -> 0 | Q29: 10 | R29: =IF(Q29=15,"WIN","LOST") -> LOST | S29: =Input!H6 -> 0 | T29: =Input!I6 -> 0
A30: Open Men Singles | B30: =B29 -> Adda | C30: =D29+TIME(0,3,0) -> 46117.389 | D30: =C30+TIME(0,7,0) -> 46117.394 | E30: Group | F30: =F28 -> 1 | G30: 5 | H30: =IF(OR(S30="",T30=""),"",IFERROR(_xludf.XLOOKUP(S30,'Registrations'!#REF!,'Registrations'!#REF!,_xludf.XLOOKUP(S30,'Registrations'!$B$4:$B$211,'Registrations'!$E$4:$E$211,S30)),S30) & " vs " & IFERROR(_xludf.XLOOKUP(T30,'Registrations'!#REF!,'Registrations'!#REF!,_xludf.XLOOKUP(T30,'Registrations'!$B$4:$B$211,'Registrations'!$E$4:$E$211,T30)),T30)) -> 0 vs 0 | I30: =_xlfn.TEXTBEFORE(H30," vs ") -> 0 | J30: =_xlfn.TEXTAFTER(H30," vs ") -> 0 | K30: =Schedules[[#This Row],[Player 1]] -> 0 | L30: 15 | M30: =IF(L30=15,"WIN","LOST") -> WIN | P30: =Schedules[[#This Row],[Player 2]] -> 0 | Q30: 10 | R30: =IF(Q30=15,"WIN","LOST") -> LOST | S30: =Input!B7 -> 0 | T30: =Input!C7 -> 0
A31: Open Men Singles | B31: =B30 -> Adda | C31: =C30 -> 46117.389 | D31: =D30 -> 46117.394 | E31: =E30 -> Group | F31: =F29 -> 2 | G31: 6 | H31: =IF(OR(S31="",T31=""),"",IFERROR(_xludf.XLOOKUP(S31,'Registrations'!#REF!,'Registrations'!#REF!,_xludf.XLOOKUP(S31,'Registrations'!$B$4:$B$211,'Registrations'!$E$4:$E$211,S31)),S31) & " vs " & IFERROR(_xludf.XLOOKUP(T31,'Registrations'!#REF!,'Registrations'!#REF!,_xludf.XLOOKUP(T31,'Registrations'!$B$4:$B$211,'Registrations'!$E$4:$E$211,T31)),T31)) -> 0 vs 0 | I31: =_xlfn.TEXTBEFORE(H31," vs ") -> 0 | J31: =_xlfn.TEXTAFTER(H31," vs ") -> 0 | K31: =Schedules[[#This Row],[Player 1]] -> 0 | L31: 15 | M31: =IF(L31=15,"WIN","LOST") -> WIN | P31: =Schedules[[#This Row],[Player 2]] -> 0 | Q31: 10 | R31: =IF(Q31=15,"WIN","LOST") -> LOST | S31: =Input!B8 -> 0 | T31: =Input!C8 -> 0
A32: Open Men Singles | B32: =B31 -> Adda | C32: =D31+TIME(0,3,0) -> 46117.396 | D32: =C32+TIME(0,7,0) -> 46117.401 | E32: =E31 -> Group | F32: =F30 -> 1 | G32: =G30 -> 5 | H32: =IF(OR(S32="",T32=""),"",IFERROR(_xludf.XLOOKUP(S32,'Registrations'!#REF!,'Registrations'!#REF!,_xludf.XLOOKUP(S32,'Registrations'!$B$4:$B$211,'Registrations'!$E$4:$E$211,S32)),S32) & " vs " & IFERROR(_xludf.XLOOKUP(T32,'Registrations'!#REF!,'Registrations'!#REF!,_xludf.XLOOKUP(T32,'Registrations'!$B$4:$B$211,'Registrations'!$E$4:$E$211,T32)),T32)) -> 0 vs 0 | I32: =_xlfn.TEXTBEFORE(H32," vs ") -> 0 | J32: =_xlfn.TEXTAFTER(H32," vs ") -> 0 | K32: =Schedules[[#This Row],[Player 1]] -> 0 | L32: 15 | M32: =IF(L32=15,"WIN","LOST") -> WIN | P32: =Schedules[[#This Row],[Player 2]] -> 0 | Q32: 10 | R32: =IF(Q32=15,"WIN","LOST") -> LOST | S32: =Input!D7 -> 0 | T32: =Input!E7 -> 0
A33: Open Men Singles | B33: =B32 -> Adda | C33: =C32 -> 46117.396 | D33: =D32 -> 46117.401 | E33: =E32 -> Group | F33: =F31 -> 2 | G33: =G31 -> 6 | H33: =IF(OR(S33="",T33=""),"",IFERROR(_xludf.XLOOKUP(S33,'Registrations'!#REF!,'Registrations'!#REF!,_xludf.XLOOKUP(S33,'Registrations'!$B$4:$B$211,'Registrations'!$E$4:$E$211,S33)),S33) & " vs " & IFERROR(_xludf.XLOOKUP(T33,'Registrations'!#REF!,'Registrations'!#REF!,_xludf.XLOOKUP(T33,'Registrations'!$B$4:$B$211,'Registrations'!$E$4:$E$211,T33)),T33)) -> 0 vs 0 | I33: =_xlfn.TEXTBEFORE(H33," vs ") -> 0 | J33: =_xlfn.TEXTAFTER(H33," vs ") -> 0 | K33: =Schedules[[#This Row],[Player 1]] -> 0 | L33: 15 | M33: =IF(L33=15,"WIN","LOST") -> WIN | P33: =Schedules[[#This Row],[Player 2]] -> 0 | Q33: 10 | R33: =IF(Q33=15,"WIN","LOST") -> LOST | S33: =Input!D8 -> 0 | T33: =Input!E8 -> 0
A34: Open Men Singles | B34: =B33 -> Adda | C34: =D33+TIME(0,3,0) -> 46117.403 | D34: =C34+TIME(0,7,0) -> 46117.408 | E34: =E33 -> Group | F34: =F32 -> 1 | G34: =G32 -> 5 | H34: =IF(OR(S34="",T34=""),"",IFERROR(_xludf.XLOOKUP(S34,'Registrations'!#REF!,'Registrations'!#REF!,_xludf.XLOOKUP(S34,'Registrations'!$B$4:$B$211,'Registrations'!$E$4:$E$211,S34)),S34) & " vs " & IFERROR(_xludf.XLOOKUP(T34,'Registrations'!#REF!,'Registrations'!#REF!,_xludf.XLOOKUP(T34,'Registrations'!$B$4:$B$211,'Registrations'!$E$4:$E$211,T34)),T34)) -> 0 vs 0 | I34: =_xlfn.TEXTBEFORE(H34," vs ") -> 0 | J34: =_xlfn.TEXTAFTER(H34," vs ") -> 0 | K34: =Schedules[[#This Row],[Player 1]] -> 0 | L34: 15 | M34: =IF(L34=15,"WIN","LOST") -> WIN | P34: =Schedules[[#This Row],[Player 2]] -> 0 | Q34: 10 | R34: =IF(Q34=15,"WIN","LOST") -> LOST | S34: =Input!B7 -> 0 | T34: =Input!D7 -> 0
A35: Open Men Singles | B35: =B34 -> Adda | C35: =C34 -> 46117.403 | D35: =D34 -> 46117.408 | E35: Group | F35: =F33 -> 2 | G35: =G33 -> 6 | H35: =IF(OR(S35="",T35=""),"",IFERROR(_xludf.XLOOKUP(S35,'Registrations'!#REF!,'Registrations'!#REF!,_xludf.XLOOKUP(S35,'Registrations'!$B$4:$B$211,'Registrations'!$E$4:$E$211,S35)),S35) & " vs " & IFERROR(_xludf.XLOOKUP(T35,'Registrations'!#REF!,'Registrations'!#REF!,_xludf.XLOOKUP(T35,'Registrations'!$B$4:$B$211,'Registrations'!$E$4:$E$211,T35)),T35)) -> 0 vs 0 | I35: =_xlfn.TEXTBEFORE(H35," vs ") -> 0 | J35: =_xlfn.TEXTAFTER(H35," vs ") -> 0 | K35: =Schedules[[#This Row],[Player 1]] -> 0 | L35: 15 | M35: =IF(L35=15,"WIN","LOST") -> WIN | P35: =Schedules[[#This Row],[Player 2]] -> 0 | Q35: 10 | R35: =IF(Q35=15,"WIN","LOST") -> LOST | S35: =Input!B8 -> 0 | T35: =Input!D8 -> 0
A36: Open Men Singles | B36: =B35 -> Adda | C36: =D35+TIME(0,3,0) -> 46117.41 | D36: =C36+TIME(0,7,0) -> 46117.415 | E36: Group | F36: =F34 -> 1 | G36: =G34 -> 5 | H36: =IF(OR(S36="",T36=""),"",IFERROR(_xludf.XLOOKUP(S36,'Registrations'!#REF!,'Registrations'!#REF!,_xludf.XLOOKUP(S36,'Registrations'!$B$4:$B$211,'Registrations'!$E$4:$E$211,S36)),S36) & " vs " & IFERROR(_xludf.XLOOKUP(T36,'Registrations'!#REF!,'Registrations'!#REF!,_xludf.XLOOKUP(T36,'Registrations'!$B$4:$B$211,'Registrations'!$E$4:$E$211,T36)),T36)) -> 0 vs 0 | I36: =_xlfn.TEXTBEFORE(H36," vs ") -> 0 | J36: =_xlfn.TEXTAFTER(H36," vs ") -> 0 | K36: =Schedules[[#This Row],[Player 1]] -> 0 | L36: 15 | M36: =IF(L36=15,"WIN","LOST") -> WIN | P36: =Schedules[[#This Row],[Player 2]] -> 0 | Q36: 10 | R36: =IF(Q36=15,"WIN","LOST") -> LOST | S36: =Input!C7 -> 0 | T36: =Input!E7 -> 0
A37: Open Men Singles | B37: =B36 -> Adda | C37: =C36 -> 46117.41 | D37: =D36 -> 46117.415 | E37: Group | F37: =F35 -> 2 | G37: =G35 -> 6 | H37: =IF(OR(S37="",T37=""),"",IFERROR(_xludf.XLOOKUP(S37,'Registrations'!#REF!,'Registrations'!#REF!,_xludf.XLOOKUP(S37,'Registrations'!$B$4:$B$211,'Registrations'!$E$4:$E$211,S37)),S37) & " vs " & IFERROR(_xludf.XLOOKUP(T37,'Registrations'!#REF!,'Registrations'!#REF!,_xludf.XLOOKUP(T37,'Registrations'!$B$4:$B$211,'Registrations'!$E$4:$E$211,T37)),T37)) -> 0 vs 0 | I37: =_xlfn.TEXTBEFORE(H37," vs ") -> 0 | J37: =_xlfn.TEXTAFTER(H37," vs ") -> 0 | K37: =Schedules[[#This Row],[Player 1]] -> 0 | L37: 15 | M37: =IF(L37=15,"WIN","LOST") -> WIN | P37: =Schedules[[#This Row],[Player 2]] -> 0 | Q37: 10 | R37: =IF(Q37=15,"WIN","LOST") -> LOST | S37: =Input!C8 -> 0 | T37: =Input!E8 -> 0
A38: Open Men Singles | B38: =B37 -> Adda | C38: =D37+TIME(0,3,0) -> 46117.417 | D38: =C38+TIME(0,7,0) -> 46117.422 | E38: Group | F38: =F36 -> 1 | G38: =G36 -> 5 | H38: =IF(OR(S38="",T38=""),"",IFERROR(_xludf.XLOOKUP(S38,'Registrations'!#REF!,'Registrations'!#REF!,_xludf.XLOOKUP(S38,'Registrations'!$B$4:$B$211,'Registrations'!$E$4:$E$211,S38)),S38) & " vs " & IFERROR(_xludf.XLOOKUP(T38,'Registrations'!#REF!,'Registrations'!#REF!,_xludf.XLOOKUP(T38,'Registrations'!$B$4:$B$211,'Registrations'!$E$4:$E$211,T38)),T38)) -> 0 vs 0 | I38: =_xlfn.TEXTBEFORE(H38," vs ") -> 0 | J38: =_xlfn.TEXTAFTER(H38," vs ") -> 0 | K38: =Schedules[[#This Row],[Player 1]] -> 0 | L38: 15 | M38: =IF(L38=15,"WIN","LOST") -> WIN | P38: =Schedules[[#This Row],[Player 2]] -> 0 | Q38: 10 | R38: =IF(Q38=15,"WIN","LOST") -> LOST | S38: =Input!B7 -> 0 | T38: =Input!E7 -> 0
A39: Open Men Singles | B39: =B38 -> Adda | C39: =C38 -> 46117.417 | D39: =D38 -> 46117.422 | E39: =E38 -> Group | F39: =F37 -> 2 | G39: =G37 -> 6 | H39: =IF(OR(S39="",T39=""),"",IFERROR(_xludf.XLOOKUP(S39,'Registrations'!#REF!,'Registrations'!#REF!,_xludf.XLOOKUP(S39,'Registrations'!$B$4:$B$211,'Registrations'!$E$4:$E$211,S39)),S39) & " vs " & IFERROR(_xludf.XLOOKUP(T39,'Registrations'!#REF!,'Registrations'!#REF!,_xludf.XLOOKUP(T39,'Registrations'!$B$4:$B$211,'Registrations'!$E$4:$E$211,T39)),T39)) -> 0 vs 0 | I39: =_xlfn.TEXTBEFORE(H39," vs ") -> 0 | J39: =_xlfn.TEXTAFTER(H39," vs ") -> 0 | K39: =Schedules[[#This Row],[Player 1]] -> 0 | L39: 15 | M39: =IF(L39=15,"WIN","LOST") -> WIN | P39: =Schedules[[#This Row],[Player 2]] -> 0 | Q39: 10 | R39: =IF(Q39=15,"WIN","LOST") -> LOST | S39: =Input!B8 -> 0 | T39: =Input!E8 -> 0
A40: Open Men Singles | B40: =B39 -> Adda | C40: =D39+TIME(0,3,0) -> 46117.424 | D40: =C40+TIME(0,7,0) -> 46117.428 | E40: =E39 -> Group | F40: =F38 -> 1 | G40: =G38 -> 5 | H40: =IF(OR(S40="",T40=""),"",IFERROR(_xludf.XLOOKUP(S40,'Registrations'!#REF!,'Registrations'!#REF!,_xludf.XLOOKUP(S40,'Registrations'!$B$4:$B$211,'Registrations'!$E$4:$E$211,S40)),S40) & " vs " & IFERROR(_xludf.XLOOKUP(T40,'Registrations'!#REF!,'Registrations'!#REF!,_xludf.XLOOKUP(T40,'Registrations'!$B$4:$B$211,'Registrations'!$E$4:$E$211,T40)),T40)) -> 0 vs 0 | I40: =_xlfn.TEXTBEFORE(H40," vs ") -> 0 | J40: =_xlfn.TEXTAFTER(H40," vs ") -> 0 | K40: =Schedules[[#This Row],[Player 1]] -> 0 | L40: 15 | M40: =IF(L40=15,"WIN","LOST") -> WIN | P40: =Schedules[[#This Row],[Player 2]] -> 0 | Q40: 10 | R40: =IF(Q40=15,"WIN","LOST") -> LOST | S40: =Input!C7 -> 0 | T40: =Input!D7 -> 0
A41: Open Men Singles | B41: =B40 -> Adda | C41: =C40 -> 46117.424 | D41: =D40 -> 46117.428 | E41: Group | F41: =F39 -> 2 | G41: =G39 -> 6 | H41: =IF(OR(S41="",T41=""),"",IFERROR(_xludf.XLOOKUP(S41,'Registrations'!#REF!,'Registrations'!#REF!,_xludf.XLOOKUP(S41,'Registrations'!$B$4:$B$211,'Registrations'!$E$4:$E$211,S41)),S41) & " vs " & IFERROR(_xludf.XLOOKUP(T41,'Registrations'!#REF!,'Registrations'!#REF!,_xludf.XLOOKUP(T41,'Registrations'!$B$4:$B$211,'Registrations'!$E$4:$E$211,T41)),T41)) -> 0 vs 0 | I41: =_xlfn.TEXTBEFORE(H41," vs ") -> 0 | J41: =_xlfn.TEXTAFTER(H41," vs ") -> 0 | K41: =Schedules[[#This Row],[Player 1]] -> 0 | L41: 15 | M41: =IF(L41=15,"WIN","LOST") -> WIN | P41: =Schedules[[#This Row],[Player 2]] -> 0 | Q41: 10 | R41: =IF(Q41=15,"WIN","LOST") -> LOST | S41: =Input!C8 -> 0 | T41: =Input!D8 -> 0
A42: Open Men Singles | B42: =B41 -> Adda | C42: =D41+TIME(0,3,0) -> 46117.431 | D42: =C42+TIME(0,7,0) -> 46117.435 | E42: Pre-Q | F42: =F40 -> 1 | G42: 5 vs 6 | H42: =IF(OR(S42="",T42=""),"",IFERROR(_xludf.XLOOKUP(S42,'Registrations'!#REF!,'Registrations'!#REF!,_xludf.XLOOKUP(S42,'Registrations'!$B$4:$B$211,'Registrations'!$E$4:$E$211,S42)),S42) & " vs " & IFERROR(_xludf.XLOOKUP(T42,'Registrations'!#REF!,'Registrations'!#REF!,_xludf.XLOOKUP(T42,'Registrations'!$B$4:$B$211,'Registrations'!$E$4:$E$211,T42)),T42)) -> 0 vs 0 | I42: =_xlfn.TEXTBEFORE(H42," vs ") -> 0 | J42: =_xlfn.TEXTAFTER(H42," vs ") -> 0 | K42: =Schedules[[#This Row],[Player 1]] -> 0 | L42: 15 | M42: =IF(L42=15,"WIN","LOST") -> WIN | P42: =Schedules[[#This Row],[Player 2]] -> 0 | Q42: 10 | R42: =IF(Q42=15,"WIN","LOST") -> LOST | S42: =Input!H7 -> 0 | T42: =Input!I7 -> 0
A43: Open Men Singles | B43: =B42 -> Adda | C43: =C42 -> 46117.431 | D43: =D42 -> 46117.435 | E43: =E42 -> Pre-Q | F43: =F41 -> 2 | G43: 5 vs 6 | H43: =IF(OR(S43="",T43=""),"",IFERROR(_xludf.XLOOKUP(S43,'Registrations'!#REF!,'Registrations'!#REF!,_xludf.XLOOKUP(S43,'Registrations'!$B$4:$B$211,'Registrations'!$E$4:$E$211,S43)),S43) & " vs " & IFERROR(_xludf.XLOOKUP(T43,'Registrations'!#REF!,'Registrations'!#REF!,_xludf.XLOOKUP(T43,'Registrations'!$B$4:$B$211,'Registrations'!$E$4:$E$211,T43)),T43)) -> 0 vs 0 | I43: =_xlfn.TEXTBEFORE(H43," vs ") -> 0 | J43: =_xlfn.TEXTAFTER(H43," vs ") -> 0 | K43: =Schedules[[#This Row],[Player 1]] -> 0 | L43: 15 | M43: =IF(L43=15,"WIN","LOST") -> WIN | P43: =Schedules[[#This Row],[Player 2]] -> 0 | Q43: 10 | R43: =IF(Q43=15,"WIN","LOST") -> LOST | S43: =Input!H8 -> 0 | T43: =Input!I8 -> 0
A44: Open Men Singles | B44: =B43 -> Adda | C44: =D43+TIME(0,3,0) -> 46117.438 | D44: =C44+TIME(0,7,0) -> 46117.442 | E44: Quarters | F44: =F42 -> 1 | G44: 1 vs 6 | H44: =IF(OR(S44="",T44=""),"",IFERROR(_xludf.XLOOKUP(S44,'Registrations'!#REF!,'Registrations'!#REF!,_xludf.XLOOKUP(S44,'Registrations'!$B$4:$B$211,'Registrations'!$E$4:$E$211,S44)),S44) & " vs " & IFERROR(_xludf.XLOOKUP(T44,'Registrations'!#REF!,'Registrations'!#REF!,_xludf.XLOOKUP(T44,'Registrations'!$B$4:$B$211,'Registrations'!$E$4:$E$211,T44)),T44)) -> Sanjay Gatti vs 0 | I44: =_xlfn.TEXTBEFORE(H44," vs ") -> Sanjay Gatti | J44: =_xlfn.TEXTAFTER(H44," vs ") -> 0 | K44: =Schedules[[#This Row],[Player 1]] -> Sanjay Gatti | L44: 15 | M44: =IF(L44=15,"WIN","LOST") -> WIN | P44: =Schedules[[#This Row],[Player 2]] -> 0 | Q44: 10 | R44: =IF(Q44=15,"WIN","LOST") -> LOST | S44: =Input!L3 -> Sanjay Gatti | T44: =Input!M3 -> 0
A45: Open Men Singles | B45: =B44 -> Adda | C45: =C44 -> 46117.438 | D45: =D44 -> 46117.442 | E45: =E44 -> Quarters | F45: =F43 -> 2 | G45: 2 vs 5 | H45: =IF(OR(S45="",T45=""),"",IFERROR(_xludf.XLOOKUP(S45,'Registrations'!#REF!,'Registrations'!#REF!,_xludf.XLOOKUP(S45,'Registrations'!$B$4:$B$211,'Registrations'!$E$4:$E$211,S45)),S45) & " vs " & IFERROR(_xludf.XLOOKUP(T45,'Registrations'!#REF!,'Registrations'!#REF!,_xludf.XLOOKUP(T45,'Registrations'!$B$4:$B$211,'Registrations'!$E$4:$E$211,T45)),T45)) -> 0 vs 0 | I45: =_xlfn.TEXTBEFORE(H45," vs ") -> 0 | J45: =_xlfn.TEXTAFTER(H45," vs ") -> 0 | K45: =Schedules[[#This Row],[Player 1]] -> 0 | L45: 15 | M45: =IF(L45=15,"WIN","LOST") -> WIN | P45: =Schedules[[#This Row],[Player 2]] -> 0 | Q45: 10 | R45: =IF(Q45=15,"WIN","LOST") -> LOST | S45: =Input!L4 -> 0 | T45: =Input!M4 -> 0
A46: Open Men Singles | B46: =B45 -> Adda | C46: =D45+TIME(0,3,0) -> 46117.444 | D46: =C46+TIME(0,7,0) -> 46117.449 | E46: Quarters | F46: =F44 -> 1 | G46: 3 vs 4 | H46: =IF(OR(S46="",T46=""),"",IFERROR(_xludf.XLOOKUP(S46,'Registrations'!#REF!,'Registrations'!#REF!,_xludf.XLOOKUP(S46,'Registrations'!$B$4:$B$211,'Registrations'!$E$4:$E$211,S46)),S46) & " vs " & IFERROR(_xludf.XLOOKUP(T46,'Registrations'!#REF!,'Registrations'!#REF!,_xludf.XLOOKUP(T46,'Registrations'!$B$4:$B$211,'Registrations'!$E$4:$E$211,T46)),T46)) -> 0 vs 0 | I46: =_xlfn.TEXTBEFORE(H46," vs ") -> 0 | J46: =_xlfn.TEXTAFTER(H46," vs ") -> 0 | K46: =Schedules[[#This Row],[Player 1]] -> 0 | L46: 15 | M46: =IF(L46=15,"WIN","LOST") -> WIN | P46: =Schedules[[#This Row],[Player 2]] -> 0 | Q46: 10 | R46: =IF(Q46=15,"WIN","LOST") -> LOST | S46: =Input!L5 -> 0 | T46: =Input!M5 -> 0
A47: Open Men Singles | B47: =B46 -> Adda | C47: =C46 -> 46117.444 | D47: =D46 -> 46117.449 | E47: Warm-up / Open Play | F47: =F45 -> 2 | K47: =Schedules[[#This Row],[Player 1]] -> 0 | P47: =Schedules[[#This Row],[Player 2]] -> 0
A48: Open Men Singles | B48: =B47 -> Adda | C48: =D47+TIME(0,3,0) -> 46117.451 | D48: =C48+TIME(0,7,0) -> 46117.456 | E48: Semi Finals | F48: =F46 -> 1 | G48: 1 vs 3 | H48: =IF(OR(S48="",T48=""),"",IFERROR(_xludf.XLOOKUP(S48,'Registrations'!#REF!,'Registrations'!#REF!,_xludf.XLOOKUP(S48,'Registrations'!$B$4:$B$211,'Registrations'!$E$4:$E$211,S48)),S48) & " vs " & IFERROR(_xludf.XLOOKUP(T48,'Registrations'!#REF!,'Registrations'!#REF!,_xludf.XLOOKUP(T48,'Registrations'!$B$4:$B$211,'Registrations'!$E$4:$E$211,T48)),T48)) -> Sanjay Gatti vs 0 | I48: =_xlfn.TEXTBEFORE(H48," vs ") -> Sanjay Gatti | J48: =_xlfn.TEXTAFTER(H48," vs ") -> 0 | K48: =Schedules[[#This Row],[Player 1]] -> Sanjay Gatti | L48: 15 | M48: =IF(L48=15,"WIN","LOST") -> WIN | P48: =Schedules[[#This Row],[Player 2]] -> 0 | Q48: 10 | R48: =IF(Q48=15,"WIN","LOST") -> LOST | S48: =Input!P3 -> Sanjay Gatti | T48: =Input!Q3 -> 0
A49: Open Men Singles | B49: =B48 -> Adda | C49: =C48 -> 46117.451 | D49: =D48 -> 46117.456 | E49: =E48 -> Semi Finals | F49: =F47 -> 2 | G49: 2 vs WC | H49: =IF(OR(S49="",T49=""),"",IFERROR(_xludf.XLOOKUP(S49,'Registrations'!#REF!,'Registrations'!#REF!,_xludf.XLOOKUP(S49,'Registrations'!$B$4:$B$211,'Registrations'!$E$4:$E$211,S49)),S49) & " vs " & IFERROR(_xludf.XLOOKUP(T49,'Registrations'!#REF!,'Registrations'!#REF!,_xludf.XLOOKUP(T49,'Registrations'!$B$4:$B$211,'Registrations'!$E$4:$E$211,T49)),T49)) -> 0 vs WC 01 | I49: =_xlfn.TEXTBEFORE(H49," vs ") -> 0 | J49: =_xlfn.TEXTAFTER(H49," vs ") -> WC 01 | K49: =Schedules[[#This Row],[Player 1]] -> 0 | L49: 15 | M49: =IF(L49=15,"WIN","LOST") -> WIN | P49: =Schedules[[#This Row],[Player 2]] -> WC 01 | Q49: 10 | R49: =IF(Q49=15,"WIN","LOST") -> LOST | S49: =Input!P4 -> 0 | T49: =Input!Q4 -> WC 01
A50: Open Men Singles | B50: =B49 -> Adda | C50: =D49+TIME(0,3,0) -> 46117.458 | D50: =C50+TIME(0,7,0) -> 46117.463 | E50: Finals | F50: 1 | G50: 1 vs 2 | H50: =IF(OR(S50="",T50=""),"",IFERROR(_xludf.XLOOKUP(S50,'Registrations'!#REF!,'Registrations'!#REF!,_xludf.XLOOKUP(S50,'Registrations'!$B$4:$B$211,'Registrations'!$E$4:$E$211,S50)),S50) & " vs " & IFERROR(_xludf.XLOOKUP(T50,'Registrations'!#REF!,'Registrations'!#REF!,_xludf.XLOOKUP(T50,'Registrations'!$B$4:$B$211,'Registrations'!$E$4:$E$211,T50)),T50)) -> Sanjay Gatti vs 0 | I50: =_xlfn.TEXTBEFORE(H50," vs ") -> Sanjay Gatti | J50: =_xlfn.TEXTAFTER(H50," vs ") -> 0 | K50: =Schedules[[#This Row],[Player 1]] -> Sanjay Gatti | L50: 15 | M50: =IF(L50=15,"WIN","LOST") -> WIN | P50: =Schedules[[#This Row],[Player 2]] -> 0 | Q50: 10 | R50: =IF(Q50=15,"WIN","LOST") -> LOST | S50: =Input!T3 -> Sanjay Gatti | T50: =Input!U3 -> 0
A51: Open Men Singles | B51: =B50 -> Adda | C51: =C50 -> 46117.458 | D51: =D50 -> 46117.463 | E51: Warm-up / Open Play | F51: 2 | H51: =IF(OR(S51="",T51=""),"",IFERROR(_xludf.XLOOKUP(S51,'Registrations'!#REF!,'Registrations'!#REF!,_xludf.XLOOKUP(S51,'Registrations'!$B$4:$B$211,'Registrations'!$E$4:$E$211,S51)),S51) & " vs " & IFERROR(_xludf.XLOOKUP(T51,'Registrations'!#REF!,'Registrations'!#REF!,_xludf.XLOOKUP(T51,'Registrations'!$B$4:$B$211,'Registrations'!$E$4:$E$211,T51)),T51)) | K51: =Schedules[[#This Row],[Player 1]] -> 0 | P51: =Schedules[[#This Row],[Player 2]] -> 0
A52: Intermediate 35+ Split Doubles | B52: =B51 -> Adda | C52: =D51+TIME(0,3,0) -> 46117.465 | D52: =C52+TIME(0,10,0) -> 46117.472 | E52: Group | F52: =F50 -> 1 | G52: 1 | H52: =IF(OR(S52="",T52=""),"",IFERROR(_xludf.XLOOKUP(S52,'Registrations'!#REF!,'Registrations'!#REF!,_xludf.XLOOKUP(S52,'Registrations'!$B$4:$B$211,'Registrations'!$E$4:$E$211,S52)),S52) & " vs " & IFERROR(_xludf.XLOOKUP(T52,'Registrations'!#REF!,'Registrations'!#REF!,_xludf.XLOOKUP(T52,'Registrations'!$B$4:$B$211,'Registrations'!$E$4:$E$211,T52)),T52)) -> 0 vs 0 | I52: =_xlfn.TEXTBEFORE(H52," vs ") -> 0 | J52: =_xlfn.TEXTAFTER(H52," vs ") -> 0 | K52: =IF(Schedules[[#This Row],[Player 2]]="",Schedules[[#This Row],[Player 1]],Schedules[[#This Row],[Player 1]]&" / "&Schedules[[#This Row],[Player 2]]) -> 0 / 0 | L52: 15 | M52: =IF(L52=15,"WIN","LOST") -> WIN | P52: =IF(Schedules[[#This Row],[Player 4]]="",Schedules[[#This Row],[Player 3]],Schedules[[#This Row],[Player 3]]&" / "&Schedules[[#This Row],[Player 4]]) -> 0 | Q52: 10 | R52: =IF(Q52=15,"WIN","LOST") -> LOST | S52: =Input!B14 -> 0 | T52: =Input!C14 -> 0
A53: Intermediate 35+ Split Doubles | B53: =B52 -> Adda | C53: =C52 -> 46117.465 | D53: =D52 -> 46117.472 | E53: Final | F53: =F51 -> 2 | G53: 3 | H53: =IF(OR(S53="",T53=""),"",IFERROR(_xludf.XLOOKUP(S53,'Registrations'!#REF!,'Registrations'!#REF!,_xludf.XLOOKUP(S53,'Registrations'!$B$4:$B$211,'Registrations'!$E$4:$E$211,S53)),S53) & " vs " & IFERROR(_xludf.XLOOKUP(T53,'Registrations'!#REF!,'Registrations'!#REF!,_xludf.XLOOKUP(T53,'Registrations'!$B$4:$B$211,'Registrations'!$E$4:$E$211,T53)),T53)) -> 0 vs 0 | I53: =_xlfn.TEXTBEFORE(H53," vs ") -> 0 | J53: =_xlfn.TEXTAFTER(H53," vs ") -> 0 | K53: =IF(Schedules[[#This Row],[Player 2]]="",Schedules[[#This Row],[Player 1]],Schedules[[#This Row],[Player 1]]&" / "&Schedules[[#This Row],[Player 2]]) -> 0 / 0 | L53: 15 | M53: =IF(L53=15,"WIN","LOST") -> WIN | P53: =IF(Schedules[[#This Row],[Player 4]]="",Schedules[[#This Row],[Player 3]],Schedules[[#This Row],[Player 3]]&" / "&Schedules[[#This Row],[Player 4]]) -> 0 | Q53: 10 | R53: =IF(Q53=15,"WIN","LOST") -> LOST | S53: =Input!B16 -> 0 | T53: =Input!C16 -> 0
A54: Intermediate 35+ Split Doubles | B54: =B53 -> Adda | C54: =D53+TIME(0,3,0) -> 46117.474 | D54: =C54+TIME(0,10,0) -> 46117.481 | E54: Group | F54: =F52 -> 1 | G54: =G52 -> 1 | H54: =IF(OR(S54="",T54=""),"",IFERROR(_xludf.XLOOKUP(S54,'Registrations'!#REF!,'Registrations'!#REF!,_xludf.XLOOKUP(S54,'Registrations'!$B$4:$B$211,'Registrations'!$E$4:$E$211,S54)),S54) & " vs " & IFERROR(_xludf.XLOOKUP(T54,'Registrations'!#REF!,'Registrations'!#REF!,_xludf.XLOOKUP(T54,'Registrations'!$B$4:$B$211,'Registrations'!$E$4:$E$211,T54)),T54)) -> 0 vs 0 | I54: =_xlfn.TEXTBEFORE(H54," vs ") -> 0 | J54: =_xlfn.TEXTAFTER(H54," vs ") -> 0 | K54: =IF(Schedules[[#This Row],[Player 2]]="",Schedules[[#This Row],[Player 1]],Schedules[[#This Row],[Player 1]]&" / "&Schedules[[#This Row],[Player 2]]) -> 0 / 0 | L54: 15 | M54: =IF(L54=15,"WIN","LOST") -> WIN | P54: =IF(Schedules[[#This Row],[Player 4]]="",Schedules[[#This Row],[Player 3]],Schedules[[#This Row],[Player 3]]&" / "&Schedules[[#This Row],[Player 4]]) -> 0 | Q54: 10 | R54: =IF(Q54=15,"WIN","LOST") -> LOST | S54: =Input!D14 -> 0 | T54: =Input!E14 -> 0
A55: Intermediate 35+ Split Doubles | B55: =B54 -> Adda | C55: =C54 -> 46117.474 | D55: =D54 -> 46117.481 | E55: =E54 -> Group | F55: =F53 -> 2 | G55: =G53 -> 3 | H55: =IF(OR(S55="",T55=""),"",IFERROR(_xludf.XLOOKUP(S55,'Registrations'!#REF!,'Registrations'!#REF!,_xludf.XLOOKUP(S55,'Registrations'!$B$4:$B$211,'Registrations'!$E$4:$E$211,S55)),S55) & " vs " & IFERROR(_xludf.XLOOKUP(T55,'Registrations'!#REF!,'Registrations'!#REF!,_xludf.XLOOKUP(T55,'Registrations'!$B$4:$B$211,'Registrations'!$E$4:$E$211,T55)),T55)) -> 0 vs 0 | I55: =_xlfn.TEXTBEFORE(H55," vs ") -> 0 | J55: =_xlfn.TEXTAFTER(H55," vs ") -> 0 | K55: =IF(Schedules[[#This Row],[Player 2]]="",Schedules[[#This Row],[Player 1]],Schedules[[#This Row],[Player 1]]&" / "&Schedules[[#This Row],[Player 2]]) -> 0 / 0 | L55: 15 | M55: =IF(L55=15,"WIN","LOST") -> WIN | P55: =IF(Schedules[[#This Row],[Player 4]]="",Schedules[[#This Row],[Player 3]],Schedules[[#This Row],[Player 3]]&" / "&Schedules[[#This Row],[Player 4]]) -> 0 | Q55: 10 | R55: =IF(Q55=15,"WIN","LOST") -> LOST | S55: =Input!D16 -> 0 | T55: =Input!E16 -> 0
A56: Intermediate 35+ Split Doubles | B56: =B55 -> Adda | C56: =D55+TIME(0,3,0) -> 46117.483 | D56: =C56+TIME(0,10,0) -> 46117.49 | E56: =E55 -> Group | F56: =F54 -> 1 | G56: =G54 -> 1 | H56: =IF(OR(S56="",T56=""),"",IFERROR(_xludf.XLOOKUP(S56,'Registrations'!#REF!,'Registrations'!#REF!,_xludf.XLOOKUP(S56,'Registrations'!$B$4:$B$211,'Registrations'!$E$4:$E$211,S56)),S56) & " vs " & IFERROR(_xludf.XLOOKUP(T56,'Registrations'!#REF!,'Registrations'!#REF!,_xludf.XLOOKUP(T56,'Registrations'!$B$4:$B$211,'Registrations'!$E$4:$E$211,T56)),T56)) -> 0 vs 0 | I56: =_xlfn.TEXTBEFORE(H56," vs ") -> 0 | J56: =_xlfn.TEXTAFTER(H56," vs ") -> 0 | K56: =IF(Schedules[[#This Row],[Player 2]]="",Schedules[[#This Row],[Player 1]],Schedules[[#This Row],[Player 1]]&" / "&Schedules[[#This Row],[Player 2]]) -> 0 / 0 | L56: 15 | M56: =IF(L56=15,"WIN","LOST") -> WIN | P56: =IF(Schedules[[#This Row],[Player 4]]="",Schedules[[#This Row],[Player 3]],Schedules[[#This Row],[Player 3]]&" / "&Schedules[[#This Row],[Player 4]]) -> 0 | Q56: 10 | R56: =IF(Q56=15,"WIN","LOST") -> LOST | S56: =Input!B14 -> 0 | T56: =Input!D14 -> 0
A57: Intermediate 35+ Split Doubles | B57: =B56 -> Adda | C57: =C56 -> 46117.483 | D57: =D56 -> 46117.49 | E57: =E56 -> Group | F57: =F55 -> 2 | G57: =G55 -> 3 | H57: =IF(OR(S57="",T57=""),"",IFERROR(_xludf.XLOOKUP(S57,'Registrations'!#REF!,'Registrations'!#REF!,_xludf.XLOOKUP(S57,'Registrations'!$B$4:$B$211,'Registrations'!$E$4:$E$211,S57)),S57) & " vs " & IFERROR(_xludf.XLOOKUP(T57,'Registrations'!#REF!,'Registrations'!#REF!,_xludf.XLOOKUP(T57,'Registrations'!$B$4:$B$211,'Registrations'!$E$4:$E$211,T57)),T57)) -> 0 vs 0 | I57: =_xlfn.TEXTBEFORE(H57," vs ") -> 0 | J57: =_xlfn.TEXTAFTER(H57," vs ") -> 0 | K57: =IF(Schedules[[#This Row],[Player 2]]="",Schedules[[#This Row],[Player 1]],Schedules[[#This Row],[Player 1]]&" / "&Schedules[[#This Row],[Player 2]]) -> 0 / 0 | L57: 15 | M57: =IF(L57=15,"WIN","LOST") -> WIN | P57: =IF(Schedules[[#This Row],[Player 4]]="",Schedules[[#This Row],[Player 3]],Schedules[[#This Row],[Player 3]]&" / "&Schedules[[#This Row],[Player 4]]) -> 0 | Q57: 10 | R57: =IF(Q57=15,"WIN","LOST") -> LOST | S57: =Input!B16 -> 0 | T57: =Input!D16 -> 0
A58: Intermediate 35+ Split Doubles | B58: =B57 -> Adda | C58: =D57+TIME(0,3,0) -> 46117.492 | D58: =C58+TIME(0,10,0) -> 46117.499 | E58: =E57 -> Group | F58: =F56 -> 1 | G58: =G56 -> 1 | H58: =IF(OR(S58="",T58=""),"",IFERROR(_xludf.XLOOKUP(S58,'Registrations'!#REF!,'Registrations'!#REF!,_xludf.XLOOKUP(S58,'Registrations'!$B$4:$B$211,'Registrations'!$E$4:$E$211,S58)),S58) & " vs " & IFERROR(_xludf.XLOOKUP(T58,'Registrations'!#REF!,'Registrations'!#REF!,_xludf.XLOOKUP(T58,'Registrations'!$B$4:$B$211,'Registrations'!$E$4:$E$211,T58)),T58)) -> 0 vs 0 | I58: =_xlfn.TEXTBEFORE(H58," vs ") -> 0 | J58: =_xlfn.TEXTAFTER(H58," vs ") -> 0 | K58: =IF(Schedules[[#This Row],[Player 2]]="",Schedules[[#This Row],[Player 1]],Schedules[[#This Row],[Player 1]]&" / "&Schedules[[#This Row],[Player 2]]) -> 0 / 0 | L58: 15 | M58: =IF(L58=15,"WIN","LOST") -> WIN | P58: =IF(Schedules[[#This Row],[Player 4]]="",Schedules[[#This Row],[Player 3]],Schedules[[#This Row],[Player 3]]&" / "&Schedules[[#This Row],[Player 4]]) -> 0 | Q58: 10 | R58: =IF(Q58=15,"WIN","LOST") -> LOST | S58: =Input!C14 -> 0 | T58: =Input!E14 -> 0
A59: Intermediate 35+ Split Doubles | B59: =B58 -> Adda | C59: =C58 -> 46117.492 | D59: =D58 -> 46117.499 | E59: =E58 -> Group | F59: =F57 -> 2 | G59: =G57 -> 3 | H59: =IF(OR(S59="",T59=""),"",IFERROR(_xludf.XLOOKUP(S59,'Registrations'!#REF!,'Registrations'!#REF!,_xludf.XLOOKUP(S59,'Registrations'!$B$4:$B$211,'Registrations'!$E$4:$E$211,S59)),S59) & " vs " & IFERROR(_xludf.XLOOKUP(T59,'Registrations'!#REF!,'Registrations'!#REF!,_xludf.XLOOKUP(T59,'Registrations'!$B$4:$B$211,'Registrations'!$E$4:$E$211,T59)),T59)) -> 0 vs 0 | I59: =_xlfn.TEXTBEFORE(H59," vs ") -> 0 | J59: =_xlfn.TEXTAFTER(H59," vs ") -> 0 | K59: =IF(Schedules[[#This Row],[Player 2]]="",Schedules[[#This Row],[Player 1]],Schedules[[#This Row],[Player 1]]&" / "&Schedules[[#This Row],[Player 2]]) -> 0 / 0 | L59: 15 | M59: =IF(L59=15,"WIN","LOST") -> WIN | P59: =IF(Schedules[[#This Row],[Player 4]]="",Schedules[[#This Row],[Player 3]],Schedules[[#This Row],[Player 3]]&" / "&Schedules[[#This Row],[Player 4]]) -> 0 | Q59: 10 | R59: =IF(Q59=15,"WIN","LOST") -> LOST | S59: =Input!C16 -> 0 | T59: =Input!E16 -> 0
A60: Intermediate 35+ Split Doubles | B60: =B59 -> Adda | C60: =D59+TIME(0,3,0) -> 46117.501 | D60: =C60+TIME(0,10,0) -> 46117.508 | E60: =E59 -> Group | F60: =F58 -> 1 | G60: =G58 -> 1 | H60: =IF(OR(S60="",T60=""),"",IFERROR(_xludf.XLOOKUP(S60,'Registrations'!#REF!,'Registrations'!#REF!,_xludf.XLOOKUP(S60,'Registrations'!$B$4:$B$211,'Registrations'!$E$4:$E$211,S60)),S60) & " vs " & IFERROR(_xludf.XLOOKUP(T60,'Registrations'!#REF!,'Registrations'!#REF!,_xludf.XLOOKUP(T60,'Registrations'!$B$4:$B$211,'Registrations'!$E$4:$E$211,T60)),T60)) -> 0 vs 0 | I60: =_xlfn.TEXTBEFORE(H60," vs ") -> 0 | J60: =_xlfn.TEXTAFTER(H60," vs ") -> 0 | K60: =IF(Schedules[[#This Row],[Player 2]]="",Schedules[[#This Row],[Player 1]],Schedules[[#This Row],[Player 1]]&" / "&Schedules[[#This Row],[Player 2]]) -> 0 / 0 | L60: 15 | M60: =IF(L60=15,"WIN","LOST") -> WIN | P60: =IF(Schedules[[#This Row],[Player 4]]="",Schedules[[#This Row],[Player 3]],Schedules[[#This Row],[Player 3]]&" / "&Schedules[[#This Row],[Player 4]]) -> 0 | Q60: 10 | R60: =IF(Q60=15,"WIN","LOST") -> LOST | S60: =Input!B14 -> 0 | T60: =Input!E14 -> 0
A61: Intermediate 35+ Split Doubles | B61: =B60 -> Adda | C61: =C60 -> 46117.501 | D61: =D60 -> 46117.508 | E61: =E60 -> Group | F61: =F59 -> 2 | G61: =G59 -> 3 | H61: =IF(OR(S61="",T61=""),"",IFERROR(_xludf.XLOOKUP(S61,'Registrations'!#REF!,'Registrations'!#REF!,_xludf.XLOOKUP(S61,'Registrations'!$B$4:$B$211,'Registrations'!$E$4:$E$211,S61)),S61) & " vs " & IFERROR(_xludf.XLOOKUP(T61,'Registrations'!#REF!,'Registrations'!#REF!,_xludf.XLOOKUP(T61,'Registrations'!$B$4:$B$211,'Registrations'!$E$4:$E$211,T61)),T61)) -> 0 vs 0 | I61: =_xlfn.TEXTBEFORE(H61," vs ") -> 0 | J61: =_xlfn.TEXTAFTER(H61," vs ") -> 0 | K61: =IF(Schedules[[#This Row],[Player 2]]="",Schedules[[#This Row],[Player 1]],Schedules[[#This Row],[Player 1]]&" / "&Schedules[[#This Row],[Player 2]]) -> 0 / 0 | L61: 15 | M61: =IF(L61=15,"WIN","LOST") -> WIN | P61: =IF(Schedules[[#This Row],[Player 4]]="",Schedules[[#This Row],[Player 3]],Schedules[[#This Row],[Player 3]]&" / "&Schedules[[#This Row],[Player 4]]) -> 0 | Q61: 10 | R61: =IF(Q61=15,"WIN","LOST") -> LOST | S61: =Input!B16 -> 0 | T61: =Input!E16 -> 0
A62: Intermediate 35+ Split Doubles | B62: =B61 -> Adda | C62: =D61+TIME(0,3,0) -> 46117.51 | D62: =C62+TIME(0,10,0) -> 46117.517 | E62: =E61 -> Group | F62: =F60 -> 1 | G62: =G60 -> 1 | H62: =IF(OR(S62="",T62=""),"",IFERROR(_xludf.XLOOKUP(S62,'Registrations'!#REF!,'Registrations'!#REF!,_xludf.XLOOKUP(S62,'Registrations'!$B$4:$B$211,'Registrations'!$E$4:$E$211,S62)),S62) & " vs " & IFERROR(_xludf.XLOOKUP(T62,'Registrations'!#REF!,'Registrations'!#REF!,_xludf.XLOOKUP(T62,'Registrations'!$B$4:$B$211,'Registrations'!$E$4:$E$211,T62)),T62)) -> 0 vs 0 | I62: =_xlfn.TEXTBEFORE(H62," vs ") -> 0 | J62: =_xlfn.TEXTAFTER(H62," vs ") -> 0 | K62: =IF(Schedules[[#This Row],[Player 2]]="",Schedules[[#This Row],[Player 1]],Schedules[[#This Row],[Player 1]]&" / "&Schedules[[#This Row],[Player 2]]) -> 0 / 0 | L62: 15 | M62: =IF(L62=15,"WIN","LOST") -> WIN | P62: =IF(Schedules[[#This Row],[Player 4]]="",Schedules[[#This Row],[Player 3]],Schedules[[#This Row],[Player 3]]&" / "&Schedules[[#This Row],[Player 4]]) -> 0 | Q62: 10 | R62: =IF(Q62=15,"WIN","LOST") -> LOST | S62: =Input!C14 -> 0 | T62: =Input!D14 -> 0
A63: Intermediate 35+ Split Doubles | B63: =B62 -> Adda | C63: =C62 -> 46117.51 | D63: =D62 -> 46117.517 | E63: =E62 -> Group | F63: =F61 -> 2 | G63: =G61 -> 3 | H63: =IF(OR(S63="",T63=""),"",IFERROR(_xludf.XLOOKUP(S63,'Registrations'!#REF!,'Registrations'!#REF!,_xludf.XLOOKUP(S63,'Registrations'!$B$4:$B$211,'Registrations'!$E$4:$E$211,S63)),S63) & " vs " & IFERROR(_xludf.XLOOKUP(T63,'Registrations'!#REF!,'Registrations'!#REF!,_xludf.XLOOKUP(T63,'Registrations'!$B$4:$B$211,'Registrations'!$E$4:$E$211,T63)),T63)) -> 0 vs 0 | I63: =_xlfn.TEXTBEFORE(H63," vs ") -> 0 | J63: =_xlfn.TEXTAFTER(H63," vs ") -> 0 | K63: =IF(Schedules[[#This Row],[Player 2]]="",Schedules[[#This Row],[Player 1]],Schedules[[#This Row],[Player 1]]&" / "&Schedules[[#This Row],[Player 2]]) -> 0 / 0 | L63: 15 | M63: =IF(L63=15,"WIN","LOST") -> WIN | P63: =IF(Schedules[[#This Row],[Player 4]]="",Schedules[[#This Row],[Player 3]],Schedules[[#This Row],[Player 3]]&" / "&Schedules[[#This Row],[Player 4]]) -> 0 | Q63: 10 | R63: =IF(Q63=15,"WIN","LOST") -> LOST | S63: =Input!C16 -> 0 | T63: =Input!D16 -> 0
A64: Intermediate 35+ Split Doubles | B64: =B63 -> Adda | C64: =D63+TIME(0,3,0) -> 46117.519 | D64: =C64+TIME(0,10,0) -> 46117.526 | E64: Quarters | F64: =F62 -> 1 | G64: 1 vs 3 | H64: =IF(OR(S64="",T64=""),"",IFERROR(_xludf.XLOOKUP(S64,'Registrations'!#REF!,'Registrations'!#REF!,_xludf.XLOOKUP(S64,'Registrations'!$B$4:$B$211,'Registrations'!$E$4:$E$211,S64)),S64) & " vs " & IFERROR(_xludf.XLOOKUP(T64,'Registrations'!#REF!,'Registrations'!#REF!,_xludf.XLOOKUP(T64,'Registrations'!$B$4:$B$211,'Registrations'!$E$4:$E$211,T64)),T64)) -> 0 vs 0 | I64: =_xlfn.TEXTBEFORE(H64," vs ") -> 0 | J64: =_xlfn.TEXTAFTER(H64," vs ") -> 0 | K64: =IF(Schedules[[#This Row],[Player 2]]="",Schedules[[#This Row],[Player 1]],Schedules[[#This Row],[Player 1]]&" / "&Schedules[[#This Row],[Player 2]]) -> 0 / 0 | L64: 15 | M64: =IF(L64=15,"WIN","LOST") -> WIN | P64: =IF(Schedules[[#This Row],[Player 4]]="",Schedules[[#This Row],[Player 3]],Schedules[[#This Row],[Player 3]]&" / "&Schedules[[#This Row],[Player 4]]) -> 0 | Q64: 10 | R64: =IF(Q64=15,"WIN","LOST") -> LOST | S64: =Input!H14 -> 0 | T64: =Input!I14 -> 0
A65: Intermediate 35+ Split Doubles | B65: =B64 -> Adda | C65: =C64 -> 46117.519 | D65: =D64 -> 46117.526 | E65: Warm-up / Open Play | F65: =F63 -> 2 | K65: =IF(Schedules[[#This Row],[Player 2]]="",Schedules[[#This Row],[Player 1]],Schedules[[#This Row],[Player 1]]&" / "&Schedules[[#This Row],[Player 2]]) -> 0 | P65: =IF(Schedules[[#This Row],[Player 4]]="",Schedules[[#This Row],[Player 3]],Schedules[[#This Row],[Player 3]]&" / "&Schedules[[#This Row],[Player 4]]) -> 0
A66: Intermediate 35+ Split Doubles | B66: =B65 -> Adda | C66: =D65+TIME(0,3,0) -> 46117.528 | D66: =C66+TIME(0,10,0) -> 46117.535 | E66: Group | F66: =F64 -> 1 | G66: 2 | H66: =IF(OR(S66="",T66=""),"",IFERROR(_xludf.XLOOKUP(S66,'Registrations'!#REF!,'Registrations'!#REF!,_xludf.XLOOKUP(S66,'Registrations'!$B$4:$B$211,'Registrations'!$E$4:$E$211,S66)),S66) & " vs " & IFERROR(_xludf.XLOOKUP(T66,'Registrations'!#REF!,'Registrations'!#REF!,_xludf.XLOOKUP(T66,'Registrations'!$B$4:$B$211,'Registrations'!$E$4:$E$211,T66)),T66)) -> 0 vs 0 | I66: =_xlfn.TEXTBEFORE(H66," vs ") -> 0 | J66: =_xlfn.TEXTAFTER(H66," vs ") -> 0 | K66: =IF(Schedules[[#This Row],[Player 2]]="",Schedules[[#This Row],[Player 1]],Schedules[[#This Row],[Player 1]]&" / "&Schedules[[#This Row],[Player 2]]) -> 0 / 0 | L66: 15 | M66: =IF(L66=15,"WIN","LOST") -> WIN | P66: =IF(Schedules[[#This Row],[Player 4]]="",Schedules[[#This Row],[Player 3]],Schedules[[#This Row],[Player 3]]&" / "&Schedules[[#This Row],[Player 4]]) -> 0 | Q66: 10 | R66: =IF(Q66=15,"WIN","LOST") -> LOST | S66: =Input!B15 -> 0 | T66: =Input!C15 -> 0
A67: Intermediate 35+ Split Doubles | B67: =B66 -> Adda | C67: =C66 -> 46117.528 | D67: =D66 -> 46117.535 | E67: =E66 -> Group | F67: =F65 -> 2 | G67: =G66 -> 2 | H67: =IF(OR(S67="",T67=""),"",IFERROR(_xludf.XLOOKUP(S67,'Registrations'!#REF!,'Registrations'!#REF!,_xludf.XLOOKUP(S67,'Registrations'!$B$4:$B$211,'Registrations'!$E$4:$E$211,S67)),S67) & " vs " & IFERROR(_xludf.XLOOKUP(T67,'Registrations'!#REF!,'Registrations'!#REF!,_xludf.XLOOKUP(T67,'Registrations'!$B$4:$B$211,'Registrations'!$E$4:$E$211,T67)),T67)) -> 0 vs 0 | I67: =_xlfn.TEXTBEFORE(H67," vs ") -> 0 | J67: =_xlfn.TEXTAFTER(H67," vs ") -> 0 | K67: =IF(Schedules[[#This Row],[Player 2]]="",Schedules[[#This Row],[Player 1]],Schedules[[#This Row],[Player 1]]&" / "&Schedules[[#This Row],[Player 2]]) -> 0 / 0 | L67: 15 | M67: =IF(L67=15,"WIN","LOST") -> WIN | P67: =IF(Schedules[[#This Row],[Player 4]]="",Schedules[[#This Row],[Player 3]],Schedules[[#This Row],[Player 3]]&" / "&Schedules[[#This Row],[Player 4]]) -> 0 | Q67: 10 | R67: =IF(Q67=15,"WIN","LOST") -> LOST | S67: =Input!D15 -> 0 | T67: =Input!E15 -> 0
A68: Intermediate 35+ Split Doubles | B68: =B67 -> Adda | C68: =D67+TIME(0,3,0) -> 46117.538 | D68: =C68+TIME(0,10,0) -> 46117.544 | E68: =E67 -> Group | F68: =F66 -> 1 | G68: 3 | H68: =IF(OR(S68="",T68=""),"",IFERROR(_xludf.XLOOKUP(S68,'Registrations'!#REF!,'Registrations'!#REF!,_xludf.XLOOKUP(S68,'Registrations'!$B$4:$B$211,'Registrations'!$E$4:$E$211,S68)),S68) & " vs " & IFERROR(_xludf.XLOOKUP(T68,'Registrations'!#REF!,'Registrations'!#REF!,_xludf.XLOOKUP(T68,'Registrations'!$B$4:$B$211,'Registrations'!$E$4:$E$211,T68)),T68)) -> 0 vs 0 | I68: =_xlfn.TEXTBEFORE(H68," vs ") -> 0 | J68: =_xlfn.TEXTAFTER(H68," vs ") -> 0 | K68: =IF(Schedules[[#This Row],[Player 2]]="",Schedules[[#This Row],[Player 1]],Schedules[[#This Row],[Player 1]]&" / "&Schedules[[#This Row],[Player 2]]) -> 0 / 0 | L68: 15 | M68: =IF(L68=15,"WIN","LOST") -> WIN | P68: =IF(Schedules[[#This Row],[Player 4]]="",Schedules[[#This Row],[Player 3]],Schedules[[#This Row],[Player 3]]&" / "&Schedules[[#This Row],[Player 4]]) -> 0 | Q68: 10 | R68: =IF(Q68=15,"WIN","LOST") -> LOST | S68: =Input!B15 -> 0 | T68: =Input!D15 -> 0
A69: Intermediate 35+ Split Doubles | B69: =B68 -> Adda | C69: =C68 -> 46117.538 | D69: =D68 -> 46117.544 | E69: =E68 -> Group | F69: =F67 -> 2 | G69: 4 | H69: =IF(OR(S69="",T69=""),"",IFERROR(_xludf.XLOOKUP(S69,'Registrations'!#REF!,'Registrations'!#REF!,_xludf.XLOOKUP(S69,'Registrations'!$B$4:$B$211,'Registrations'!$E$4:$E$211,S69)),S69) & " vs " & IFERROR(_xludf.XLOOKUP(T69,'Registrations'!#REF!,'Registrations'!#REF!,_xludf.XLOOKUP(T69,'Registrations'!$B$4:$B$211,'Registrations'!$E$4:$E$211,T69)),T69)) -> 0 vs 0 | I69: =_xlfn.TEXTBEFORE(H69," vs ") -> 0 | J69: =_xlfn.TEXTAFTER(H69," vs ") -> 0 | K69: =IF(Schedules[[#This Row],[Player 2]]="",Schedules[[#This Row],[Player 1]],Schedules[[#This Row],[Player 1]]&" / "&Schedules[[#This Row],[Player 2]]) -> 0 / 0 | L69: 15 | M69: =IF(L69=15,"WIN","LOST") -> WIN | P69: =IF(Schedules[[#This Row],[Player 4]]="",Schedules[[#This Row],[Player 3]],Schedules[[#This Row],[Player 3]]&" / "&Schedules[[#This Row],[Player 4]]) -> 0 | Q69: 10 | R69: =IF(Q69=15,"WIN","LOST") -> LOST | S69: =Input!C15 -> 0 | T69: =Input!E15 -> 0
A70: Intermediate 35+ Split Doubles | B70: =B69 -> Adda | C70: =D69+TIME(0,3,0) -> 46117.547 | D70: =C70+TIME(0,10,0) -> 46117.553 | E70: =E69 -> Group | F70: =F68 -> 1 | G70: 3 | H70: =IF(OR(S70="",T70=""),"",IFERROR(_xludf.XLOOKUP(S70,'Registrations'!#REF!,'Registrations'!#REF!,_xludf.XLOOKUP(S70,'Registrations'!$B$4:$B$211,'Registrations'!$E$4:$E$211,S70)),S70) & " vs " & IFERROR(_xludf.XLOOKUP(T70,'Registrations'!#REF!,'Registrations'!#REF!,_xludf.XLOOKUP(T70,'Registrations'!$B$4:$B$211,'Registrations'!$E$4:$E$211,T70)),T70)) -> 0 vs 0 | I70: =_xlfn.TEXTBEFORE(H70," vs ") -> 0 | J70: =_xlfn.TEXTAFTER(H70," vs ") -> 0 | K70: =IF(Schedules[[#This Row],[Player 2]]="",Schedules[[#This Row],[Player 1]],Schedules[[#This Row],[Player 1]]&" / "&Schedules[[#This Row],[Player 2]]) -> 0 / 0 | L70: 15 | M70: =IF(L70=15,"WIN","LOST") -> WIN | P70: =IF(Schedules[[#This Row],[Player 4]]="",Schedules[[#This Row],[Player 3]],Schedules[[#This Row],[Player 3]]&" / "&Schedules[[#This Row],[Player 4]]) -> 0 | Q70: 10 | R70: =IF(Q70=15,"WIN","LOST") -> LOST | S70: =Input!B15 -> 0 | T70: =Input!E15 -> 0
A71: Intermediate 35+ Split Doubles | B71: =B70 -> Adda | C71: =C70 -> 46117.547 | D71: =D70 -> 46117.553 | E71: =E70 -> Group | F71: =F69 -> 2 | G71: 4 | H71: =IF(OR(S71="",T71=""),"",IFERROR(_xludf.XLOOKUP(S71,'Registrations'!#REF!,'Registrations'!#REF!,_xludf.XLOOKUP(S71,'Registrations'!$B$4:$B$211,'Registrations'!$E$4:$E$211,S71)),S71) & " vs " & IFERROR(_xludf.XLOOKUP(T71,'Registrations'!#REF!,'Registrations'!#REF!,_xludf.XLOOKUP(T71,'Registrations'!$B$4:$B$211,'Registrations'!$E$4:$E$211,T71)),T71)) -> 0 vs 0 | I71: =_xlfn.TEXTBEFORE(H71," vs ") -> 0 | J71: =_xlfn.TEXTAFTER(H71," vs ") -> 0 | K71: =IF(Schedules[[#This Row],[Player 2]]="",Schedules[[#This Row],[Player 1]],Schedules[[#This Row],[Player 1]]&" / "&Schedules[[#This Row],[Player 2]]) -> 0 / 0 | L71: 15 | M71: =IF(L71=15,"WIN","LOST") -> WIN | P71: =IF(Schedules[[#This Row],[Player 4]]="",Schedules[[#This Row],[Player 3]],Schedules[[#This Row],[Player 3]]&" / "&Schedules[[#This Row],[Player 4]]) -> 0 | Q71: 10 | R71: =IF(Q71=15,"WIN","LOST") -> LOST | S71: =Input!C15 -> 0 | T71: =Input!D15 -> 0
A72: Intermediate 35+ Split Doubles | B72: =B71 -> Adda | C72: =D71+TIME(0,3,0) -> 46117.556 | D72: =C72+TIME(0,10,0) -> 46117.563 | E72: Quarters | F72: =F70 -> 1 | G72: 2 vs 1 | H72: =IF(OR(S72="",T72=""),"",IFERROR(_xludf.XLOOKUP(S72,'Registrations'!#REF!,'Registrations'!#REF!,_xludf.XLOOKUP(S72,'Registrations'!$B$4:$B$211,'Registrations'!$E$4:$E$211,S72)),S72) & " vs " & IFERROR(_xludf.XLOOKUP(T72,'Registrations'!#REF!,'Registrations'!#REF!,_xludf.XLOOKUP(T72,'Registrations'!$B$4:$B$211,'Registrations'!$E$4:$E$211,T72)),T72)) -> 0 vs 0 | I72: =_xlfn.TEXTBEFORE(H72," vs ") -> 0 | J72: =_xlfn.TEXTAFTER(H72," vs ") -> 0 | K72: =IF(Schedules[[#This Row],[Player 2]]="",Schedules[[#This Row],[Player 1]],Schedules[[#This Row],[Player 1]]&" / "&Schedules[[#This Row],[Player 2]]) -> 0 / 0 | L72: 15 | M72: =IF(L72=15,"WIN","LOST") -> WIN | P72: =IF(Schedules[[#This Row],[Player 4]]="",Schedules[[#This Row],[Player 3]],Schedules[[#This Row],[Player 3]]&" / "&Schedules[[#This Row],[Player 4]]) -> 0 | Q72: 10 | R72: =IF(Q72=15,"WIN","LOST") -> LOST | S72: =Input!H15 -> 0 | T72: =Input!I15 -> 0
A73: Intermediate 35+ Split Doubles | B73: =B72 -> Adda | C73: =C72 -> 46117.556 | D73: =D72 -> 46117.563 | E73: =E72 -> Quarters | F73: =F71 -> 2 | G73: 3 vs 2 | H73: =IF(OR(S73="",T73=""),"",IFERROR(_xludf.XLOOKUP(S73,'Registrations'!#REF!,'Registrations'!#REF!,_xludf.XLOOKUP(S73,'Registrations'!$B$4:$B$211,'Registrations'!$E$4:$E$211,S73)),S73) & " vs " & IFERROR(_xludf.XLOOKUP(T73,'Registrations'!#REF!,'Registrations'!#REF!,_xludf.XLOOKUP(T73,'Registrations'!$B$4:$B$211,'Registrations'!$E$4:$E$211,T73)),T73)) -> 0 vs 0 | I73: =_xlfn.TEXTBEFORE(H73," vs ") -> 0 | J73: =_xlfn.TEXTAFTER(H73," vs ") -> 0 | K73: =IF(Schedules[[#This Row],[Player 2]]="",Schedules[[#This Row],[Player 1]],Schedules[[#This Row],[Player 1]]&" / "&Schedules[[#This Row],[Player 2]]) -> 0 / 0 | L73: 15 | M73: =IF(L73=15,"WIN","LOST") -> WIN | P73: =IF(Schedules[[#This Row],[Player 4]]="",Schedules[[#This Row],[Player 3]],Schedules[[#This Row],[Player 3]]&" / "&Schedules[[#This Row],[Player 4]]) -> 0 | Q73: 10 | R73: =IF(Q73=15,"WIN","LOST") -> LOST | S73: =Input!H16 -> 0 | T73: =Input!I16 -> 0
A74: Intermediate 35+ Split Doubles | B74: =B73 -> Adda | C74: =D73+TIME(0,3,0) -> 46117.565 | D74: =C74+TIME(0,10,0) -> 46117.572 | E74: Semi Finals | F74: =F72 -> 1 | G74: 1 vs 2 | H74: =IF(OR(S74="",T74=""),"",IFERROR(_xludf.XLOOKUP(S74,'Registrations'!#REF!,'Registrations'!#REF!,_xludf.XLOOKUP(S74,'Registrations'!$B$4:$B$211,'Registrations'!$E$4:$E$211,S74)),S74) & " vs " & IFERROR(_xludf.XLOOKUP(T74,'Registrations'!#REF!,'Registrations'!#REF!,_xludf.XLOOKUP(T74,'Registrations'!$B$4:$B$211,'Registrations'!$E$4:$E$211,T74)),T74)) -> 0 vs 0 | I74: =_xlfn.TEXTBEFORE(H74," vs ") -> 0 | J74: =_xlfn.TEXTAFTER(H74," vs ") -> 0 | K74: =IF(Schedules[[#This Row],[Player 2]]="",Schedules[[#This Row],[Player 1]],Schedules[[#This Row],[Player 1]]&" / "&Schedules[[#This Row],[Player 2]]) -> 0 / 0 | L74: 15 | M74: =IF(L74=15,"WIN","LOST") -> WIN | P74: =IF(Schedules[[#This Row],[Player 4]]="",Schedules[[#This Row],[Player 3]],Schedules[[#This Row],[Player 3]]&" / "&Schedules[[#This Row],[Player 4]]) -> 0 | Q74: 10 | R74: =IF(Q74=15,"WIN","LOST") -> LOST | S74: =Input!L14 -> 0 | T74: =Input!M14 -> 0
A75: Intermediate 35+ Split Doubles | B75: =B74 -> Adda | C75: =C74 -> 46117.565 | D75: =D74 -> 46117.572 | E75: =E74 -> Semi Finals | F75: =F73 -> 2 | G75: 3 vs WC 1 | H75: =IF(OR(S75="",T75=""),"",IFERROR(_xludf.XLOOKUP(S75,'Registrations'!#REF!,'Registrations'!#REF!,_xludf.XLOOKUP(S75,'Registrations'!$B$4:$B$211,'Registrations'!$E$4:$E$211,S75)),S75) & " vs " & IFERROR(_xludf.XLOOKUP(T75,'Registrations'!#REF!,'Registrations'!#REF!,_xludf.XLOOKUP(T75,'Registrations'!$B$4:$B$211,'Registrations'!$E$4:$E$211,T75)),T75)) -> 0 vs WC 1 | I75: =_xlfn.TEXTBEFORE(H75," vs ") -> 0 | J75: =_xlfn.TEXTAFTER(H75," vs ") -> WC 1 | K75: =IF(Schedules[[#This Row],[Player 2]]="",Schedules[[#This Row],[Player 1]],Schedules[[#This Row],[Player 1]]&" / "&Schedules[[#This Row],[Player 2]]) -> 0 / WC 1 | L75: 15 | M75: =IF(L75=15,"WIN","LOST") -> WIN | P75: =IF(Schedules[[#This Row],[Player 4]]="",Schedules[[#This Row],[Player 3]],Schedules[[#This Row],[Player 3]]&" / "&Schedules[[#This Row],[Player 4]]) -> 0 | Q75: 10 | R75: =IF(Q75=15,"WIN","LOST") -> LOST | S75: =Input!L15 -> 0 | T75: =Input!M15 -> WC 1
A76: Intermediate 35+ Split Doubles | B76: =B75 -> Adda | C76: =D75+TIME(0,3,0) -> 46117.574 | D76: =C76+TIME(0,10,0) -> 46117.581 | E76: Finals | F76: =F74 -> 1 | G76: 1 vs 2 | H76: =IF(OR(S76="",T76=""),"",IFERROR(_xludf.XLOOKUP(S76,'Registrations'!#REF!,'Registrations'!#REF!,_xludf.XLOOKUP(S76,'Registrations'!$B$4:$B$211,'Registrations'!$E$4:$E$211,S76)),S76) & " vs " & IFERROR(_xludf.XLOOKUP(T76,'Registrations'!#REF!,'Registrations'!#REF!,_xludf.XLOOKUP(T76,'Registrations'!$B$4:$B$211,'Registrations'!$E$4:$E$211,T76)),T76)) -> 0 vs 0 | I76: =_xlfn.TEXTBEFORE(H76," vs ") -> 0 | J76: =_xlfn.TEXTAFTER(H76," vs ") -> 0 | K76: =IF(Schedules[[#This Row],[Player 2]]="",Schedules[[#This Row],[Player 1]],Schedules[[#This Row],[Player 1]]&" / "&Schedules[[#This Row],[Player 2]]) -> 0 / 0 | L76: 15 | M76: =IF(L76=15,"WIN","LOST") -> WIN | P76: =IF(Schedules[[#This Row],[Player 4]]="",Schedules[[#This Row],[Player 3]],Schedules[[#This Row],[Player 3]]&" / "&Schedules[[#This Row],[Player 4]]) -> 0 | Q76: 10 | R76: =IF(Q76=15,"WIN","LOST") -> LOST | S76: =Input!P14 -> 0 | T76: =Input!Q14 -> 0
A77: Int Men Doubles | B77: =B76 -> Adda | C77: 0.625 | D77: =C77+TIME(0,10,0) -> 0.63194444 | E77: Group | F77: 1 | G77: 1 | H77: =IF(OR(S77="",T77=""),"",IFERROR(_xludf.XLOOKUP(S77,'Registrations'!#REF!,'Registrations'!#REF!,_xludf.XLOOKUP(S77,'Registrations'!$B$4:$B$211,'Registrations'!$E$4:$E$211,S77)),S77) & " vs " & IFERROR(_xludf.XLOOKUP(T77,'Registrations'!#REF!,'Registrations'!#REF!,_xludf.XLOOKUP(T77,'Registrations'!$B$4:$B$211,'Registrations'!$E$4:$E$211,T77)),T77)) -> 0 vs 0 | I77: =_xlfn.TEXTBEFORE(H77," vs ") -> 0 | J77: =_xlfn.TEXTAFTER(H77," vs ") -> 0 | K77: =IF(Schedules[[#This Row],[Player 2]]="",Schedules[[#This Row],[Player 1]],Schedules[[#This Row],[Player 1]]&" / "&Schedules[[#This Row],[Player 2]]) -> 0 / 0 | L77: 15 | M77: =IF(L77=15,"WIN","LOST") -> WIN | P77: =IF(Schedules[[#This Row],[Player 4]]="",Schedules[[#This Row],[Player 3]],Schedules[[#This Row],[Player 3]]&" / "&Schedules[[#This Row],[Player 4]]) -> 0 | Q77: 10 | R77: =IF(Q77=15,"WIN","LOST") -> LOST | S77: =Input!B25 -> 0 | T77: =Input!C25 -> 0
A78: Int Men Doubles | B78: =B77 -> Adda | C78: =C77 -> 0.625 | D78: =D77 -> 0.63194444 | E78: =E77 -> Group | F78: 2 | G78: 2 | H78: =IF(OR(S78="",T78=""),"",IFERROR(_xludf.XLOOKUP(S78,'Registrations'!#REF!,'Registrations'!#REF!,_xludf.XLOOKUP(S78,'Registrations'!$B$4:$B$211,'Registrations'!$E$4:$E$211,S78)),S78) & " vs " & IFERROR(_xludf.XLOOKUP(T78,'Registrations'!#REF!,'Registrations'!#REF!,_xludf.XLOOKUP(T78,'Registrations'!$B$4:$B$211,'Registrations'!$E$4:$E$211,T78)),T78)) -> 0 vs 0 | I78: =_xlfn.TEXTBEFORE(H78," vs ") -> 0 | J78: =_xlfn.TEXTAFTER(H78," vs ") -> 0 | K78: =IF(Schedules[[#This Row],[Player 2]]="",Schedules[[#This Row],[Player 1]],Schedules[[#This Row],[Player 1]]&" / "&Schedules[[#This Row],[Player 2]]) -> 0 / 0 | L78: 15 | M78: =IF(L78=15,"WIN","LOST") -> WIN | P78: =IF(Schedules[[#This Row],[Player 4]]="",Schedules[[#This Row],[Player 3]],Schedules[[#This Row],[Player 3]]&" / "&Schedules[[#This Row],[Player 4]]) -> 0 | Q78: 10 | R78: =IF(Q78=15,"WIN","LOST") -> LOST | S78: =Input!B26 -> 0 | T78: =Input!C26 -> 0
A79: Int Men Doubles | B79: =B78 -> Adda | C79: =D78+TIME(0,3,0) -> 0.63402778 | D79: =C79+TIME(0,10,0) -> 0.64097222 | E79: =E78 -> Group | F79: 1 | G79: 1 | H79: =IF(OR(S79="",T79=""),"",IFERROR(_xludf.XLOOKUP(S79,'Registrations'!#REF!,'Registrations'!#REF!,_xludf.XLOOKUP(S79,'Registrations'!$B$4:$B$211,'Registrations'!$E$4:$E$211,S79)),S79) & " vs " & IFERROR(_xludf.XLOOKUP(T79,'Registrations'!#REF!,'Registrations'!#REF!,_xludf.XLOOKUP(T79,'Registrations'!$B$4:$B$211,'Registrations'!$E$4:$E$211,T79)),T79)) -> 0 vs 0 | I79: =_xlfn.TEXTBEFORE(H79," vs ") -> 0 | J79: =_xlfn.TEXTAFTER(H79," vs ") -> 0 | K79: =IF(Schedules[[#This Row],[Player 2]]="",Schedules[[#This Row],[Player 1]],Schedules[[#This Row],[Player 1]]&" / "&Schedules[[#This Row],[Player 2]]) -> 0 / 0 | L79: 15 | M79: =IF(L79=15,"WIN","LOST") -> WIN | P79: =IF(Schedules[[#This Row],[Player 4]]="",Schedules[[#This Row],[Player 3]],Schedules[[#This Row],[Player 3]]&" / "&Schedules[[#This Row],[Player 4]]) -> 0 | Q79: 10 | R79: =IF(Q79=15,"WIN","LOST") -> LOST | S79: =Input!D25 -> 0 | T79: =Input!E25 -> 0
A80: Int Men Doubles | B80: =B79 -> Adda | C80: =C79 -> 0.63402778 | D80: =D79 -> 0.64097222 | E80: =E79 -> Group | F80: 2 | G80: 2 | H80: =IF(OR(S80="",T80=""),"",IFERROR(_xludf.XLOOKUP(S80,'Registrations'!#REF!,'Registrations'!#REF!,_xludf.XLOOKUP(S80,'Registrations'!$B$4:$B$211,'Registrations'!$E$4:$E$211,S80)),S80) & " vs " & IFERROR(_xludf.XLOOKUP(T80,'Registrations'!#REF!,'Registrations'!#REF!,_xludf.XLOOKUP(T80,'Registrations'!$B$4:$B$211,'Registrations'!$E$4:$E$211,T80)),T80)) -> 0 vs 0 | I80: =_xlfn.TEXTBEFORE(H80," vs ") -> 0 | J80: =_xlfn.TEXTAFTER(H80," vs ") -> 0 | K80: =IF(Schedules[[#This Row],[Player 2]]="",Schedules[[#This Row],[Player 1]],Schedules[[#This Row],[Player 1]]&" / "&Schedules[[#This Row],[Player 2]]) -> 0 / 0 | L80: 15 | M80: =IF(L80=15,"WIN","LOST") -> WIN | P80: =IF(Schedules[[#This Row],[Player 4]]="",Schedules[[#This Row],[Player 3]],Schedules[[#This Row],[Player 3]]&" / "&Schedules[[#This Row],[Player 4]]) -> 0 | Q80: 10 | R80: =IF(Q80=15,"WIN","LOST") -> LOST | S80: =Input!D26 -> 0 | T80: =Input!E26 -> 0
A81: Int Men Doubles | B81: =B80 -> Adda | C81: =D80+TIME(0,3,0) -> 0.64305556 | D81: =C81+TIME(0,10,0) -> 0.65 | E81: =E80 -> Group | F81: 1 | G81: 1 | H81: =IF(OR(S81="",T81=""),"",IFERROR(_xludf.XLOOKUP(S81,'Registrations'!#REF!,'Registrations'!#REF!,_xludf.XLOOKUP(S81,'Registrations'!$B$4:$B$211,'Registrations'!$E$4:$E$211,S81)),S81) & " vs " & IFERROR(_xludf.XLOOKUP(T81,'Registrations'!#REF!,'Registrations'!#REF!,_xludf.XLOOKUP(T81,'Registrations'!$B$4:$B$211,'Registrations'!$E$4:$E$211,T81)),T81)) -> 0 vs 0 | I81: =_xlfn.TEXTBEFORE(H81," vs ") -> 0 | J81: =_xlfn.TEXTAFTER(H81," vs ") -> 0 | K81: =IF(Schedules[[#This Row],[Player 2]]="",Schedules[[#This Row],[Player 1]],Schedules[[#This Row],[Player 1]]&" / "&Schedules[[#This Row],[Player 2]]) -> 0 / 0 | L81: 15 | M81: =IF(L81=15,"WIN","LOST") -> WIN | P81: =IF(Schedules[[#This Row],[Player 4]]="",Schedules[[#This Row],[Player 3]],Schedules[[#This Row],[Player 3]]&" / "&Schedules[[#This Row],[Player 4]]) -> 0 | Q81: 10 | R81: =IF(Q81=15,"WIN","LOST") -> LOST | S81: =Input!B25 -> 0 | T81: =Input!D25 -> 0
A82: Int Men Doubles | B82: =B81 -> Adda | C82: =C81 -> 0.64305556 | D82: =D81 -> 0.65 | E82: =E81 -> Group | F82: 2 | G82: 2 | H82: =IF(OR(S82="",T82=""),"",IFERROR(_xludf.XLOOKUP(S82,'Registrations'!#REF!,'Registrations'!#REF!,_xludf.XLOOKUP(S82,'Registrations'!$B$4:$B$211,'Registrations'!$E$4:$E$211,S82)),S82) & " vs " & IFERROR(_xludf.XLOOKUP(T82,'Registrations'!#REF!,'Registrations'!#REF!,_xludf.XLOOKUP(T82,'Registrations'!$B$4:$B$211,'Registrations'!$E$4:$E$211,T82)),T82)) -> 0 vs 0 | I82: =_xlfn.TEXTBEFORE(H82," vs ") -> 0 | J82: =_xlfn.TEXTAFTER(H82," vs ") -> 0 | K82: =IF(Schedules[[#This Row],[Player 2]]="",Schedules[[#This Row],[Player 1]],Schedules[[#This Row],[Player 1]]&" / "&Schedules[[#This Row],[Player 2]]) -> 0 / 0 | L82: 15 | M82: =IF(L82=15,"WIN","LOST") -> WIN | P82: =IF(Schedules[[#This Row],[Player 4]]="",Schedules[[#This Row],[Player 3]],Schedules[[#This Row],[Player 3]]&" / "&Schedules[[#This Row],[Player 4]]) -> 0 | Q82: 10 | R82: =IF(Q82=15,"WIN","LOST") -> LOST | S82: =Input!B26 -> 0 | T82: =Input!D26 -> 0
A83: Int Men Doubles | B83: =B82 -> Adda | C83: =D82+TIME(0,3,0) -> 0.65208333 | D83: =C83+TIME(0,10,0) -> 0.65902778 | E83: =E82 -> Group | F83: 1 | G83: 1 | H83: =IF(OR(S83="",T83=""),"",IFERROR(_xludf.XLOOKUP(S83,'Registrations'!#REF!,'Registrations'!#REF!,_xludf.XLOOKUP(S83,'Registrations'!$B$4:$B$211,'Registrations'!$E$4:$E$211,S83)),S83) & " vs " & IFERROR(_xludf.XLOOKUP(T83,'Registrations'!#REF!,'Registrations'!#REF!,_xludf.XLOOKUP(T83,'Registrations'!$B$4:$B$211,'Registrations'!$E$4:$E$211,T83)),T83)) -> 0 vs 0 | I83: =_xlfn.TEXTBEFORE(H83," vs ") -> 0 | J83: =_xlfn.TEXTAFTER(H83," vs ") -> 0 | K83: =IF(Schedules[[#This Row],[Player 2]]="",Schedules[[#This Row],[Player 1]],Schedules[[#This Row],[Player 1]]&" / "&Schedules[[#This Row],[Player 2]]) -> 0 / 0 | L83: 15 | M83: =IF(L83=15,"WIN","LOST") -> WIN | P83: =IF(Schedules[[#This Row],[Player 4]]="",Schedules[[#This Row],[Player 3]],Schedules[[#This Row],[Player 3]]&" / "&Schedules[[#This Row],[Player 4]]) -> 0 | Q83: 10 | R83: =IF(Q83=15,"WIN","LOST") -> LOST | S83: =Input!C25 -> 0 | T83: =Input!E25 -> 0
A84: Int Men Doubles | B84: =B83 -> Adda | C84: =C83 -> 0.65208333 | D84: =D83 -> 0.65902778 | E84: =E83 -> Group | F84: 2 | G84: 2 | H84: =IF(OR(S84="",T84=""),"",IFERROR(_xludf.XLOOKUP(S84,'Registrations'!#REF!,'Registrations'!#REF!,_xludf.XLOOKUP(S84,'Registrations'!$B$4:$B$211,'Registrations'!$E$4:$E$211,S84)),S84) & " vs " & IFERROR(_xludf.XLOOKUP(T84,'Registrations'!#REF!,'Registrations'!#REF!,_xludf.XLOOKUP(T84,'Registrations'!$B$4:$B$211,'Registrations'!$E$4:$E$211,T84)),T84)) -> 0 vs 0 | I84: =_xlfn.TEXTBEFORE(H84," vs ") -> 0 | J84: =_xlfn.TEXTAFTER(H84," vs ") -> 0 | K84: =IF(Schedules[[#This Row],[Player 2]]="",Schedules[[#This Row],[Player 1]],Schedules[[#This Row],[Player 1]]&" / "&Schedules[[#This Row],[Player 2]]) -> 0 / 0 | L84: 15 | M84: =IF(L84=15,"WIN","LOST") -> WIN | P84: =IF(Schedules[[#This Row],[Player 4]]="",Schedules[[#This Row],[Player 3]],Schedules[[#This Row],[Player 3]]&" / "&Schedules[[#This Row],[Player 4]]) -> 0 | Q84: 10 | R84: =IF(Q84=15,"WIN","LOST") -> LOST | S84: =Input!C26 -> 0 | T84: =Input!E26 -> 0
A85: Int Men Doubles | B85: =B84 -> Adda | C85: =D84+TIME(0,3,0) -> 0.66111111 | D85: =C85+TIME(0,10,0) -> 0.66805556 | E85: =E84 -> Group | F85: 1 | G85: 1 | H85: =IF(OR(S85="",T85=""),"",IFERROR(_xludf.XLOOKUP(S85,'Registrations'!#REF!,'Registrations'!#REF!,_xludf.XLOOKUP(S85,'Registrations'!$B$4:$B$211,'Registrations'!$E$4:$E$211,S85)),S85) & " vs " & IFERROR(_xludf.XLOOKUP(T85,'Registrations'!#REF!,'Registrations'!#REF!,_xludf.XLOOKUP(T85,'Registrations'!$B$4:$B$211,'Registrations'!$E$4:$E$211,T85)),T85)) -> 0 vs 0 | I85: =_xlfn.TEXTBEFORE(H85," vs ") -> 0 | J85: =_xlfn.TEXTAFTER(H85," vs ") -> 0 | K85: =IF(Schedules[[#This Row],[Player 2]]="",Schedules[[#This Row],[Player 1]],Schedules[[#This Row],[Player 1]]&" / "&Schedules[[#This Row],[Player 2]]) -> 0 / 0 | L85: 15 | M85: =IF(L85=15,"WIN","LOST") -> WIN | P85: =IF(Schedules[[#This Row],[Player 4]]="",Schedules[[#This Row],[Player 3]],Schedules[[#This Row],[Player 3]]&" / "&Schedules[[#This Row],[Player 4]]) -> 0 | Q85: 10 | R85: =IF(Q85=15,"WIN","LOST") -> LOST | S85: =Input!B25 -> 0 | T85: =Input!E25 -> 0
A86: Int Men Doubles | B86: =B85 -> Adda | C86: =C85 -> 0.66111111 | D86: =D85 -> 0.66805556 | E86: =E85 -> Group | F86: 2 | G86: 2 | H86: =IF(OR(S86="",T86=""),"",IFERROR(_xludf.XLOOKUP(S86,'Registrations'!#REF!,'Registrations'!#REF!,_xludf.XLOOKUP(S86,'Registrations'!$B$4:$B$211,'Registrations'!$E$4:$E$211,S86)),S86) & " vs " & IFERROR(_xludf.XLOOKUP(T86,'Registrations'!#REF!,'Registrations'!#REF!,_xludf.XLOOKUP(T86,'Registrations'!$B$4:$B$211,'Registrations'!$E$4:$E$211,T86)),T86)) -> 0 vs 0 | I86: =_xlfn.TEXTBEFORE(H86," vs ") -> 0 | J86: =_xlfn.TEXTAFTER(H86," vs ") -> 0 | K86: =IF(Schedules[[#This Row],[Player 2]]="",Schedules[[#This Row],[Player 1]],Schedules[[#This Row],[Player 1]]&" / "&Schedules[[#This Row],[Player 2]]) -> 0 / 0 | L86: 15 | M86: =IF(L86=15,"WIN","LOST") -> WIN | P86: =IF(Schedules[[#This Row],[Player 4]]="",Schedules[[#This Row],[Player 3]],Schedules[[#This Row],[Player 3]]&" / "&Schedules[[#This Row],[Player 4]]) -> 0 | Q86: 10 | R86: =IF(Q86=15,"WIN","LOST") -> LOST | S86: =Input!B26 -> 0 | T86: =Input!E26 -> 0
A87: Int Men Doubles | B87: =B86 -> Adda | C87: =D86+TIME(0,3,0) -> 0.67013889 | D87: =C87+TIME(0,10,0) -> 0.67708333 | E87: =E86 -> Group | F87: 1 | G87: 1 | H87: =IF(OR(S87="",T87=""),"",IFERROR(_xludf.XLOOKUP(S87,'Registrations'!#REF!,'Registrations'!#REF!,_xludf.XLOOKUP(S87,'Registrations'!$B$4:$B$211,'Registrations'!$E$4:$E$211,S87)),S87) & " vs " & IFERROR(_xludf.XLOOKUP(T87,'Registrations'!#REF!,'Registrations'!#REF!,_xludf.XLOOKUP(T87,'Registrations'!$B$4:$B$211,'Registrations'!$E$4:$E$211,T87)),T87)) -> 0 vs 0 | I87: =_xlfn.TEXTBEFORE(H87," vs ") -> 0 | J87: =_xlfn.TEXTAFTER(H87," vs ") -> 0 | K87: =IF(Schedules[[#This Row],[Player 2]]="",Schedules[[#This Row],[Player 1]],Schedules[[#This Row],[Player 1]]&" / "&Schedules[[#This Row],[Player 2]]) -> 0 / 0 | L87: 15 | M87: =IF(L87=15,"WIN","LOST") -> WIN | P87: =IF(Schedules[[#This Row],[Player 4]]="",Schedules[[#This Row],[Player 3]],Schedules[[#This Row],[Player 3]]&" / "&Schedules[[#This Row],[Player 4]]) -> 0 | Q87: 10 | R87: =IF(Q87=15,"WIN","LOST") -> LOST | S87: =Input!C25 -> 0 | T87: =Input!D25 -> 0
A88: Int Men Doubles | B88: =B87 -> Adda | C88: =C87 -> 0.67013889 | D88: =D87 -> 0.67708333 | E88: =E87 -> Group | F88: 2 | G88: 2 | H88: =IF(OR(S88="",T88=""),"",IFERROR(_xludf.XLOOKUP(S88,'Registrations'!#REF!,'Registrations'!#REF!,_xludf.XLOOKUP(S88,'Registrations'!$B$4:$B$211,'Registrations'!$E$4:$E$211,S88)),S88) & " vs " & IFERROR(_xludf.XLOOKUP(T88,'Registrations'!#REF!,'Registrations'!#REF!,_xludf.XLOOKUP(T88,'Registrations'!$B$4:$B$211,'Registrations'!$E$4:$E$211,T88)),T88)) -> 0 vs 0 | I88: =_xlfn.TEXTBEFORE(H88," vs ") -> 0 | J88: =_xlfn.TEXTAFTER(H88," vs ") -> 0 | K88: =IF(Schedules[[#This Row],[Player 2]]="",Schedules[[#This Row],[Player 1]],Schedules[[#This Row],[Player 1]]&" / "&Schedules[[#This Row],[Player 2]]) -> 0 / 0 | L88: 15 | M88: =IF(L88=15,"WIN","LOST") -> WIN | P88: =IF(Schedules[[#This Row],[Player 4]]="",Schedules[[#This Row],[Player 3]],Schedules[[#This Row],[Player 3]]&" / "&Schedules[[#This Row],[Player 4]]) -> 0 | Q88: 10 | R88: =IF(Q88=15,"WIN","LOST") -> LOST | S88: =Input!C26 -> 0 | T88: =Input!D26 -> 0
A89: Int Men Doubles | B89: =B88 -> Adda | C89: =D88+TIME(0,3,0) -> 0.67916667 | D89: =C89+TIME(0,10,0) -> 0.68611111 | E89: Pre-Q | F89: 1 | G89: 1 vs 2 | H89: =IF(OR(S89="",T89=""),"",IFERROR(_xludf.XLOOKUP(S89,'Registrations'!#REF!,'Registrations'!#REF!,_xludf.XLOOKUP(S89,'Registrations'!$B$4:$B$211,'Registrations'!$E$4:$E$211,S89)),S89) & " vs " & IFERROR(_xludf.XLOOKUP(T89,'Registrations'!#REF!,'Registrations'!#REF!,_xludf.XLOOKUP(T89,'Registrations'!$B$4:$B$211,'Registrations'!$E$4:$E$211,T89)),T89)) -> 0 vs 0 | I89: =_xlfn.TEXTBEFORE(H89," vs ") -> 0 | J89: =_xlfn.TEXTAFTER(H89," vs ") -> 0 | K89: =IF(Schedules[[#This Row],[Player 2]]="",Schedules[[#This Row],[Player 1]],Schedules[[#This Row],[Player 1]]&" / "&Schedules[[#This Row],[Player 2]]) -> 0 / 0 | L89: 15 | M89: =IF(L89=15,"WIN","LOST") -> WIN | P89: =IF(Schedules[[#This Row],[Player 4]]="",Schedules[[#This Row],[Player 3]],Schedules[[#This Row],[Player 3]]&" / "&Schedules[[#This Row],[Player 4]]) -> 0 | Q89: 10 | R89: =IF(Q89=15,"WIN","LOST") -> LOST | S89: =Input!H25 -> 0 | T89: =Input!I25 -> 0
A90: Int Men Doubles | B90: =B89 -> Adda | C90: =C89 -> 0.67916667 | D90: =D89 -> 0.68611111 | E90: =E89 -> Pre-Q | F90: 2 | G90: =G89 -> 1 vs 2 | H90: =IF(OR(S90="",T90=""),"",IFERROR(_xludf.XLOOKUP(S90,'Registrations'!#REF!,'Registrations'!#REF!,_xludf.XLOOKUP(S90,'Registrations'!$B$4:$B$211,'Registrations'!$E$4:$E$211,S90)),S90) & " vs " & IFERROR(_xludf.XLOOKUP(T90,'Registrations'!#REF!,'Registrations'!#REF!,_xludf.XLOOKUP(T90,'Registrations'!$B$4:$B$211,'Registrations'!$E$4:$E$211,T90)),T90)) -> 0 vs 0 | I90: =_xlfn.TEXTBEFORE(H90," vs ") -> 0 | J90: =_xlfn.TEXTAFTER(H90," vs ") -> 0 | K90: =IF(Schedules[[#This Row],[Player 2]]="",Schedules[[#This Row],[Player 1]],Schedules[[#This Row],[Player 1]]&" / "&Schedules[[#This Row],[Player 2]]) -> 0 / 0 | L90: 15 | M90: =IF(L90=15,"WIN","LOST") -> WIN | P90: =IF(Schedules[[#This Row],[Player 4]]="",Schedules[[#This Row],[Player 3]],Schedules[[#This Row],[Player 3]]&" / "&Schedules[[#This Row],[Player 4]]) -> 0 | Q90: 10 | R90: =IF(Q90=15,"WIN","LOST") -> LOST | S90: =Input!H26 -> 0 | T90: =Input!I26 -> 0
A91: Int Men Doubles | B91: =B90 -> Adda | C91: =D90+TIME(0,3,0) -> 0.68819444 | D91: =C91+TIME(0,10,0) -> 0.69513889 | E91: Group | F91: 1 | G91: 3 | H91: =IF(OR(S91="",T91=""),"",IFERROR(_xludf.XLOOKUP(S91,'Registrations'!#REF!,'Registrations'!#REF!,_xludf.XLOOKUP(S91,'Registrations'!$B$4:$B$211,'Registrations'!$E$4:$E$211,S91)),S91) & " vs " & IFERROR(_xludf.XLOOKUP(T91,'Registrations'!#REF!,'Registrations'!#REF!,_xludf.XLOOKUP(T91,'Registrations'!$B$4:$B$211,'Registrations'!$E$4:$E$211,T91)),T91)) -> 0 vs 0 | I91: =_xlfn.TEXTBEFORE(H91," vs ") -> 0 | J91: =_xlfn.TEXTAFTER(H91," vs ") -> 0 | K91: =IF(Schedules[[#This Row],[Player 2]]="",Schedules[[#This Row],[Player 1]],Schedules[[#This Row],[Player 1]]&" / "&Schedules[[#This Row],[Player 2]]) -> 0 / 0 | L91: 15 | M91: =IF(L91=15,"WIN","LOST") -> WIN | P91: =IF(Schedules[[#This Row],[Player 4]]="",Schedules[[#This Row],[Player 3]],Schedules[[#This Row],[Player 3]]&" / "&Schedules[[#This Row],[Player 4]]) -> 0 | Q91: 10 | R91: =IF(Q91=15,"WIN","LOST") -> LOST | S91: =Input!B27 -> 0 | T91: =Input!C27 -> 0
A92: Int Men Doubles | B92: =B91 -> Adda | C92: =C91 -> 0.68819444 | D92: =D91 -> 0.69513889 | E92: =E91 -> Group | F92: 2 | G92: 4 | H92: =IF(OR(S92="",T92=""),"",IFERROR(_xludf.XLOOKUP(S92,'Registrations'!#REF!,'Registrations'!#REF!,_xludf.XLOOKUP(S92,'Registrations'!$B$4:$B$211,'Registrations'!$E$4:$E$211,S92)),S92) & " vs " & IFERROR(_xludf.XLOOKUP(T92,'Registrations'!#REF!,'Registrations'!#REF!,_xludf.XLOOKUP(T92,'Registrations'!$B$4:$B$211,'Registrations'!$E$4:$E$211,T92)),T92)) -> 0 vs 0 | I92: =_xlfn.TEXTBEFORE(H92," vs ") -> 0 | J92: =_xlfn.TEXTAFTER(H92," vs ") -> 0 | K92: =IF(Schedules[[#This Row],[Player 2]]="",Schedules[[#This Row],[Player 1]],Schedules[[#This Row],[Player 1]]&" / "&Schedules[[#This Row],[Player 2]]) -> 0 / 0 | L92: 15 | M92: =IF(L92=15,"WIN","LOST") -> WIN | P92: =IF(Schedules[[#This Row],[Player 4]]="",Schedules[[#This Row],[Player 3]],Schedules[[#This Row],[Player 3]]&" / "&Schedules[[#This Row],[Player 4]]) -> 0 | Q92: 10 | R92: =IF(Q92=15,"WIN","LOST") -> LOST | S92: =Input!B28 -> 0 | T92: =Input!C28 -> 0
A93: Int Men Doubles | B93: =B92 -> Adda | C93: =D92+TIME(0,3,0) -> 0.69722222 | D93: =C93+TIME(0,10,0) -> 0.70416667 | E93: =E92 -> Group | F93: =F91 -> 1 | G93: =G91 -> 3 | H93: =IF(OR(S93="",T93=""),"",IFERROR(_xludf.XLOOKUP(S93,'Registrations'!#REF!,'Registrations'!#REF!,_xludf.XLOOKUP(S93,'Registrations'!$B$4:$B$211,'Registrations'!$E$4:$E$211,S93)),S93) & " vs " & IFERROR(_xludf.XLOOKUP(T93,'Registrations'!#REF!,'Registrations'!#REF!,_xludf.XLOOKUP(T93,'Registrations'!$B$4:$B$211,'Registrations'!$E$4:$E$211,T93)),T93)) -> 0 vs 0 | I93: =_xlfn.TEXTBEFORE(H93," vs ") -> 0 | J93: =_xlfn.TEXTAFTER(H93," vs ") -> 0 | K93: =IF(Schedules[[#This Row],[Player 2]]="",Schedules[[#This Row],[Player 1]],Schedules[[#This Row],[Player 1]]&" / "&Schedules[[#This Row],[Player 2]]) -> 0 / 0 | L93: 15 | M93: =IF(L93=15,"WIN","LOST") -> WIN | P93: =IF(Schedules[[#This Row],[Player 4]]="",Schedules[[#This Row],[Player 3]],Schedules[[#This Row],[Player 3]]&" / "&Schedules[[#This Row],[Player 4]]) -> 0 | Q93: 10 | R93: =IF(Q93=15,"WIN","LOST") -> LOST | S93: =Input!D27 -> 0 | T93: =Input!E27 -> 0
A94: Int Men Doubles | B94: =B93 -> Adda | C94: =C93 -> 0.69722222 | D94: =D93 -> 0.70416667 | E94: =E93 -> Group | F94: =F92 -> 2 | G94: =G92 -> 4 | H94: =IF(OR(S94="",T94=""),"",IFERROR(_xludf.XLOOKUP(S94,'Registrations'!#REF!,'Registrations'!#REF!,_xludf.XLOOKUP(S94,'Registrations'!$B$4:$B$211,'Registrations'!$E$4:$E$211,S94)),S94) & " vs " & IFERROR(_xludf.XLOOKUP(T94,'Registrations'!#REF!,'Registrations'!#REF!,_xludf.XLOOKUP(T94,'Registrations'!$B$4:$B$211,'Registrations'!$E$4:$E$211,T94)),T94)) -> 0 vs 0 | I94: =_xlfn.TEXTBEFORE(H94," vs ") -> 0 | J94: =_xlfn.TEXTAFTER(H94," vs ") -> 0 | K94: =IF(Schedules[[#This Row],[Player 2]]="",Schedules[[#This Row],[Player 1]],Schedules[[#This Row],[Player 1]]&" / "&Schedules[[#This Row],[Player 2]]) -> 0 / 0 | L94: 15 | M94: =IF(L94=15,"WIN","LOST") -> WIN | P94: =IF(Schedules[[#This Row],[Player 4]]="",Schedules[[#This Row],[Player 3]],Schedules[[#This Row],[Player 3]]&" / "&Schedules[[#This Row],[Player 4]]) -> 0 | Q94: 10 | R94: =IF(Q94=15,"WIN","LOST") -> LOST | S94: =Input!D28 -> 0 | T94: =Input!E28 -> 0
A95: Int Men Doubles | B95: =B94 -> Adda | C95: =D94+TIME(0,3,0) -> 0.70625 | D95: =C95+TIME(0,10,0) -> 0.71319444 | E95: =E94 -> Group | F95: =F93 -> 1 | G95: =G93 -> 3 | H95: =IF(OR(S95="",T95=""),"",IFERROR(_xludf.XLOOKUP(S95,'Registrations'!#REF!,'Registrations'!#REF!,_xludf.XLOOKUP(S95,'Registrations'!$B$4:$B$211,'Registrations'!$E$4:$E$211,S95)),S95) & " vs " & IFERROR(_xludf.XLOOKUP(T95,'Registrations'!#REF!,'Registrations'!#REF!,_xludf.XLOOKUP(T95,'Registrations'!$B$4:$B$211,'Registrations'!$E$4:$E$211,T95)),T95)) -> 0 vs 0 | I95: =_xlfn.TEXTBEFORE(H95," vs ") -> 0 | J95: =_xlfn.TEXTAFTER(H95," vs ") -> 0 | K95: =IF(Schedules[[#This Row],[Player 2]]="",Schedules[[#This Row],[Player 1]],Schedules[[#This Row],[Player 1]]&" / "&Schedules[[#This Row],[Player 2]]) -> 0 / 0 | L95: 15 | M95: =IF(L95=15,"WIN","LOST") -> WIN | P95: =IF(Schedules[[#This Row],[Player 4]]="",Schedules[[#This Row],[Player 3]],Schedules[[#This Row],[Player 3]]&" / "&Schedules[[#This Row],[Player 4]]) -> 0 | Q95: 10 | R95: =IF(Q95=15,"WIN","LOST") -> LOST | S95: =Input!B27 -> 0 | T95: =Input!D27 -> 0
A96: Int Men Doubles | B96: =B95 -> Adda | C96: =C95 -> 0.70625 | D96: =D95 -> 0.71319444 | E96: =E95 -> Group | F96: =F94 -> 2 | G96: =G94 -> 4 | H96: =IF(OR(S96="",T96=""),"",IFERROR(_xludf.XLOOKUP(S96,'Registrations'!#REF!,'Registrations'!#REF!,_xludf.XLOOKUP(S96,'Registrations'!$B$4:$B$211,'Registrations'!$E$4:$E$211,S96)),S96) & " vs " & IFERROR(_xludf.XLOOKUP(T96,'Registrations'!#REF!,'Registrations'!#REF!,_xludf.XLOOKUP(T96,'Registrations'!$B$4:$B$211,'Registrations'!$E$4:$E$211,T96)),T96)) -> 0 vs 0 | I96: =_xlfn.TEXTBEFORE(H96," vs ") -> 0 | J96: =_xlfn.TEXTAFTER(H96," vs ") -> 0 | K96: =IF(Schedules[[#This Row],[Player 2]]="",Schedules[[#This Row],[Player 1]],Schedules[[#This Row],[Player 1]]&" / "&Schedules[[#This Row],[Player 2]]) -> 0 / 0 | L96: 15 | M96: =IF(L96=15,"WIN","LOST") -> WIN | P96: =IF(Schedules[[#This Row],[Player 4]]="",Schedules[[#This Row],[Player 3]],Schedules[[#This Row],[Player 3]]&" / "&Schedules[[#This Row],[Player 4]]) -> 0 | Q96: 10 | R96: =IF(Q96=15,"WIN","LOST") -> LOST | S96: =Input!B28 -> 0 | T96: =Input!D28 -> 0
A97: Int Men Doubles | B97: =B96 -> Adda | C97: =D96+TIME(0,3,0) -> 0.71527778 | D97: =C97+TIME(0,10,0) -> 0.72222222 | E97: =E96 -> Group | F97: =F95 -> 1 | G97: =G95 -> 3 | H97: =IF(OR(S97="",T97=""),"",IFERROR(_xludf.XLOOKUP(S97,'Registrations'!#REF!,'Registrations'!#REF!,_xludf.XLOOKUP(S97,'Registrations'!$B$4:$B$211,'Registrations'!$E$4:$E$211,S97)),S97) & " vs " & IFERROR(_xludf.XLOOKUP(T97,'Registrations'!#REF!,'Registrations'!#REF!,_xludf.XLOOKUP(T97,'Registrations'!$B$4:$B$211,'Registrations'!$E$4:$E$211,T97)),T97)) -> 0 vs 0 | I97: =_xlfn.TEXTBEFORE(H97," vs ") -> 0 | J97: =_xlfn.TEXTAFTER(H97," vs ") -> 0 | K97: =IF(Schedules[[#This Row],[Player 2]]="",Schedules[[#This Row],[Player 1]],Schedules[[#This Row],[Player 1]]&" / "&Schedules[[#This Row],[Player 2]]) -> 0 / 0 | L97: 15 | M97: =IF(L97=15,"WIN","LOST") -> WIN | P97: =IF(Schedules[[#This Row],[Player 4]]="",Schedules[[#This Row],[Player 3]],Schedules[[#This Row],[Player 3]]&" / "&Schedules[[#This Row],[Player 4]]) -> 0 | Q97: 10 | R97: =IF(Q97=15,"WIN","LOST") -> LOST | S97: =Input!C27 -> 0 | T97: =Input!E27 -> 0
A98: Int Men Doubles | B98: =B97 -> Adda | C98: =C97 -> 0.71527778 | D98: =D97 -> 0.72222222 | E98: =E97 -> Group | F98: =F96 -> 2 | G98: =G96 -> 4 | H98: =IF(OR(S98="",T98=""),"",IFERROR(_xludf.XLOOKUP(S98,'Registrations'!#REF!,'Registrations'!#REF!,_xludf.XLOOKUP(S98,'Registrations'!$B$4:$B$211,'Registrations'!$E$4:$E$211,S98)),S98) & " vs " & IFERROR(_xludf.XLOOKUP(T98,'Registrations'!#REF!,'Registrations'!#REF!,_xludf.XLOOKUP(T98,'Registrations'!$B$4:$B$211,'Registrations'!$E$4:$E$211,T98)),T98)) -> 0 vs 0 | I98: =_xlfn.TEXTBEFORE(H98," vs ") -> 0 | J98: =_xlfn.TEXTAFTER(H98," vs ") -> 0 | K98: =IF(Schedules[[#This Row],[Player 2]]="",Schedules[[#This Row],[Player 1]],Schedules[[#This Row],[Player 1]]&" / "&Schedules[[#This Row],[Player 2]]) -> 0 / 0 | L98: 15 | M98: =IF(L98=15,"WIN","LOST") -> WIN | P98: =IF(Schedules[[#This Row],[Player 4]]="",Schedules[[#This Row],[Player 3]],Schedules[[#This Row],[Player 3]]&" / "&Schedules[[#This Row],[Player 4]]) -> 0 | Q98: 10 | R98: =IF(Q98=15,"WIN","LOST") -> LOST | S98: =Input!C28 -> 0 | T98: =Input!E28 -> 0
A99: Int Men Doubles | B99: =B98 -> Adda | C99: =D98+TIME(0,3,0) -> 0.72430556 | D99: =C99+TIME(0,10,0) -> 0.73125 | E99: =E98 -> Group | F99: =F97 -> 1 | G99: =G97 -> 3 | H99: =IF(OR(S99="",T99=""),"",IFERROR(_xludf.XLOOKUP(S99,'Registrations'!#REF!,'Registrations'!#REF!,_xludf.XLOOKUP(S99,'Registrations'!$B$4:$B$211,'Registrations'!$E$4:$E$211,S99)),S99) & " vs " & IFERROR(_xludf.XLOOKUP(T99,'Registrations'!#REF!,'Registrations'!#REF!,_xludf.XLOOKUP(T99,'Registrations'!$B$4:$B$211,'Registrations'!$E$4:$E$211,T99)),T99)) -> 0 vs 0 | I99: =_xlfn.TEXTBEFORE(H99," vs ") -> 0 | J99: =_xlfn.TEXTAFTER(H99," vs ") -> 0 | K99: =IF(Schedules[[#This Row],[Player 2]]="",Schedules[[#This Row],[Player 1]],Schedules[[#This Row],[Player 1]]&" / "&Schedules[[#This Row],[Player 2]]) -> 0 / 0 | L99: 15 | M99: =IF(L99=15,"WIN","LOST") -> WIN | P99: =IF(Schedules[[#This Row],[Player 4]]="",Schedules[[#This Row],[Player 3]],Schedules[[#This Row],[Player 3]]&" / "&Schedules[[#This Row],[Player 4]]) -> 0 | Q99: 10 | R99: =IF(Q99=15,"WIN","LOST") -> LOST | S99: =Input!B27 -> 0 | T99: =Input!E27 -> 0
A100: Int Men Doubles | B100: =B99 -> Adda | C100: =C99 -> 0.72430556 | D100: =D99 -> 0.73125 | E100: =E99 -> Group | F100: =F98 -> 2 | G100: =G98 -> 4 | H100: =IF(OR(S100="",T100=""),"",IFERROR(_xludf.XLOOKUP(S100,'Registrations'!#REF!,'Registrations'!#REF!,_xludf.XLOOKUP(S100,'Registrations'!$B$4:$B$211,'Registrations'!$E$4:$E$211,S100)),S100) & " vs " & IFERROR(_xludf.XLOOKUP(T100,'Registrations'!#REF!,'Registrations'!#REF!,_xludf.XLOOKUP(T100,'Registrations'!$B$4:$B$211,'Registrations'!$E$4:$E$211,T100)),T100)) -> 0 vs 0 | I100: =_xlfn.TEXTBEFORE(H100," vs ") -> 0 | J100: =_xlfn.TEXTAFTER(H100," vs ") -> 0 | K100: =IF(Schedules[[#This Row],[Player 2]]="",Schedules[[#This Row],[Player 1]],Schedules[[#This Row],[Player 1]]&" / "&Schedules[[#This Row],[Player 2]]) -> 0 / 0 | L100: 15 | M100: =IF(L100=15,"WIN","LOST") -> WIN | P100: =IF(Schedules[[#This Row],[Player 4]]="",Schedules[[#This Row],[Player 3]],Schedules[[#This Row],[Player 3]]&" / "&Schedules[[#This Row],[Player 4]]) -> 0 | Q100: 10 | R100: =IF(Q100=15,"WIN","LOST") -> LOST | S100: =Input!B28 -> 0 | T100: =Input!E28 -> 0
...

Sheet PnL
A1: Court Mafia 2.0 - Financial Model
A3: Details | B3: Open Men Singles | C3: Open Veteran Doubles | D3: 45+ Split Doubles | E3: Beginner Men's Doubles | F3: Beginner Mx Doubles | G3: Int Men Doubles | H3: Open Mx Doubles | I3: Adv Men Doubles
A4: No of players | B4: 24 | C4: 0 | D4: 0 | E4: 0 | F4: 0 | G4: 0
A5: No of teams | B5: 0 | C5: 12 | D5: 28 | E5: 24 | F5: 20 | G5: 32 | H5: 28 | I5: 24
A6: Entry fee | B6: 800 | C6: 1600 | D6: 1600 | E6: =D6 -> 1600 | F6: =E6 -> 1600 | G6: =F6 -> 1600 | H6: =G6 -> 1600 | I6: =H6 -> 1600
A7: Fee income | B7: =(B6*B4)+(B6*B5) -> 19200 | C7: =(C6*C4)+(C6*C5) -> 19200 | D7: =(D6*D4)+(D6*D5) -> 44800 | E7: =(E6*E4)+(E6*E5) -> 38400 | F7: =(F6*F4)+(F6*F5) -> 32000 | G7: =(G6*G4)+(G6*G5) -> 51200 | H7: =(H6*H4)+(H6*H5) -> 44800 | I7: =(I6*I4)+(I6*I5) -> 38400
A9: Particulars | B9: Amt (in Rs)
A10: Income:
A11: Entry fees | B11: =SUM(B7:I7) -> 288000
A12: Sponsorship | B12: 30000
A13: Stall rentals | B13: =B14*B15 -> 25000
A14: -No of stalls | B14: 5
A15: -Rent/stall | B15: 5000
A16: Total Income | B16: =SUM(B11:B13) -> 343000
A17: Expense:
A18: Prize pool | B18: 100000
A19: Court charges | B19: =SUM(I32:I37) -> 22800
A20: Balls | B20: =(120*15)+(155*15) -> 4125
A21: Referee | B21: =B22*B23*B24 -> 14400
A22: -No of days | B22: 4
A23: -Per day fee | B23: 1200
A24: -Total referees | B24: 3
A25: Misc | B25: 60000
A26: Total Expense | B26: =SUM(B18:B20,B21,B25) -> 201325
A27: Net Profit | B27: =B16-B26 -> 141675
A30: Court Charges
A31: Day | B31: Venue | C31: Category to be played | D31: Courts | E31: Matches | F31: Slot (min) | G31: Actual Hours | H31: Court/hr | I31: Court cost
A32: 5th April | B32: Gawand Baug | C32: Open Mens Singles | D32: 3 | E32: 48 | F32: 10 | G32: 3 | H32: 400 | I32: =H32*D32*G32 -> 3600
A33: =A32 -> 5th April | B33: =B32 -> Gawand Baug | C33: Open Veteran Doubles | D33: 3 | E33: 21 | F33: 13 | G33: 1 | H33: 400 | I33: =H33*D33*G33 -> 1200
A34: =A33 -> 5th April | B34: =B33 -> Gawand Baug | C34: 45+ Split Doubles | D34: 3 | E34: 31 | F34: 10 | G34: 2 | H34: 400 | I34: =H34*D34*G34 -> 2400
A35: Saturday | B35: Pickle Adda | C35: MXD | D35: 2 | E35: 63 | F35: 13 | G35: 7 | H35: 400 | I35: =H35*D35*G35 -> 5600
A36: Sunday | B36: Pickle Adda | C36: SD | D36: 2 | E36: 48 | F36: 13 | G36: 5.5 | H36: 400 | I36: =H36*D36*G36 -> 4400
A37: Sunday | B37: Pickle Adda | C37: MD | D37: 2 | E37: 63 | F37: 13 | G37: 7 | H37: 400 | I37: =H37*D37*G37 -> 5600

Sheet Scorecard
A1: OPEN MEN'S SINGLES
A3: Category | B3: Teams | C3: Standing | D3: Points | E3: Matches Played | F3: Wins | G3: Win % | H3: Total Score | I3: Conceded Score | J3: Concession ratio %
A4: ='Registrations'!A4 -> Open Men Singles | B4: ='Registrations'!E4 -> Sanjay Gatti | C4: =_xlfn.RANK.EQ(OpenSingles[[#This Row],[Points]],OpenSingles[Points],0)+COUNTIFS(OpenSingles[Points],OpenSingles[[#This Row],[Points]],OpenSingles[Concession ratio %],"<"&OpenSingles[[#This Row],[Concession ratio %]])+COUNTIFS(OpenSingles[Points],OpenSingles[[#This Row],[Points]],OpenSingles[Concession ratio %],OpenSingles[[#This Row],[Concession ratio %]],OpenSingles[Teams],"<"&OpenSingles[[#This Row],[Teams]]) -> 24 | D4: =OpenSingles[[#This Row],[Wins]]*3 -> 18 | E4: =COUNTIF(Schedules[Team 1 Name], B4) + COUNTIF(Schedules[Team 2 Name], B4) -> 6 | F4: =COUNTIFS(Schedules[Team 1 Name], B4, Schedules[Team 1 Outcome], "Win") + COUNTIFS(Schedules[Team 2 Name], B4, Schedules[Team 2 Outcome], "Win") -> 6 | G4: =IFERROR(OpenSingles[[#This Row],[Wins]]/OpenSingles[[#This Row],[Matches Played]],0%) -> 1 | H4: =SUMIFS(Schedules[Team 1 Score],Schedules[Team 1 Name],B4)+SUMIFS(Schedules[Team 2 Score],Schedules[Team 2 Name],B4) -> 90 | I4: =SUMIFS(Schedules[Team 2 Score],Schedules[Team 1 Name],B4)+SUMIFS(Schedules[Team 1 Score],Schedules[Team 2 Name],B4) -> 60 | J4: =IFERROR(OpenSingles[[#This Row],[Conceded Score]]/OpenSingles[[#This Row],[Total Score]],0%) -> 0.66666667
A5: ='Registrations'!A5 -> Open Men Singles | B5: ='Registrations'!E5 -> 0 | C5: =_xlfn.RANK.EQ(OpenSingles[[#This Row],[Points]],OpenSingles[Points],0)+COUNTIFS(OpenSingles[Points],OpenSingles[[#This Row],[Points]],OpenSingles[Concession ratio %],"<"&OpenSingles[[#This Row],[Concession ratio %]])+COUNTIFS(OpenSingles[Points],OpenSingles[[#This Row],[Points]],OpenSingles[Concession ratio %],OpenSingles[[#This Row],[Concession ratio %]],OpenSingles[Teams],"<"&OpenSingles[[#This Row],[Teams]]) -> 1 | D5: =OpenSingles[[#This Row],[Wins]]*3 -> 987 | E5: =COUNTIF(Schedules[Team 1 Name], B5) + COUNTIF(Schedules[Team 2 Name], B5) -> 756 | F5: =COUNTIFS(Schedules[Team 1 Name], B5, Schedules[Team 1 Outcome], "Win") + COUNTIFS(Schedules[Team 2 Name], B5, Schedules[Team 2 Outcome], "Win") -> 329 | G5: =IFERROR(OpenSingles[[#This Row],[Wins]]/OpenSingles[[#This Row],[Matches Played]],0%) -> 0.43518519 | H5: =SUMIFS(Schedules[Team 1 Score],Schedules[Team 1 Name],B5)+SUMIFS(Schedules[Team 2 Score],Schedules[Team 2 Name],B5) -> 9145 | I5: =SUMIFS(Schedules[Team 2 Score],Schedules[Team 1 Name],B5)+SUMIFS(Schedules[Team 1 Score],Schedules[Team 2 Name],B5) -> 9605 | J5: =IFERROR(OpenSingles[[#This Row],[Conceded Score]]/OpenSingles[[#This Row],[Total Score]],0%) -> 1.0503007
A6: ='Registrations'!A6 -> Open Men Singles | B6: ='Registrations'!E6 -> 0 | C6: =_xlfn.RANK.EQ(OpenSingles[[#This Row],[Points]],OpenSingles[Points],0)+COUNTIFS(OpenSingles[Points],OpenSingles[[#This Row],[Points]],OpenSingles[Concession ratio %],"<"&OpenSingles[[#This Row],[Concession ratio %]])+COUNTIFS(OpenSingles[Points],OpenSingles[[#This Row],[Points]],OpenSingles[Concession ratio %],OpenSingles[[#This Row],[Concession ratio %]],OpenSingles[Teams],"<"&OpenSingles[[#This Row],[Teams]]) -> 1 | D6: =OpenSingles[[#This Row],[Wins]]*3 -> 987 | E6: =COUNTIF(Schedules[Team 1 Name], B6) + COUNTIF(Schedules[Team 2 Name], B6) -> 756 | F6: =COUNTIFS(Schedules[Team 1 Name], B6, Schedules[Team 1 Outcome], "Win") + COUNTIFS(Schedules[Team 2 Name], B6, Schedules[Team 2 Outcome], "Win") -> 329 | G6: =IFERROR(OpenSingles[[#This Row],[Wins]]/OpenSingles[[#This Row],[Matches Played]],0%) -> 0.43518519 | H6: =SUMIFS(Schedules[Team 1 Score],Schedules[Team 1 Name],B6)+SUMIFS(Schedules[Team 2 Score],Schedules[Team 2 Name],B6) -> 9145 | I6: =SUMIFS(Schedules[Team 2 Score],Schedules[Team 1 Name],B6)+SUMIFS(Schedules[Team 1 Score],Schedules[Team 2 Name],B6) -> 9605 | J6: =IFERROR(OpenSingles[[#This Row],[Conceded Score]]/OpenSingles[[#This Row],[Total Score]],0%) -> 1.0503007
A7: ='Registrations'!A7 -> Open Men Singles | B7: ='Registrations'!E7 -> 0 | C7: =_xlfn.RANK.EQ(OpenSingles[[#This Row],[Points]],OpenSingles[Points],0)+COUNTIFS(OpenSingles[Points],OpenSingles[[#This Row],[Points]],OpenSingles[Concession ratio %],"<"&OpenSingles[[#This Row],[Concession ratio %]])+COUNTIFS(OpenSingles[Points],OpenSingles[[#This Row],[Points]],OpenSingles[Concession ratio %],OpenSingles[[#This Row],[Concession ratio %]],OpenSingles[Teams],"<"&OpenSingles[[#This Row],[Teams]]) -> 1 | D7: =OpenSingles[[#This Row],[Wins]]*3 -> 987 | E7: =COUNTIF(Schedules[Team 1 Name], B7) + COUNTIF(Schedules[Team 2 Name], B7) -> 756 | F7: =COUNTIFS(Schedules[Team 1 Name], B7, Schedules[Team 1 Outcome], "Win") + COUNTIFS(Schedules[Team 2 Name], B7, Schedules[Team 2 Outcome], "Win") -> 329 | G7: =IFERROR(OpenSingles[[#This Row],[Wins]]/OpenSingles[[#This Row],[Matches Played]],0%) -> 0.43518519 | H7: =SUMIFS(Schedules[Team 1 Score],Schedules[Team 1 Name],B7)+SUMIFS(Schedules[Team 2 Score],Schedules[Team 2 Name],B7) -> 9145 | I7: =SUMIFS(Schedules[Team 2 Score],Schedules[Team 1 Name],B7)+SUMIFS(Schedules[Team 1 Score],Schedules[Team 2 Name],B7) -> 9605 | J7: =IFERROR(OpenSingles[[#This Row],[Conceded Score]]/OpenSingles[[#This Row],[Total Score]],0%) -> 1.0503007
A8: ='Registrations'!A8 -> Open Men Singles | B8: ='Registrations'!E8 -> 0 | C8: =_xlfn.RANK.EQ(OpenSingles[[#This Row],[Points]],OpenSingles[Points],0)+COUNTIFS(OpenSingles[Points],OpenSingles[[#This Row],[Points]],OpenSingles[Concession ratio %],"<"&OpenSingles[[#This Row],[Concession ratio %]])+COUNTIFS(OpenSingles[Points],OpenSingles[[#This Row],[Points]],OpenSingles[Concession ratio %],OpenSingles[[#This Row],[Concession ratio %]],OpenSingles[Teams],"<"&OpenSingles[[#This Row],[Teams]]) -> 1 | D8: =OpenSingles[[#This Row],[Wins]]*3 -> 987 | E8: =COUNTIF(Schedules[Team 1 Name], B8) + COUNTIF(Schedules[Team 2 Name], B8) -> 756 | F8: =COUNTIFS(Schedules[Team 1 Name], B8, Schedules[Team 1 Outcome], "Win") + COUNTIFS(Schedules[Team 2 Name], B8, Schedules[Team 2 Outcome], "Win") -> 329 | G8: =IFERROR(OpenSingles[[#This Row],[Wins]]/OpenSingles[[#This Row],[Matches Played]],0%) -> 0.43518519 | H8: =SUMIFS(Schedules[Team 1 Score],Schedules[Team 1 Name],B8)+SUMIFS(Schedules[Team 2 Score],Schedules[Team 2 Name],B8) -> 9145 | I8: =SUMIFS(Schedules[Team 2 Score],Schedules[Team 1 Name],B8)+SUMIFS(Schedules[Team 1 Score],Schedules[Team 2 Name],B8) -> 9605 | J8: =IFERROR(OpenSingles[[#This Row],[Conceded Score]]/OpenSingles[[#This Row],[Total Score]],0%) -> 1.0503007
A9: ='Registrations'!A9 -> Open Men Singles | B9: ='Registrations'!E9 -> 0 | C9: =_xlfn.RANK.EQ(OpenSingles[[#This Row],[Points]],OpenSingles[Points],0)+COUNTIFS(OpenSingles[Points],OpenSingles[[#This Row],[Points]],OpenSingles[Concession ratio %],"<"&OpenSingles[[#This Row],[Concession ratio %]])+COUNTIFS(OpenSingles[Points],OpenSingles[[#This Row],[Points]],OpenSingles[Concession ratio %],OpenSingles[[#This Row],[Concession ratio %]],OpenSingles[Teams],"<"&OpenSingles[[#This Row],[Teams]]) -> 1 | D9: =OpenSingles[[#This Row],[Wins]]*3 -> 987 | E9: =COUNTIF(Schedules[Team 1 Name], B9) + COUNTIF(Schedules[Team 2 Name], B9) -> 756 | F9: =COUNTIFS(Schedules[Team 1 Name], B9, Schedules[Team 1 Outcome], "Win") + COUNTIFS(Schedules[Team 2 Name], B9, Schedules[Team 2 Outcome], "Win") -> 329 | G9: =IFERROR(OpenSingles[[#This Row],[Wins]]/OpenSingles[[#This Row],[Matches Played]],0%) -> 0.43518519 | H9: =SUMIFS(Schedules[Team 1 Score],Schedules[Team 1 Name],B9)+SUMIFS(Schedules[Team 2 Score],Schedules[Team 2 Name],B9) -> 9145 | I9: =SUMIFS(Schedules[Team 2 Score],Schedules[Team 1 Name],B9)+SUMIFS(Schedules[Team 1 Score],Schedules[Team 2 Name],B9) -> 9605 | J9: =IFERROR(OpenSingles[[#This Row],[Conceded Score]]/OpenSingles[[#This Row],[Total Score]],0%) -> 1.0503007
A10: ='Registrations'!A10 -> Open Men Singles | B10: ='Registrations'!E10 -> 0 | C10: =_xlfn.RANK.EQ(OpenSingles[[#This Row],[Points]],OpenSingles[Points],0)+COUNTIFS(OpenSingles[Points],OpenSingles[[#This Row],[Points]],OpenSingles[Concession ratio %],"<"&OpenSingles[[#This Row],[Concession ratio %]])+COUNTIFS(OpenSingles[Points],OpenSingles[[#This Row],[Points]],OpenSingles[Concession ratio %],OpenSingles[[#This Row],[Concession ratio %]],OpenSingles[Teams],"<"&OpenSingles[[#This Row],[Teams]]) -> 1 | D10: =OpenSingles[[#This Row],[Wins]]*3 -> 987 | E10: =COUNTIF(Schedules[Team 1 Name], B10) + COUNTIF(Schedules[Team 2 Name], B10) -> 756 | F10: =COUNTIFS(Schedules[Team 1 Name], B10, Schedules[Team 1 Outcome], "Win") + COUNTIFS(Schedules[Team 2 Name], B10, Schedules[Team 2 Outcome], "Win") -> 329 | G10: =IFERROR(OpenSingles[[#This Row],[Wins]]/OpenSingles[[#This Row],[Matches Played]],0%) -> 0.43518519 | H10: =SUMIFS(Schedules[Team 1 Score],Schedules[Team 1 Name],B10)+SUMIFS(Schedules[Team 2 Score],Schedules[Team 2 Name],B10) -> 9145 | I10: =SUMIFS(Schedules[Team 2 Score],Schedules[Team 1 Name],B10)+SUMIFS(Schedules[Team 1 Score],Schedules[Team 2 Name],B10) -> 9605 | J10: =IFERROR(OpenSingles[[#This Row],[Conceded Score]]/OpenSingles[[#This Row],[Total Score]],0%) -> 1.0503007
A11: ='Registrations'!A11 -> Open Men Singles | B11: ='Registrations'!E11 -> 0 | C11: =_xlfn.RANK.EQ(OpenSingles[[#This Row],[Points]],OpenSingles[Points],0)+COUNTIFS(OpenSingles[Points],OpenSingles[[#This Row],[Points]],OpenSingles[Concession ratio %],"<"&OpenSingles[[#This Row],[Concession ratio %]])+COUNTIFS(OpenSingles[Points],OpenSingles[[#This Row],[Points]],OpenSingles[Concession ratio %],OpenSingles[[#This Row],[Concession ratio %]],OpenSingles[Teams],"<"&OpenSingles[[#This Row],[Teams]]) -> 1 | D11: =OpenSingles[[#This Row],[Wins]]*3 -> 987 | E11: =COUNTIF(Schedules[Team 1 Name], B11) + COUNTIF(Schedules[Team 2 Name], B11) -> 756 | F11: =COUNTIFS(Schedules[Team 1 Name], B11, Schedules[Team 1 Outcome], "Win") + COUNTIFS(Schedules[Team 2 Name], B11, Schedules[Team 2 Outcome], "Win") -> 329 | G11: =IFERROR(OpenSingles[[#This Row],[Wins]]/OpenSingles[[#This Row],[Matches Played]],0%) -> 0.43518519 | H11: =SUMIFS(Schedules[Team 1 Score],Schedules[Team 1 Name],B11)+SUMIFS(Schedules[Team 2 Score],Schedules[Team 2 Name],B11) -> 9145 | I11: =SUMIFS(Schedules[Team 2 Score],Schedules[Team 1 Name],B11)+SUMIFS(Schedules[Team 1 Score],Schedules[Team 2 Name],B11) -> 9605 | J11: =IFERROR(OpenSingles[[#This Row],[Conceded Score]]/OpenSingles[[#This Row],[Total Score]],0%) -> 1.0503007
A12: ='Registrations'!A12 -> Open Men Singles | B12: ='Registrations'!E12 -> 0 | C12: =_xlfn.RANK.EQ(OpenSingles[[#This Row],[Points]],OpenSingles[Points],0)+COUNTIFS(OpenSingles[Points],OpenSingles[[#This Row],[Points]],OpenSingles[Concession ratio %],"<"&OpenSingles[[#This Row],[Concession ratio %]])+COUNTIFS(OpenSingles[Points],OpenSingles[[#This Row],[Points]],OpenSingles[Concession ratio %],OpenSingles[[#This Row],[Concession ratio %]],OpenSingles[Teams],"<"&OpenSingles[[#This Row],[Teams]]) -> 1 | D12: =OpenSingles[[#This Row],[Wins]]*3 -> 987 | E12: =COUNTIF(Schedules[Team 1 Name], B12) + COUNTIF(Schedules[Team 2 Name], B12) -> 756 | F12: =COUNTIFS(Schedules[Team 1 Name], B12, Schedules[Team 1 Outcome], "Win") + COUNTIFS(Schedules[Team 2 Name], B12, Schedules[Team 2 Outcome], "Win") -> 329 | G12: =IFERROR(OpenSingles[[#This Row],[Wins]]/OpenSingles[[#This Row],[Matches Played]],0%) -> 0.43518519 | H12: =SUMIFS(Schedules[Team 1 Score],Schedules[Team 1 Name],B12)+SUMIFS(Schedules[Team 2 Score],Schedules[Team 2 Name],B12) -> 9145 | I12: =SUMIFS(Schedules[Team 2 Score],Schedules[Team 1 Name],B12)+SUMIFS(Schedules[Team 1 Score],Schedules[Team 2 Name],B12) -> 9605 | J12: =IFERROR(OpenSingles[[#This Row],[Conceded Score]]/OpenSingles[[#This Row],[Total Score]],0%) -> 1.0503007
A13: ='Registrations'!A13 -> Open Men Singles | B13: ='Registrations'!E13 -> 0 | C13: =_xlfn.RANK.EQ(OpenSingles[[#This Row],[Points]],OpenSingles[Points],0)+COUNTIFS(OpenSingles[Points],OpenSingles[[#This Row],[Points]],OpenSingles[Concession ratio %],"<"&OpenSingles[[#This Row],[Concession ratio %]])+COUNTIFS(OpenSingles[Points],OpenSingles[[#This Row],[Points]],OpenSingles[Concession ratio %],OpenSingles[[#This Row],[Concession ratio %]],OpenSingles[Teams],"<"&OpenSingles[[#This Row],[Teams]]) -> 1 | D13: =OpenSingles[[#This Row],[Wins]]*3 -> 987 | E13: =COUNTIF(Schedules[Team 1 Name], B13) + COUNTIF(Schedules[Team 2 Name], B13) -> 756 | F13: =COUNTIFS(Schedules[Team 1 Name], B13, Schedules[Team 1 Outcome], "Win") + COUNTIFS(Schedules[Team 2 Name], B13, Schedules[Team 2 Outcome], "Win") -> 329 | G13: =IFERROR(OpenSingles[[#This Row],[Wins]]/OpenSingles[[#This Row],[Matches Played]],0%) -> 0.43518519 | H13: =SUMIFS(Schedules[Team 1 Score],Schedules[Team 1 Name],B13)+SUMIFS(Schedules[Team 2 Score],Schedules[Team 2 Name],B13) -> 9145 | I13: =SUMIFS(Schedules[Team 2 Score],Schedules[Team 1 Name],B13)+SUMIFS(Schedules[Team 1 Score],Schedules[Team 2 Name],B13) -> 9605 | J13: =IFERROR(OpenSingles[[#This Row],[Conceded Score]]/OpenSingles[[#This Row],[Total Score]],0%) -> 1.0503007
A14: ='Registrations'!A14 -> Open Men Singles | B14: ='Registrations'!E14 -> 0 | C14: =_xlfn.RANK.EQ(OpenSingles[[#This Row],[Points]],OpenSingles[Points],0)+COUNTIFS(OpenSingles[Points],OpenSingles[[#This Row],[Points]],OpenSingles[Concession ratio %],"<"&OpenSingles[[#This Row],[Concession ratio %]])+COUNTIFS(OpenSingles[Points],OpenSingles[[#This Row],[Points]],OpenSingles[Concession ratio %],OpenSingles[[#This Row],[Concession ratio %]],OpenSingles[Teams],"<"&OpenSingles[[#This Row],[Teams]]) -> 1 | D14: =OpenSingles[[#This Row],[Wins]]*3 -> 987 | E14: =COUNTIF(Schedules[Team 1 Name], B14) + COUNTIF(Schedules[Team 2 Name], B14) -> 756 | F14: =COUNTIFS(Schedules[Team 1 Name], B14, Schedules[Team 1 Outcome], "Win") + COUNTIFS(Schedules[Team 2 Name], B14, Schedules[Team 2 Outcome], "Win") -> 329 | G14: =IFERROR(OpenSingles[[#This Row],[Wins]]/OpenSingles[[#This Row],[Matches Played]],0%) -> 0.43518519 | H14: =SUMIFS(Schedules[Team 1 Score],Schedules[Team 1 Name],B14)+SUMIFS(Schedules[Team 2 Score],Schedules[Team 2 Name],B14) -> 9145 | I14: =SUMIFS(Schedules[Team 2 Score],Schedules[Team 1 Name],B14)+SUMIFS(Schedules[Team 1 Score],Schedules[Team 2 Name],B14) -> 9605 | J14: =IFERROR(OpenSingles[[#This Row],[Conceded Score]]/OpenSingles[[#This Row],[Total Score]],0%) -> 1.0503007
A15: ='Registrations'!A15 -> Open Men Singles | B15: ='Registrations'!E15 -> 0 | C15: =_xlfn.RANK.EQ(OpenSingles[[#This Row],[Points]],OpenSingles[Points],0)+COUNTIFS(OpenSingles[Points],OpenSingles[[#This Row],[Points]],OpenSingles[Concession ratio %],"<"&OpenSingles[[#This Row],[Concession ratio %]])+COUNTIFS(OpenSingles[Points],OpenSingles[[#This Row],[Points]],OpenSingles[Concession ratio %],OpenSingles[[#This Row],[Concession ratio %]],OpenSingles[Teams],"<"&OpenSingles[[#This Row],[Teams]]) -> 1 | D15: =OpenSingles[[#This Row],[Wins]]*3 -> 987 | E15: =COUNTIF(Schedules[Team 1 Name], B15) + COUNTIF(Schedules[Team 2 Name], B15) -> 756 | F15: =COUNTIFS(Schedules[Team 1 Name], B15, Schedules[Team 1 Outcome], "Win") + COUNTIFS(Schedules[Team 2 Name], B15, Schedules[Team 2 Outcome], "Win") -> 329 | G15: =IFERROR(OpenSingles[[#This Row],[Wins]]/OpenSingles[[#This Row],[Matches Played]],0%) -> 0.43518519 | H15: =SUMIFS(Schedules[Team 1 Score],Schedules[Team 1 Name],B15)+SUMIFS(Schedules[Team 2 Score],Schedules[Team 2 Name],B15) -> 9145 | I15: =SUMIFS(Schedules[Team 2 Score],Schedules[Team 1 Name],B15)+SUMIFS(Schedules[Team 1 Score],Schedules[Team 2 Name],B15) -> 9605 | J15: =IFERROR(OpenSingles[[#This Row],[Conceded Score]]/OpenSingles[[#This Row],[Total Score]],0%) -> 1.0503007
... A27: ='Registrations'!A27 -> Open Men Singles | B27: ='Registrations'!E27 -> 0 | C27: =_xlfn.RANK.EQ(OpenSingles[[#This Row],[Points]],OpenSingles[Points],0)+COUNTIFS(OpenSingles[Points],OpenSingles[[#This Row],[Points]],OpenSingles[Concession ratio %],"<"&OpenSingles[[#This Row],[Concession ratio %]])+COUNTIFS(OpenSingles[Points],OpenSingles[[#This Row],[Points]],OpenSingles[Concession ratio %],OpenSingles[[#This Row],[Concession ratio %]],OpenSingles[Teams],"<"&OpenSingles[[#This Row],[Teams]]) -> 1 | D27: =OpenSingles[[#This Row],[Wins]]*3 -> 987 | E27: =COUNTIF(Schedules[Team 1 Name], B27) + COUNTIF(Schedules[Team 2 Name], B27) -> 756 | F27: =COUNTIFS(Schedules[Team 1 Name], B27, Schedules[Team 1 Outcome], "Win") + COUNTIFS(Schedules[Team 2 Name], B27, Schedules[Team 2 Outcome], "Win") -> 329 | G27: =IFERROR(OpenSingles[[#This Row],[Wins]]/OpenSingles[[#This Row],[Matches Played]],0%) -> 0.43518519 | H27: =SUMIFS(Schedules[Team 1 Score],Schedules[Team 1 Name],B27)+SUMIFS(Schedules[Team 2 Score],Schedules[Team 2 Name],B27) -> 9145 | I27: =SUMIFS(Schedules[Team 2 Score],Schedules[Team 1 Name],B27)+SUMIFS(Schedules[Team 1 Score],Schedules[Team 2 Name],B27) -> 9605 | J27: =IFERROR(OpenSingles[[#This Row],[Conceded Score]]/OpenSingles[[#This Row],[Total Score]],0%) -> 1.0503007
A30: INTERMEDIATE 35+ SPLIT DOUBLES
A32: Category | B32: Teams | C32: Standing | D32: Points | E32: Matches Played | F32: Wins | G32: Win % | H32: Total Score | I32: Conceded Score | J32: Concession ratio %
A33: ='Registrations'!A28 -> Intermediate 35+ Split Doubles | B33: ='Registrations'!E28 -> 0 | C33: =_xlfn.RANK.EQ(Int35SD[[#This Row],[Points]],Int35SD[Points],0)+COUNTIFS(Int35SD[Points],Int35SD[[#This Row],[Points]],Int35SD[Concession ratio %],"<"&Int35SD[[#This Row],[Concession ratio %]])+COUNTIFS(Int35SD[Points],Int35SD[[#This Row],[Points]],Int35SD[Concession ratio %],Int35SD[[#This Row],[Concession ratio %]],Int35SD[Teams],"<"&Int35SD[[#This Row],[Teams]]) -> 1 | D33: =Int35SD[[#This Row],[Wins]]*3 -> 987 | E33: =COUNTIF(Schedules[Team 1 Name], B33) + COUNTIF(Schedules[Team 2 Name], B33) -> 756 | F33: =COUNTIFS(Schedules[Team 1 Name], B33, Schedules[Team 1 Outcome], "Win") + COUNTIFS(Schedules[Team 2 Name], B33, Schedules[Team 2 Outcome], "Win") -> 329 | G33: =IFERROR(Int35SD[[#This Row],[Wins]]/Int35SD[[#This Row],[Matches Played]],0%) -> 0.43518519 | H33: =SUMIFS(Schedules[Team 1 Score],Schedules[Team 1 Name],B33)+SUMIFS(Schedules[Team 2 Score],Schedules[Team 2 Name],B33) -> 9145 | I33: =SUMIFS(Schedules[Team 2 Score],Schedules[Team 1 Name],B33)+SUMIFS(Schedules[Team 1 Score],Schedules[Team 2 Name],B33) -> 9605 | J33: =IFERROR(Int35SD[[#This Row],[Conceded Score]]/Int35SD[[#This Row],[Total Score]],0%) -> 1.0503007
A34: ='Registrations'!A29 -> Intermediate 35+ Split Doubles | B34: ='Registrations'!E29 -> 0 | C34: =_xlfn.RANK.EQ(Int35SD[[#This Row],[Points]],Int35SD[Points],0)+COUNTIFS(Int35SD[Points],Int35SD[[#This Row],[Points]],Int35SD[Concession ratio %],"<"&Int35SD[[#This Row],[Concession ratio %]])+COUNTIFS(Int35SD[Points],Int35SD[[#This Row],[Points]],Int35SD[Concession ratio %],Int35SD[[#This Row],[Concession ratio %]],Int35SD[Teams],"<"&Int35SD[[#This Row],[Teams]]) -> 1 | D34: =Int35SD[[#This Row],[Wins]]*3 -> 987 | E34: =COUNTIF(Schedules[Team 1 Name], B34) + COUNTIF(Schedules[Team 2 Name], B34) -> 756 | F34: =COUNTIFS(Schedules[Team 1 Name], B34, Schedules[Team 1 Outcome], "Win") + COUNTIFS(Schedules[Team 2 Name], B34, Schedules[Team 2 Outcome], "Win") -> 329 | G34: =IFERROR(Int35SD[[#This Row],[Wins]]/Int35SD[[#This Row],[Matches Played]],0%) -> 0.43518519 | H34: =SUMIFS(Schedules[Team 1 Score],Schedules[Team 1 Name],B34)+SUMIFS(Schedules[Team 2 Score],Schedules[Team 2 Name],B34) -> 9145 | I34: =SUMIFS(Schedules[Team 2 Score],Schedules[Team 1 Name],B34)+SUMIFS(Schedules[Team 1 Score],Schedules[Team 2 Name],B34) -> 9605 | J34: =IFERROR(Int35SD[[#This Row],[Conceded Score]]/Int35SD[[#This Row],[Total Score]],0%) -> 1.0503007
A35: ='Registrations'!A30 -> Intermediate 35+ Split Doubles | B35: ='Registrations'!E30 -> 0 | C35: =_xlfn.RANK.EQ(Int35SD[[#This Row],[Points]],Int35SD[Points],0)+COUNTIFS(Int35SD[Points],Int35SD[[#This Row],[Points]],Int35SD[Concession ratio %],"<"&Int35SD[[#This Row],[Concession ratio %]])+COUNTIFS(Int35SD[Points],Int35SD[[#This Row],[Points]],Int35SD[Concession ratio %],Int35SD[[#This Row],[Concession ratio %]],Int35SD[Teams],"<"&Int35SD[[#This Row],[Teams]]) -> 1 | D35: =Int35SD[[#This Row],[Wins]]*3 -> 987 | E35: =COUNTIF(Schedules[Team 1 Name], B35) + COUNTIF(Schedules[Team 2 Name], B35) -> 756 | F35: =COUNTIFS(Schedules[Team 1 Name], B35, Schedules[Team 1 Outcome], "Win") + COUNTIFS(Schedules[Team 2 Name], B35, Schedules[Team 2 Outcome], "Win") -> 329 | G35: =IFERROR(Int35SD[[#This Row],[Wins]]/Int35SD[[#This Row],[Matches Played]],0%) -> 0.43518519 | H35: =SUMIFS(Schedules[Team 1 Score],Schedules[Team 1 Name],B35)+SUMIFS(Schedules[Team 2 Score],Schedules[Team 2 Name],B35) -> 9145 | I35: =SUMIFS(Schedules[Team 2 Score],Schedules[Team 1 Name],B35)+SUMIFS(Schedules[Team 1 Score],Schedules[Team 2 Name],B35) -> 9605 | J35: =IFERROR(Int35SD[[#This Row],[Conceded Score]]/Int35SD[[#This Row],[Total Score]],0%) -> 1.0503007
A36: ='Registrations'!A31 -> Intermediate 35+ Split Doubles | B36: ='Registrations'!E31 -> 0 | C36: =_xlfn.RANK.EQ(Int35SD[[#This Row],[Points]],Int35SD[Points],0)+COUNTIFS(Int35SD[Points],Int35SD[[#This Row],[Points]],Int35SD[Concession ratio %],"<"&Int35SD[[#This Row],[Concession ratio %]])+COUNTIFS(Int35SD[Points],Int35SD[[#This Row],[Points]],Int35SD[Concession ratio %],Int35SD[[#This Row],[Concession ratio %]],Int35SD[Teams],"<"&Int35SD[[#This Row],[Teams]]) -> 1 | D36: =Int35SD[[#This Row],[Wins]]*3 -> 987 | E36: =COUNTIF(Schedules[Team 1 Name], B36) + COUNTIF(Schedules[Team 2 Name], B36) -> 756 | F36: =COUNTIFS(Schedules[Team 1 Name], B36, Schedules[Team 1 Outcome], "Win") + COUNTIFS(Schedules[Team 2 Name], B36, Schedules[Team 2 Outcome], "Win") -> 329 | G36: =IFERROR(Int35SD[[#This Row],[Wins]]/Int35SD[[#This Row],[Matches Played]],0%) -> 0.43518519 | H36: =SUMIFS(Schedules[Team 1 Score],Schedules[Team 1 Name],B36)+SUMIFS(Schedules[Team 2 Score],Schedules[Team 2 Name],B36) -> 9145 | I36: =SUMIFS(Schedules[Team 2 Score],Schedules[Team 1 Name],B36)+SUMIFS(Schedules[Team 1 Score],Schedules[Team 2 Name],B36) -> 9605 | J36: =IFERROR(Int35SD[[#This Row],[Conceded Score]]/Int35SD[[#This Row],[Total Score]],0%) -> 1.0503007
A37: ='Registrations'!A32 -> Intermediate 35+ Split Doubles | B37: ='Registrations'!E32 -> 0 | C37: =_xlfn.RANK.EQ(Int35SD[[#This Row],[Points]],Int35SD[Points],0)+COUNTIFS(Int35SD[Points],Int35SD[[#This Row],[Points]],Int35SD[Concession ratio %],"<"&Int35SD[[#This Row],[Concession ratio %]])+COUNTIFS(Int35SD[Points],Int35SD[[#This Row],[Points]],Int35SD[Concession ratio %],Int35SD[[#This Row],[Concession ratio %]],Int35SD[Teams],"<"&Int35SD[[#This Row],[Teams]]) -> 1 | D37: =Int35SD[[#This Row],[Wins]]*3 -> 987 | E37: =COUNTIF(Schedules[Team 1 Name], B37) + COUNTIF(Schedules[Team 2 Name], B37) -> 756 | F37: =COUNTIFS(Schedules[Team 1 Name], B37, Schedules[Team 1 Outcome], "Win") + COUNTIFS(Schedules[Team 2 Name], B37, Schedules[Team 2 Outcome], "Win") -> 329 | G37: =IFERROR(Int35SD[[#This Row],[Wins]]/Int35SD[[#This Row],[Matches Played]],0%) -> 0.43518519 | H37: =SUMIFS(Schedules[Team 1 Score],Schedules[Team 1 Name],B37)+SUMIFS(Schedules[Team 2 Score],Schedules[Team 2 Name],B37) -> 9145 | I37: =SUMIFS(Schedules[Team 2 Score],Schedules[Team 1 Name],B37)+SUMIFS(Schedules[Team 1 Score],Schedules[Team 2 Name],B37) -> 9605 | J37: =IFERROR(Int35SD[[#This Row],[Conceded Score]]/Int35SD[[#This Row],[Total Score]],0%) -> 1.0503007
A38: ='Registrations'!A33 -> Intermediate 35+ Split Doubles | B38: ='Registrations'!E33 -> 0 | C38: =_xlfn.RANK.EQ(Int35SD[[#This Row],[Points]],Int35SD[Points],0)+COUNTIFS(Int35SD[Points],Int35SD[[#This Row],[Points]],Int35SD[Concession ratio %],"<"&Int35SD[[#This Row],[Concession ratio %]])+COUNTIFS(Int35SD[Points],Int35SD[[#This Row],[Points]],Int35SD[Concession ratio %],Int35SD[[#This Row],[Concession ratio %]],Int35SD[Teams],"<"&Int35SD[[#This Row],[Teams]]) -> 1 | D38: =Int35SD[[#This Row],[Wins]]*3 -> 987 | E38: =COUNTIF(Schedules[Team 1 Name], B38) + COUNTIF(Schedules[Team 2 Name], B38) -> 756 | F38: =COUNTIFS(Schedules[Team 1 Name], B38, Schedules[Team 1 Outcome], "Win") + COUNTIFS(Schedules[Team 2 Name], B38, Schedules[Team 2 Outcome], "Win") -> 329 | G38: =IFERROR(Int35SD[[#This Row],[Wins]]/Int35SD[[#This Row],[Matches Played]],0%) -> 0.43518519 | H38: =SUMIFS(Schedules[Team 1 Score],Schedules[Team 1 Name],B38)+SUMIFS(Schedules[Team 2 Score],Schedules[Team 2 Name],B38) -> 9145 | I38: =SUMIFS(Schedules[Team 2 Score],Schedules[Team 1 Name],B38)+SUMIFS(Schedules[Team 1 Score],Schedules[Team 2 Name],B38) -> 9605 | J38: =IFERROR(Int35SD[[#This Row],[Conceded Score]]/Int35SD[[#This Row],[Total Score]],0%) -> 1.0503007
A39: ='Registrations'!A34 -> Intermediate 35+ Split Doubles | B39: ='Registrations'!E34 -> 0 | C39: =_xlfn.RANK.EQ(Int35SD[[#This Row],[Points]],Int35SD[Points],0)+COUNTIFS(Int35SD[Points],Int35SD[[#This Row],[Points]],Int35SD[Concession ratio %],"<"&Int35SD[[#This Row],[Concession ratio %]])+COUNTIFS(Int35SD[Points],Int35SD[[#This Row],[Points]],Int35SD[Concession ratio %],Int35SD[[#This Row],[Concession ratio %]],Int35SD[Teams],"<"&Int35SD[[#This Row],[Teams]]) -> 1 | D39: =Int35SD[[#This Row],[Wins]]*3 -> 987 | E39: =COUNTIF(Schedules[Team 1 Name], B39) + COUNTIF(Schedules[Team 2 Name], B39) -> 756 | F39: =COUNTIFS(Schedules[Team 1 Name], B39, Schedules[Team 1 Outcome], "Win") + COUNTIFS(Schedules[Team 2 Name], B39, Schedules[Team 2 Outcome], "Win") -> 329 | G39: =IFERROR(Int35SD[[#This Row],[Wins]]/Int35SD[[#This Row],[Matches Played]],0%) -> 0.43518519 | H39: =SUMIFS(Schedules[Team 1 Score],Schedules[Team 1 Name],B39)+SUMIFS(Schedules[Team 2 Score],Schedules[Team 2 Name],B39) -> 9145 | I39: =SUMIFS(Schedules[Team 2 Score],Schedules[Team 1 Name],B39)+SUMIFS(Schedules[Team 1 Score],Schedules[Team 2 Name],B39) -> 9605 | J39: =IFERROR(Int35SD[[#This Row],[Conceded Score]]/Int35SD[[#This Row],[Total Score]],0%) -> 1.0503007
A40: ='Registrations'!A35 -> Intermediate 35+ Split Doubles | B40: ='Registrations'!E35 -> 0 | C40: =_xlfn.RANK.EQ(Int35SD[[#This Row],[Points]],Int35SD[Points],0)+COUNTIFS(Int35SD[Points],Int35SD[[#This Row],[Points]],Int35SD[Concession ratio %],"<"&Int35SD[[#This Row],[Concession ratio %]])+COUNTIFS(Int35SD[Points],Int35SD[[#This Row],[Points]],Int35SD[Concession ratio %],Int35SD[[#This Row],[Concession ratio %]],Int35SD[Teams],"<"&Int35SD[[#This Row],[Teams]]) -> 1 | D40: =Int35SD[[#This Row],[Wins]]*3 -> 987 | E40: =COUNTIF(Schedules[Team 1 Name], B40) + COUNTIF(Schedules[Team 2 Name], B40) -> 756 | F40: =COUNTIFS(Schedules[Team 1 Name], B40, Schedules[Team 1 Outcome], "Win") + COUNTIFS(Schedules[Team 2 Name], B40, Schedules[Team 2 Outcome], "Win") -> 329 | G40: =IFERROR(Int35SD[[#This Row],[Wins]]/Int35SD[[#This Row],[Matches Played]],0%) -> 0.43518519 | H40: =SUMIFS(Schedules[Team 1 Score],Schedules[Team 1 Name],B40)+SUMIFS(Schedules[Team 2 Score],Schedules[Team 2 Name],B40) -> 9145 | I40: =SUMIFS(Schedules[Team 2 Score],Schedules[Team 1 Name],B40)+SUMIFS(Schedules[Team 1 Score],Schedules[Team 2 Name],B40) -> 9605 | J40: =IFERROR(Int35SD[[#This Row],[Conceded Score]]/Int35SD[[#This Row],[Total Score]],0%) -> 1.0503007
A41: ='Registrations'!A36 -> Intermediate 35+ Split Doubles | B41: ='Registrations'!E36 -> 0 | C41: =_xlfn.RANK.EQ(Int35SD[[#This Row],[Points]],Int35SD[Points],0)+COUNTIFS(Int35SD[Points],Int35SD[[#This Row],[Points]],Int35SD[Concession ratio %],"<"&Int35SD[[#This Row],[Concession ratio %]])+COUNTIFS(Int35SD[Points],Int35SD[[#This Row],[Points]],Int35SD[Concession ratio %],Int35SD[[#This Row],[Concession ratio %]],Int35SD[Teams],"<"&Int35SD[[#This Row],[Teams]]) -> 1 | D41: =Int35SD[[#This Row],[Wins]]*3 -> 987 | E41: =COUNTIF(Schedules[Team 1 Name], B41) + COUNTIF(Schedules[Team 2 Name], B41) -> 756 | F41: =COUNTIFS(Schedules[Team 1 Name], B41, Schedules[Team 1 Outcome], "Win") + COUNTIFS(Schedules[Team 2 Name], B41, Schedules[Team 2 Outcome], "Win") -> 329 | G41: =IFERROR(Int35SD[[#This Row],[Wins]]/Int35SD[[#This Row],[Matches Played]],0%) -> 0.43518519 | H41: =SUMIFS(Schedules[Team 1 Score],Schedules[Team 1 Name],B41)+SUMIFS(Schedules[Team 2 Score],Schedules[Team 2 Name],B41) -> 9145 | I41: =SUMIFS(Schedules[Team 2 Score],Schedules[Team 1 Name],B41)+SUMIFS(Schedules[Team 1 Score],Schedules[Team 2 Name],B41) -> 9605 | J41: =IFERROR(Int35SD[[#This Row],[Conceded Score]]/Int35SD[[#This Row],[Total Score]],0%) -> 1.0503007
A42: ='Registrations'!A37 -> Intermediate 35+ Split Doubles | B42: ='Registrations'!E37 -> 0 | C42: =_xlfn.RANK.EQ(Int35SD[[#This Row],[Points]],Int35SD[Points],0)+COUNTIFS(Int35SD[Points],Int35SD[[#This Row],[Points]],Int35SD[Concession ratio %],"<"&Int35SD[[#This Row],[Concession ratio %]])+COUNTIFS(Int35SD[Points],Int35SD[[#This Row],[Points]],Int35SD[Concession ratio %],Int35SD[[#This Row],[Concession ratio %]],Int35SD[Teams],"<"&Int35SD[[#This Row],[Teams]]) -> 1 | D42: =Int35SD[[#This Row],[Wins]]*3 -> 987 | E42: =COUNTIF(Schedules[Team 1 Name], B42) + COUNTIF(Schedules[Team 2 Name], B42) -> 756 | F42: =COUNTIFS(Schedules[Team 1 Name], B42, Schedules[Team 1 Outcome], "Win") + COUNTIFS(Schedules[Team 2 Name], B42, Schedules[Team 2 Outcome], "Win") -> 329 | G42: =IFERROR(Int35SD[[#This Row],[Wins]]/Int35SD[[#This Row],[Matches Played]],0%) -> 0.43518519 | H42: =SUMIFS(Schedules[Team 1 Score],Schedules[Team 1 Name],B42)+SUMIFS(Schedules[Team 2 Score],Schedules[Team 2 Name],B42) -> 9145 | I42: =SUMIFS(Schedules[Team 2 Score],Schedules[Team 1 Name],B42)+SUMIFS(Schedules[Team 1 Score],Schedules[Team 2 Name],B42) -> 9605 | J42: =IFERROR(Int35SD[[#This Row],[Conceded Score]]/Int35SD[[#This Row],[Total Score]],0%) -> 1.0503007
A43: ='Registrations'!A38 -> Intermediate 35+ Split Doubles | B43: ='Registrations'!E38 -> 0 | C43: =_xlfn.RANK.EQ(Int35SD[[#This Row],[Points]],Int35SD[Points],0)+COUNTIFS(Int35SD[Points],Int35SD[[#This Row],[Points]],Int35SD[Concession ratio %],"<"&Int35SD[[#This Row],[Concession ratio %]])+COUNTIFS(Int35SD[Points],Int35SD[[#This Row],[Points]],Int35SD[Concession ratio %],Int35SD[[#This Row],[Concession ratio %]],Int35SD[Teams],"<"&Int35SD[[#This Row],[Teams]]) -> 1 | D43: =Int35SD[[#This Row],[Wins]]*3 -> 987 | E43: =COUNTIF(Schedules[Team 1 Name], B43) + COUNTIF(Schedules[Team 2 Name], B43) -> 756 | F43: =COUNTIFS(Schedules[Team 1 Name], B43, Schedules[Team 1 Outcome], "Win") + COUNTIFS(Schedules[Team 2 Name], B43, Schedules[Team 2 Outcome], "Win") -> 329 | G43: =IFERROR(Int35SD[[#This Row],[Wins]]/Int35SD[[#This Row],[Matches Played]],0%) -> 0.43518519 | H43: =SUMIFS(Schedules[Team 1 Score],Schedules[Team 1 Name],B43)+SUMIFS(Schedules[Team 2 Score],Schedules[Team 2 Name],B43) -> 9145 | I43: =SUMIFS(Schedules[Team 2 Score],Schedules[Team 1 Name],B43)+SUMIFS(Schedules[Team 1 Score],Schedules[Team 2 Name],B43) -> 9605 | J43: =IFERROR(Int35SD[[#This Row],[Conceded Score]]/Int35SD[[#This Row],[Total Score]],0%) -> 1.0503007
A44: ='Registrations'!A39 -> Intermediate 35+ Split Doubles | B44: ='Registrations'!E39 -> 0 | C44: =_xlfn.RANK.EQ(Int35SD[[#This Row],[Points]],Int35SD[Points],0)+COUNTIFS(Int35SD[Points],Int35SD[[#This Row],[Points]],Int35SD[Concession ratio %],"<"&Int35SD[[#This Row],[Concession ratio %]])+COUNTIFS(Int35SD[Points],Int35SD[[#This Row],[Points]],Int35SD[Concession ratio %],Int35SD[[#This Row],[Concession ratio %]],Int35SD[Teams],"<"&Int35SD[[#This Row],[Teams]]) -> 1 | D44: =Int35SD[[#This Row],[Wins]]*3 -> 987 | E44: =COUNTIF(Schedules[Team 1 Name], B44) + COUNTIF(Schedules[Team 2 Name], B44) -> 756 | F44: =COUNTIFS(Schedules[Team 1 Name], B44, Schedules[Team 1 Outcome], "Win") + COUNTIFS(Schedules[Team 2 Name], B44, Schedules[Team 2 Outcome], "Win") -> 329 | G44: =IFERROR(Int35SD[[#This Row],[Wins]]/Int35SD[[#This Row],[Matches Played]],0%) -> 0.43518519 | H44: =SUMIFS(Schedules[Team 1 Score],Schedules[Team 1 Name],B44)+SUMIFS(Schedules[Team 2 Score],Schedules[Team 2 Name],B44) -> 9145 | I44: =SUMIFS(Schedules[Team 2 Score],Schedules[Team 1 Name],B44)+SUMIFS(Schedules[Team 1 Score],Schedules[Team 2 Name],B44) -> 9605 | J44: =IFERROR(Int35SD[[#This Row],[Conceded Score]]/Int35SD[[#This Row],[Total Score]],0%) -> 1.0503007
A47: INTERMEDIATE 35+ SPLIT DOUBLES
A49: Category | B49: Teams | C49: Standing | D49: Points | E49: Matches Played | F49: Wins | G49: Win % | H49: Total Score | I49: Conceded Score | J49: Concession ratio %
A50: ='Registrations'!A40 -> Int Men Doubles | B50: ='Registrations'!E40 -> 0 | C50: =_xlfn.RANK.EQ(IntMenDoubles[[#This Row],[Points]],IntMenDoubles[Points],0)+COUNTIFS(IntMenDoubles[Points],IntMenDoubles[[#This Row],[Points]],IntMenDoubles[Concession ratio %],"<"&IntMenDoubles[[#This Row],[Concession ratio %]])+COUNTIFS(IntMenDoubles[Points],IntMenDoubles[[#This Row],[Points]],IntMenDoubles[Concession ratio %],IntMenDoubles[[#This Row],[Concession ratio %]],IntMenDoubles[Teams],"<"&IntMenDoubles[[#This Row],[Teams]]) -> 1 | D50: =IntMenDoubles[[#This Row],[Wins]]*3 -> 987 | E50: =COUNTIF(Schedules[Team 1 Name], B50) + COUNTIF(Schedules[Team 2 Name], B50) -> 756 | F50: =COUNTIFS(Schedules[Team 1 Name], B50, Schedules[Team 1 Outcome], "Win") + COUNTIFS(Schedules[Team 2 Name], B50, Schedules[Team 2 Outcome], "Win") -> 329 | G50: =IFERROR(OpenSingles[[#This Row],[Wins]]/OpenSingles[[#This Row],[Matches Played]],0%) -> 0 | H50: =SUMIFS(Schedules[Team 1 Score],Schedules[Team 1 Name],B50)+SUMIFS(Schedules[Team 2 Score],Schedules[Team 2 Name],B50) -> 9145 | I50: =SUMIFS(Schedules[Team 2 Score],Schedules[Team 1 Name],B50)+SUMIFS(Schedules[Team 1 Score],Schedules[Team 2 Name],B50) -> 9605 | J50: =IFERROR(IntMenDoubles[[#This Row],[Conceded Score]]/IntMenDoubles[[#This Row],[Total Score]],0%) -> 1.0503007
A51: ='Registrations'!A41 -> Int Men Doubles | B51: ='Registrations'!E41 -> 0 | C51: =_xlfn.RANK.EQ(IntMenDoubles[[#This Row],[Points]],IntMenDoubles[Points],0)+COUNTIFS(IntMenDoubles[Points],IntMenDoubles[[#This Row],[Points]],IntMenDoubles[Concession ratio %],"<"&IntMenDoubles[[#This Row],[Concession ratio %]])+COUNTIFS(IntMenDoubles[Points],IntMenDoubles[[#This Row],[Points]],IntMenDoubles[Concession ratio %],IntMenDoubles[[#This Row],[Concession ratio %]],IntMenDoubles[Teams],"<"&IntMenDoubles[[#This Row],[Teams]]) -> 1 | D51: =IntMenDoubles[[#This Row],[Wins]]*3 -> 987 | E51: =COUNTIF(Schedules[Team 1 Name], B51) + COUNTIF(Schedules[Team 2 Name], B51) -> 756 | F51: =COUNTIFS(Schedules[Team 1 Name], B51, Schedules[Team 1 Outcome], "Win") + COUNTIFS(Schedules[Team 2 Name], B51, Schedules[Team 2 Outcome], "Win") -> 329 | G51: =IFERROR(OpenSingles[[#This Row],[Wins]]/OpenSingles[[#This Row],[Matches Played]],0%) -> 0 | H51: =SUMIFS(Schedules[Team 1 Score],Schedules[Team 1 Name],B51)+SUMIFS(Schedules[Team 2 Score],Schedules[Team 2 Name],B51) -> 9145 | I51: =SUMIFS(Schedules[Team 2 Score],Schedules[Team 1 Name],B51)+SUMIFS(Schedules[Team 1 Score],Schedules[Team 2 Name],B51) -> 9605 | J51: =IFERROR(IntMenDoubles[[#This Row],[Conceded Score]]/IntMenDoubles[[#This Row],[Total Score]],0%) -> 1.0503007
A52: ='Registrations'!A42 -> Int Men Doubles | B52: ='Registrations'!E42 -> 0 | C52: =_xlfn.RANK.EQ(IntMenDoubles[[#This Row],[Points]],IntMenDoubles[Points],0)+COUNTIFS(IntMenDoubles[Points],IntMenDoubles[[#This Row],[Points]],IntMenDoubles[Concession ratio %],"<"&IntMenDoubles[[#This Row],[Concession ratio %]])+COUNTIFS(IntMenDoubles[Points],IntMenDoubles[[#This Row],[Points]],IntMenDoubles[Concession ratio %],IntMenDoubles[[#This Row],[Concession ratio %]],IntMenDoubles[Teams],"<"&IntMenDoubles[[#This Row],[Teams]]) -> 1 | D52: =IntMenDoubles[[#This Row],[Wins]]*3 -> 987 | E52: =COUNTIF(Schedules[Team 1 Name], B52) + COUNTIF(Schedules[Team 2 Name], B52) -> 756 | F52: =COUNTIFS(Schedules[Team 1 Name], B52, Schedules[Team 1 Outcome], "Win") + COUNTIFS(Schedules[Team 2 Name], B52, Schedules[Team 2 Outcome], "Win") -> 329 | G52: =IFERROR(OpenSingles[[#This Row],[Wins]]/OpenSingles[[#This Row],[Matches Played]],0%) -> 0 | H52: =SUMIFS(Schedules[Team 1 Score],Schedules[Team 1 Name],B52)+SUMIFS(Schedules[Team 2 Score],Schedules[Team 2 Name],B52) -> 9145 | I52: =SUMIFS(Schedules[Team 2 Score],Schedules[Team 1 Name],B52)+SUMIFS(Schedules[Team 1 Score],Schedules[Team 2 Name],B52) -> 9605 | J52: =IFERROR(IntMenDoubles[[#This Row],[Conceded Score]]/IntMenDoubles[[#This Row],[Total Score]],0%) -> 1.0503007
A53: ='Registrations'!A43 -> Int Men Doubles | B53: ='Registrations'!E43 -> 0 | C53: =_xlfn.RANK.EQ(IntMenDoubles[[#This Row],[Points]],IntMenDoubles[Points],0)+COUNTIFS(IntMenDoubles[Points],IntMenDoubles[[#This Row],[Points]],IntMenDoubles[Concession ratio %],"<"&IntMenDoubles[[#This Row],[Concession ratio %]])+COUNTIFS(IntMenDoubles[Points],IntMenDoubles[[#This Row],[Points]],IntMenDoubles[Concession ratio %],IntMenDoubles[[#This Row],[Concession ratio %]],IntMenDoubles[Teams],"<"&IntMenDoubles[[#This Row],[Teams]]) -> 1 | D53: =IntMenDoubles[[#This Row],[Wins]]*3 -> 987 | E53: =COUNTIF(Schedules[Team 1 Name], B53) + COUNTIF(Schedules[Team 2 Name], B53) -> 756 | F53: =COUNTIFS(Schedules[Team 1 Name], B53, Schedules[Team 1 Outcome], "Win") + COUNTIFS(Schedules[Team 2 Name], B53, Schedules[Team 2 Outcome], "Win") -> 329 | G53: =IFERROR(OpenSingles[[#This Row],[Wins]]/OpenSingles[[#This Row],[Matches Played]],0%) -> 0 | H53: =SUMIFS(Schedules[Team 1 Score],Schedules[Team 1 Name],B53)+SUMIFS(Schedules[Team 2 Score],Schedules[Team 2 Name],B53) -> 9145 | I53: =SUMIFS(Schedules[Team 2 Score],Schedules[Team 1 Name],B53)+SUMIFS(Schedules[Team 1 Score],Schedules[Team 2 Name],B53) -> 9605 | J53: =IFERROR(IntMenDoubles[[#This Row],[Conceded Score]]/IntMenDoubles[[#This Row],[Total Score]],0%) -> 1.0503007
A54: ='Registrations'!A44 -> Int Men Doubles | B54: ='Registrations'!E44 -> 0 | C54: =_xlfn.RANK.EQ(IntMenDoubles[[#This Row],[Points]],IntMenDoubles[Points],0)+COUNTIFS(IntMenDoubles[Points],IntMenDoubles[[#This Row],[Points]],IntMenDoubles[Concession ratio %],"<"&IntMenDoubles[[#This Row],[Concession ratio %]])+COUNTIFS(IntMenDoubles[Points],IntMenDoubles[[#This Row],[Points]],IntMenDoubles[Concession ratio %],IntMenDoubles[[#This Row],[Concession ratio %]],IntMenDoubles[Teams],"<"&IntMenDoubles[[#This Row],[Teams]]) -> 1 | D54: =IntMenDoubles[[#This Row],[Wins]]*3 -> 987 | E54: =COUNTIF(Schedules[Team 1 Name], B54) + COUNTIF(Schedules[Team 2 Name], B54) -> 756 | F54: =COUNTIFS(Schedules[Team 1 Name], B54, Schedules[Team 1 Outcome], "Win") + COUNTIFS(Schedules[Team 2 Name], B54, Schedules[Team 2 Outcome], "Win") -> 329 | G54: =IFERROR(OpenSingles[[#This Row],[Wins]]/OpenSingles[[#This Row],[Matches Played]],0%) -> 0 | H54: =SUMIFS(Schedules[Team 1 Score],Schedules[Team 1 Name],B54)+SUMIFS(Schedules[Team 2 Score],Schedules[Team 2 Name],B54) -> 9145 | I54: =SUMIFS(Schedules[Team 2 Score],Schedules[Team 1 Name],B54)+SUMIFS(Schedules[Team 1 Score],Schedules[Team 2 Name],B54) -> 9605 | J54: =IFERROR(IntMenDoubles[[#This Row],[Conceded Score]]/IntMenDoubles[[#This Row],[Total Score]],0%) -> 1.0503007
A55: ='Registrations'!A45 -> Int Men Doubles | B55: ='Registrations'!E45 -> 0 | C55: =_xlfn.RANK.EQ(IntMenDoubles[[#This Row],[Points]],IntMenDoubles[Points],0)+COUNTIFS(IntMenDoubles[Points],IntMenDoubles[[#This Row],[Points]],IntMenDoubles[Concession ratio %],"<"&IntMenDoubles[[#This Row],[Concession ratio %]])+COUNTIFS(IntMenDoubles[Points],IntMenDoubles[[#This Row],[Points]],IntMenDoubles[Concession ratio %],IntMenDoubles[[#This Row],[Concession ratio %]],IntMenDoubles[Teams],"<"&IntMenDoubles[[#This Row],[Teams]]) -> 1 | D55: =IntMenDoubles[[#This Row],[Wins]]*3 -> 987 | E55: =COUNTIF(Schedules[Team 1 Name], B55) + COUNTIF(Schedules[Team 2 Name], B55) -> 756 | F55: =COUNTIFS(Schedules[Team 1 Name], B55, Schedules[Team 1 Outcome], "Win") + COUNTIFS(Schedules[Team 2 Name], B55, Schedules[Team 2 Outcome], "Win") -> 329 | G55: =IFERROR(OpenSingles[[#This Row],[Wins]]/OpenSingles[[#This Row],[Matches Played]],0%) -> 0 | H55: =SUMIFS(Schedules[Team 1 Score],Schedules[Team 1 Name],B55)+SUMIFS(Schedules[Team 2 Score],Schedules[Team 2 Name],B55) -> 9145 | I55: =SUMIFS(Schedules[Team 2 Score],Schedules[Team 1 Name],B55)+SUMIFS(Schedules[Team 1 Score],Schedules[Team 2 Name],B55) -> 9605 | J55: =IFERROR(IntMenDoubles[[#This Row],[Conceded Score]]/IntMenDoubles[[#This Row],[Total Score]],0%) -> 1.0503007
A56: ='Registrations'!A46 -> Int Men Doubles | B56: ='Registrations'!E46 -> 0 | C56: =_xlfn.RANK.EQ(IntMenDoubles[[#This Row],[Points]],IntMenDoubles[Points],0)+COUNTIFS(IntMenDoubles[Points],IntMenDoubles[[#This Row],[Points]],IntMenDoubles[Concession ratio %],"<"&IntMenDoubles[[#This Row],[Concession ratio %]])+COUNTIFS(IntMenDoubles[Points],IntMenDoubles[[#This Row],[Points]],IntMenDoubles[Concession ratio %],IntMenDoubles[[#This Row],[Concession ratio %]],IntMenDoubles[Teams],"<"&IntMenDoubles[[#This Row],[Teams]]) -> 1 | D56: =IntMenDoubles[[#This Row],[Wins]]*3 -> 987 | E56: =COUNTIF(Schedules[Team 1 Name], B56) + COUNTIF(Schedules[Team 2 Name], B56) -> 756 | F56: =COUNTIFS(Schedules[Team 1 Name], B56, Schedules[Team 1 Outcome], "Win") + COUNTIFS(Schedules[Team 2 Name], B56, Schedules[Team 2 Outcome], "Win") -> 329 | G56: =IFERROR(OpenSingles[[#This Row],[Wins]]/OpenSingles[[#This Row],[Matches Played]],0%) -> 0 | H56: =SUMIFS(Schedules[Team 1 Score],Schedules[Team 1 Name],B56)+SUMIFS(Schedules[Team 2 Score],Schedules[Team 2 Name],B56) -> 9145 | I56: =SUMIFS(Schedules[Team 2 Score],Schedules[Team 1 Name],B56)+SUMIFS(Schedules[Team 1 Score],Schedules[Team 2 Name],B56) -> 9605 | J56: =IFERROR(IntMenDoubles[[#This Row],[Conceded Score]]/IntMenDoubles[[#This Row],[Total Score]],0%) -> 1.0503007
A57: ='Registrations'!A47 -> Int Men Doubles | B57: ='Registrations'!E47 -> 0 | C57: =_xlfn.RANK.EQ(IntMenDoubles[[#This Row],[Points]],IntMenDoubles[Points],0)+COUNTIFS(IntMenDoubles[Points],IntMenDoubles[[#This Row],[Points]],IntMenDoubles[Concession ratio %],"<"&IntMenDoubles[[#This Row],[Concession ratio %]])+COUNTIFS(IntMenDoubles[Points],IntMenDoubles[[#This Row],[Points]],IntMenDoubles[Concession ratio %],IntMenDoubles[[#This Row],[Concession ratio %]],IntMenDoubles[Teams],"<"&IntMenDoubles[[#This Row],[Teams]]) -> 1 | D57: =IntMenDoubles[[#This Row],[Wins]]*3 -> 987 | E57: =COUNTIF(Schedules[Team 1 Name], B57) + COUNTIF(Schedules[Team 2 Name], B57) -> 756 | F57: =COUNTIFS(Schedules[Team 1 Name], B57, Schedules[Team 1 Outcome], "Win") + COUNTIFS(Schedules[Team 2 Name], B57, Schedules[Team 2 Outcome], "Win") -> 329 | G57: =IFERROR(OpenSingles[[#This Row],[Wins]]/OpenSingles[[#This Row],[Matches Played]],0%) -> 0 | H57: =SUMIFS(Schedules[Team 1 Score],Schedules[Team 1 Name],B57)+SUMIFS(Schedules[Team 2 Score],Schedules[Team 2 Name],B57) -> 9145 | I57: =SUMIFS(Schedules[Team 2 Score],Schedules[Team 1 Name],B57)+SUMIFS(Schedules[Team 1 Score],Schedules[Team 2 Name],B57) -> 9605 | J57: =IFERROR(IntMenDoubles[[#This Row],[Conceded Score]]/IntMenDoubles[[#This Row],[Total Score]],0%) -> 1.0503007
A58: ='Registrations'!A48 -> Int Men Doubles | B58: ='Registrations'!E48 -> 0 | C58: =_xlfn.RANK.EQ(IntMenDoubles[[#This Row],[Points]],IntMenDoubles[Points],0)+COUNTIFS(IntMenDoubles[Points],IntMenDoubles[[#This Row],[Points]],IntMenDoubles[Concession ratio %],"<"&IntMenDoubles[[#This Row],[Concession ratio %]])+COUNTIFS(IntMenDoubles[Points],IntMenDoubles[[#This Row],[Points]],IntMenDoubles[Concession ratio %],IntMenDoubles[[#This Row],[Concession ratio %]],IntMenDoubles[Teams],"<"&IntMenDoubles[[#This Row],[Teams]]) -> 1 | D58: =IntMenDoubles[[#This Row],[Wins]]*3 -> 987 | E58: =COUNTIF(Schedules[Team 1 Name], B58) + COUNTIF(Schedules[Team 2 Name], B58) -> 756 | F58: =COUNTIFS(Schedules[Team 1 Name], B58, Schedules[Team 1 Outcome], "Win") + COUNTIFS(Schedules[Team 2 Name], B58, Schedules[Team 2 Outcome], "Win") -> 329 | G58: =IFERROR(OpenSingles[[#This Row],[Wins]]/OpenSingles[[#This Row],[Matches Played]],0%) -> 0 | H58: =SUMIFS(Schedules[Team 1 Score],Schedules[Team 1 Name],B58)+SUMIFS(Schedules[Team 2 Score],Schedules[Team 2 Name],B58) -> 9145 | I58: =SUMIFS(Schedules[Team 2 Score],Schedules[Team 1 Name],B58)+SUMIFS(Schedules[Team 1 Score],Schedules[Team 2 Name],B58) -> 9605 | J58: =IFERROR(IntMenDoubles[[#This Row],[Conceded Score]]/IntMenDoubles[[#This Row],[Total Score]],0%) -> 1.0503007
A59: ='Registrations'!A49 -> Int Men Doubles | B59: ='Registrations'!E49 -> 0 | C59: =_xlfn.RANK.EQ(IntMenDoubles[[#This Row],[Points]],IntMenDoubles[Points],0)+COUNTIFS(IntMenDoubles[Points],IntMenDoubles[[#This Row],[Points]],IntMenDoubles[Concession ratio %],"<"&IntMenDoubles[[#This Row],[Concession ratio %]])+COUNTIFS(IntMenDoubles[Points],IntMenDoubles[[#This Row],[Points]],IntMenDoubles[Concession ratio %],IntMenDoubles[[#This Row],[Concession ratio %]],IntMenDoubles[Teams],"<"&IntMenDoubles[[#This Row],[Teams]]) -> 1 | D59: =IntMenDoubles[[#This Row],[Wins]]*3 -> 987 | E59: =COUNTIF(Schedules[Team 1 Name], B59) + COUNTIF(Schedules[Team 2 Name], B59) -> 756 | F59: =COUNTIFS(Schedules[Team 1 Name], B59, Schedules[Team 1 Outcome], "Win") + COUNTIFS(Schedules[Team 2 Name], B59, Schedules[Team 2 Outcome], "Win") -> 329 | G59: =IFERROR(OpenSingles[[#This Row],[Wins]]/OpenSingles[[#This Row],[Matches Played]],0%) -> 0 | H59: =SUMIFS(Schedules[Team 1 Score],Schedules[Team 1 Name],B59)+SUMIFS(Schedules[Team 2 Score],Schedules[Team 2 Name],B59) -> 9145 | I59: =SUMIFS(Schedules[Team 2 Score],Schedules[Team 1 Name],B59)+SUMIFS(Schedules[Team 1 Score],Schedules[Team 2 Name],B59) -> 9605 | J59: =IFERROR(IntMenDoubles[[#This Row],[Conceded Score]]/IntMenDoubles[[#This Row],[Total Score]],0%) -> 1.0503007
A60: ='Registrations'!A50 -> Int Men Doubles | B60: ='Registrations'!E50 -> 0 | C60: =_xlfn.RANK.EQ(IntMenDoubles[[#This Row],[Points]],IntMenDoubles[Points],0)+COUNTIFS(IntMenDoubles[Points],IntMenDoubles[[#This Row],[Points]],IntMenDoubles[Concession ratio %],"<"&IntMenDoubles[[#This Row],[Concession ratio %]])+COUNTIFS(IntMenDoubles[Points],IntMenDoubles[[#This Row],[Points]],IntMenDoubles[Concession ratio %],IntMenDoubles[[#This Row],[Concession ratio %]],IntMenDoubles[Teams],"<"&IntMenDoubles[[#This Row],[Teams]]) -> 1 | D60: =IntMenDoubles[[#This Row],[Wins]]*3 -> 987 | E60: =COUNTIF(Schedules[Team 1 Name], B60) + COUNTIF(Schedules[Team 2 Name], B60) -> 756 | F60: =COUNTIFS(Schedules[Team 1 Name], B60, Schedules[Team 1 Outcome], "Win") + COUNTIFS(Schedules[Team 2 Name], B60, Schedules[Team 2 Outcome], "Win") -> 329 | G60: =IFERROR(OpenSingles[[#This Row],[Wins]]/OpenSingles[[#This Row],[Matches Played]],0%) -> 0 | H60: =SUMIFS(Schedules[Team 1 Score],Schedules[Team 1 Name],B60)+SUMIFS(Schedules[Team 2 Score],Schedules[Team 2 Name],B60) -> 9145 | I60: =SUMIFS(Schedules[Team 2 Score],Schedules[Team 1 Name],B60)+SUMIFS(Schedules[Team 1 Score],Schedules[Team 2 Name],B60) -> 9605 | J60: =IFERROR(IntMenDoubles[[#This Row],[Conceded Score]]/IntMenDoubles[[#This Row],[Total Score]],0%) -> 1.0503007
A61: ='Registrations'!A51 -> Int Men Doubles | B61: ='Registrations'!E51 -> 0 | C61: =_xlfn.RANK.EQ(IntMenDoubles[[#This Row],[Points]],IntMenDoubles[Points],0)+COUNTIFS(IntMenDoubles[Points],IntMenDoubles[[#This Row],[Points]],IntMenDoubles[Concession ratio %],"<"&IntMenDoubles[[#This Row],[Concession ratio %]])+COUNTIFS(IntMenDoubles[Points],IntMenDoubles[[#This Row],[Points]],IntMenDoubles[Concession ratio %],IntMenDoubles[[#This Row],[Concession ratio %]],IntMenDoubles[Teams],"<"&IntMenDoubles[[#This Row],[Teams]]) -> 1 | D61: =IntMenDoubles[[#This Row],[Wins]]*3 -> 987 | E61: =COUNTIF(Schedules[Team 1 Name], B61) + COUNTIF(Schedules[Team 2 Name], B61) -> 756 | F61: =COUNTIFS(Schedules[Team 1 Name], B61, Schedules[Team 1 Outcome], "Win") + COUNTIFS(Schedules[Team 2 Name], B61, Schedules[Team 2 Outcome], "Win") -> 329 | G61: =IFERROR(OpenSingles[[#This Row],[Wins]]/OpenSingles[[#This Row],[Matches Played]],0%) -> 0 | H61: =SUMIFS(Schedules[Team 1 Score],Schedules[Team 1 Name],B61)+SUMIFS(Schedules[Team 2 Score],Schedules[Team 2 Name],B61) -> 9145 | I61: =SUMIFS(Schedules[Team 2 Score],Schedules[Team 1 Name],B61)+SUMIFS(Schedules[Team 1 Score],Schedules[Team 2 Name],B61) -> 9605 | J61: =IFERROR(IntMenDoubles[[#This Row],[Conceded Score]]/IntMenDoubles[[#This Row],[Total Score]],0%) -> 1.0503007
... A81: ='Registrations'!A71 -> Int Men Doubles | B81: ='Registrations'!E71 -> 0 | C81: =_xlfn.RANK.EQ(IntMenDoubles[[#This Row],[Points]],IntMenDoubles[Points],0)+COUNTIFS(IntMenDoubles[Points],IntMenDoubles[[#This Row],[Points]],IntMenDoubles[Concession ratio %],"<"&IntMenDoubles[[#This Row],[Concession ratio %]])+COUNTIFS(IntMenDoubles[Points],IntMenDoubles[[#This Row],[Points]],IntMenDoubles[Concession ratio %],IntMenDoubles[[#This Row],[Concession ratio %]],IntMenDoubles[Teams],"<"&IntMenDoubles[[#This Row],[Teams]]) -> 1 | D81: =IntMenDoubles[[#This Row],[Wins]]*3 -> 987 | E81: =COUNTIF(Schedules[Team 1 Name], B81) + COUNTIF(Schedules[Team 2 Name], B81) -> 756 | F81: =COUNTIFS(Schedules[Team 1 Name], B81, Schedules[Team 1 Outcome], "Win") + COUNTIFS(Schedules[Team 2 Name], B81, Schedules[Team 2 Outcome], "Win") -> 329 | G81: =IFERROR(OpenSingles[[#This Row],[Wins]]/OpenSingles[[#This Row],[Matches Played]],0%) -> 0 | H81: =SUMIFS(Schedules[Team 1 Score],Schedules[Team 1 Name],B81)+SUMIFS(Schedules[Team 2 Score],Schedules[Team 2 Name],B81) -> 9145 | I81: =SUMIFS(Schedules[Team 2 Score],Schedules[Team 1 Name],B81)+SUMIFS(Schedules[Team 1 Score],Schedules[Team 2 Name],B81) -> 9605 | J81: =IFERROR(IntMenDoubles[[#This Row],[Conceded Score]]/IntMenDoubles[[#This Row],[Total Score]],0%) -> 1.0503007
A84: OPEN MIXED DOUBLES
A86: Category | B86: Teams | C86: Standing | D86: Points | E86: Matches Played | F86: Wins | G86: Win % | H86: Total Score | I86: Conceded Score | J86: Concession ratio %
A87: ='Registrations'!A72 -> Open Mixed Doubles | B87: ='Registrations'!E72 -> 0 | C87: =_xlfn.RANK.EQ(OpenMxD[[#This Row],[Points]],OpenMxD[Points],0)+COUNTIFS(OpenMxD[Points],OpenMxD[[#This Row],[Points]],OpenMxD[Concession ratio %],"<"&OpenMxD[[#This Row],[Concession ratio %]])+COUNTIFS(OpenMxD[Points],OpenMxD[[#This Row],[Points]],OpenMxD[Concession ratio %],OpenMxD[[#This Row],[Concession ratio %]],OpenMxD[Teams],"<"&OpenMxD[[#This Row],[Teams]]) -> 1 | D87: =OpenMxD[[#This Row],[Wins]]*3 -> 987 | E87: =COUNTIF(Schedules[Team 1 Name], B87) + COUNTIF(Schedules[Team 2 Name], B87) -> 756 | F87: =COUNTIFS(Schedules[Team 1 Name], B87, Schedules[Team 1 Outcome], "Win") + COUNTIFS(Schedules[Team 2 Name], B87, Schedules[Team 2 Outcome], "Win") -> 329 | G87: =IFERROR(OpenSingles[[#This Row],[Wins]]/OpenSingles[[#This Row],[Matches Played]],0%) -> 0 | H87: =SUMIFS(Schedules[Team 1 Score],Schedules[Team 1 Name],B87)+SUMIFS(Schedules[Team 2 Score],Schedules[Team 2 Name],B87) -> 9145 | I87: =SUMIFS(Schedules[Team 2 Score],Schedules[Team 1 Name],B87)+SUMIFS(Schedules[Team 1 Score],Schedules[Team 2 Name],B87) -> 9605 | J87: =IFERROR(OpenMxD[[#This Row],[Conceded Score]]/OpenMxD[[#This Row],[Total Score]],0%) -> 1.0503007
A88: ='Registrations'!A73 -> Open Mixed Doubles | B88: ='Registrations'!E73 -> 0 | C88: =_xlfn.RANK.EQ(OpenMxD[[#This Row],[Points]],OpenMxD[Points],0)+COUNTIFS(OpenMxD[Points],OpenMxD[[#This Row],[Points]],OpenMxD[Concession ratio %],"<"&OpenMxD[[#This Row],[Concession ratio %]])+COUNTIFS(OpenMxD[Points],OpenMxD[[#This Row],[Points]],OpenMxD[Concession ratio %],OpenMxD[[#This Row],[Concession ratio %]],OpenMxD[Teams],"<"&OpenMxD[[#This Row],[Teams]]) -> 1 | D88: =OpenMxD[[#This Row],[Wins]]*3 -> 987 | E88: =COUNTIF(Schedules[Team 1 Name], B88) + COUNTIF(Schedules[Team 2 Name], B88) -> 756 | F88: =COUNTIFS(Schedules[Team 1 Name], B88, Schedules[Team 1 Outcome], "Win") + COUNTIFS(Schedules[Team 2 Name], B88, Schedules[Team 2 Outcome], "Win") -> 329 | G88: =IFERROR(OpenSingles[[#This Row],[Wins]]/OpenSingles[[#This Row],[Matches Played]],0%) -> 0 | H88: =SUMIFS(Schedules[Team 1 Score],Schedules[Team 1 Name],B88)+SUMIFS(Schedules[Team 2 Score],Schedules[Team 2 Name],B88) -> 9145 | I88: =SUMIFS(Schedules[Team 2 Score],Schedules[Team 1 Name],B88)+SUMIFS(Schedules[Team 1 Score],Schedules[Team 2 Name],B88) -> 9605 | J88: =IFERROR(OpenMxD[[#This Row],[Conceded Score]]/OpenMxD[[#This Row],[Total Score]],0%) -> 1.0503007
A89: ='Registrations'!A74 -> Open Mixed Doubles | B89: ='Registrations'!E74 -> 0 | C89: =_xlfn.RANK.EQ(OpenMxD[[#This Row],[Points]],OpenMxD[Points],0)+COUNTIFS(OpenMxD[Points],OpenMxD[[#This Row],[Points]],OpenMxD[Concession ratio %],"<"&OpenMxD[[#This Row],[Concession ratio %]])+COUNTIFS(OpenMxD[Points],OpenMxD[[#This Row],[Points]],OpenMxD[Concession ratio %],OpenMxD[[#This Row],[Concession ratio %]],OpenMxD[Teams],"<"&OpenMxD[[#This Row],[Teams]]) -> 1 | D89: =OpenMxD[[#This Row],[Wins]]*3 -> 987 | E89: =COUNTIF(Schedules[Team 1 Name], B89) + COUNTIF(Schedules[Team 2 Name], B89) -> 756 | F89: =COUNTIFS(Schedules[Team 1 Name], B89, Schedules[Team 1 Outcome], "Win") + COUNTIFS(Schedules[Team 2 Name], B89, Schedules[Team 2 Outcome], "Win") -> 329 | G89: =IFERROR(OpenSingles[[#This Row],[Wins]]/OpenSingles[[#This Row],[Matches Played]],0%) -> 0 | H89: =SUMIFS(Schedules[Team 1 Score],Schedules[Team 1 Name],B89)+SUMIFS(Schedules[Team 2 Score],Schedules[Team 2 Name],B89) -> 9145 | I89: =SUMIFS(Schedules[Team 2 Score],Schedules[Team 1 Name],B89)+SUMIFS(Schedules[Team 1 Score],Schedules[Team 2 Name],B89) -> 9605 | J89: =IFERROR(OpenMxD[[#This Row],[Conceded Score]]/OpenMxD[[#This Row],[Total Score]],0%) -> 1.0503007
A90: ='Registrations'!A75 -> Open Mixed Doubles | B90: ='Registrations'!E75 -> 0 | C90: =_xlfn.RANK.EQ(OpenMxD[[#This Row],[Points]],OpenMxD[Points],0)+COUNTIFS(OpenMxD[Points],OpenMxD[[#This Row],[Points]],OpenMxD[Concession ratio %],"<"&OpenMxD[[#This Row],[Concession ratio %]])+COUNTIFS(OpenMxD[Points],OpenMxD[[#This Row],[Points]],OpenMxD[Concession ratio %],OpenMxD[[#This Row],[Concession ratio %]],OpenMxD[Teams],"<"&OpenMxD[[#This Row],[Teams]]) -> 1 | D90: =OpenMxD[[#This Row],[Wins]]*3 -> 987 | E90: =COUNTIF(Schedules[Team 1 Name], B90) + COUNTIF(Schedules[Team 2 Name], B90) -> 756 | F90: =COUNTIFS(Schedules[Team 1 Name], B90, Schedules[Team 1 Outcome], "Win") + COUNTIFS(Schedules[Team 2 Name], B90, Schedules[Team 2 Outcome], "Win") -> 329 | G90: =IFERROR(OpenSingles[[#This Row],[Wins]]/OpenSingles[[#This Row],[Matches Played]],0%) -> 0 | H90: =SUMIFS(Schedules[Team 1 Score],Schedules[Team 1 Name],B90)+SUMIFS(Schedules[Team 2 Score],Schedules[Team 2 Name],B90) -> 9145 | I90: =SUMIFS(Schedules[Team 2 Score],Schedules[Team 1 Name],B90)+SUMIFS(Schedules[Team 1 Score],Schedules[Team 2 Name],B90) -> 9605 | J90: =IFERROR(OpenMxD[[#This Row],[Conceded Score]]/OpenMxD[[#This Row],[Total Score]],0%) -> 1.0503007
A91: ='Registrations'!A76 -> Open Mixed Doubles | B91: ='Registrations'!E76 -> 0 | C91: =_xlfn.RANK.EQ(OpenMxD[[#This Row],[Points]],OpenMxD[Points],0)+COUNTIFS(OpenMxD[Points],OpenMxD[[#This Row],[Points]],OpenMxD[Concession ratio %],"<"&OpenMxD[[#This Row],[Concession ratio %]])+COUNTIFS(OpenMxD[Points],OpenMxD[[#This Row],[Points]],OpenMxD[Concession ratio %],OpenMxD[[#This Row],[Concession ratio %]],OpenMxD[Teams],"<"&OpenMxD[[#This Row],[Teams]]) -> 1 | D91: =OpenMxD[[#This Row],[Wins]]*3 -> 987 | E91: =COUNTIF(Schedules[Team 1 Name], B91) + COUNTIF(Schedules[Team 2 Name], B91) -> 756 | F91: =COUNTIFS(Schedules[Team 1 Name], B91, Schedules[Team 1 Outcome], "Win") + COUNTIFS(Schedules[Team 2 Name], B91, Schedules[Team 2 Outcome], "Win") -> 329 | G91: =IFERROR(OpenSingles[[#This Row],[Wins]]/OpenSingles[[#This Row],[Matches Played]],0%) -> 0 | H91: =SUMIFS(Schedules[Team 1 Score],Schedules[Team 1 Name],B91)+SUMIFS(Schedules[Team 2 Score],Schedules[Team 2 Name],B91) -> 9145 | I91: =SUMIFS(Schedules[Team 2 Score],Schedules[Team 1 Name],B91)+SUMIFS(Schedules[Team 1 Score],Schedules[Team 2 Name],B91) -> 9605 | J91: =IFERROR(OpenMxD[[#This Row],[Conceded Score]]/OpenMxD[[#This Row],[Total Score]],0%) -> 1.0503007
A92: ='Registrations'!A77 -> Open Mixed Doubles | B92: ='Registrations'!E77 -> 0 | C92: =_xlfn.RANK.EQ(OpenMxD[[#This Row],[Points]],OpenMxD[Points],0)+COUNTIFS(OpenMxD[Points],OpenMxD[[#This Row],[Points]],OpenMxD[Concession ratio %],"<"&OpenMxD[[#This Row],[Concession ratio %]])+COUNTIFS(OpenMxD[Points],OpenMxD[[#This Row],[Points]],OpenMxD[Concession ratio %],OpenMxD[[#This Row],[Concession ratio %]],OpenMxD[Teams],"<"&OpenMxD[[#This Row],[Teams]]) -> 1 | D92: =OpenMxD[[#This Row],[Wins]]*3 -> 987 | E92: =COUNTIF(Schedules[Team 1 Name], B92) + COUNTIF(Schedules[Team 2 Name], B92) -> 756 | F92: =COUNTIFS(Schedules[Team 1 Name], B92, Schedules[Team 1 Outcome], "Win") + COUNTIFS(Schedules[Team 2 Name], B92, Schedules[Team 2 Outcome], "Win") -> 329 | G92: =IFERROR(OpenSingles[[#This Row],[Wins]]/OpenSingles[[#This Row],[Matches Played]],0%) -> 0 | H92: =SUMIFS(Schedules[Team 1 Score],Schedules[Team 1 Name],B92)+SUMIFS(Schedules[Team 2 Score],Schedules[Team 2 Name],B92) -> 9145 | I92: =SUMIFS(Schedules[Team 2 Score],Schedules[Team 1 Name],B92)+SUMIFS(Schedules[Team 1 Score],Schedules[Team 2 Name],B92) -> 9605 | J92: =IFERROR(OpenMxD[[#This Row],[Conceded Score]]/OpenMxD[[#This Row],[Total Score]],0%) -> 1.0503007
A93: ='Registrations'!A78 -> Open Mixed Doubles | B93: ='Registrations'!E78 -> 0 | C93: =_xlfn.RANK.EQ(OpenMxD[[#This Row],[Points]],OpenMxD[Points],0)+COUNTIFS(OpenMxD[Points],OpenMxD[[#This Row],[Points]],OpenMxD[Concession ratio %],"<"&OpenMxD[[#This Row],[Concession ratio %]])+COUNTIFS(OpenMxD[Points],OpenMxD[[#This Row],[Points]],OpenMxD[Concession ratio %],OpenMxD[[#This Row],[Concession ratio %]],OpenMxD[Teams],"<"&OpenMxD[[#This Row],[Teams]]) -> 1 | D93: =OpenMxD[[#This Row],[Wins]]*3 -> 987 | E93: =COUNTIF(Schedules[Team 1 Name], B93) + COUNTIF(Schedules[Team 2 Name], B93) -> 756 | F93: =COUNTIFS(Schedules[Team 1 Name], B93, Schedules[Team 1 Outcome], "Win") + COUNTIFS(Schedules[Team 2 Name], B93, Schedules[Team 2 Outcome], "Win") -> 329 | G93: =IFERROR(OpenSingles[[#This Row],[Wins]]/OpenSingles[[#This Row],[Matches Played]],0%) -> 0 | H93: =SUMIFS(Schedules[Team 1 Score],Schedules[Team 1 Name],B93)+SUMIFS(Schedules[Team 2 Score],Schedules[Team 2 Name],B93) -> 9145 | I93: =SUMIFS(Schedules[Team 2 Score],Schedules[Team 1 Name],B93)+SUMIFS(Schedules[Team 1 Score],Schedules[Team 2 Name],B93) -> 9605 | J93: =IFERROR(OpenMxD[[#This Row],[Conceded Score]]/OpenMxD[[#This Row],[Total Score]],0%) -> 1.0503007
A94: ='Registrations'!A79 -> Open Mixed Doubles | B94: ='Registrations'!E79 -> 0 | C94: =_xlfn.RANK.EQ(OpenMxD[[#This Row],[Points]],OpenMxD[Points],0)+COUNTIFS(OpenMxD[Points],OpenMxD[[#This Row],[Points]],OpenMxD[Concession ratio %],"<"&OpenMxD[[#This Row],[Concession ratio %]])+COUNTIFS(OpenMxD[Points],OpenMxD[[#This Row],[Points]],OpenMxD[Concession ratio %],OpenMxD[[#This Row],[Concession ratio %]],OpenMxD[Teams],"<"&OpenMxD[[#This Row],[Teams]]) -> 1 | D94: =OpenMxD[[#This Row],[Wins]]*3 -> 987 | E94: =COUNTIF(Schedules[Team 1 Name], B94) + COUNTIF(Schedules[Team 2 Name], B94) -> 756 | F94: =COUNTIFS(Schedules[Team 1 Name], B94, Schedules[Team 1 Outcome], "Win") + COUNTIFS(Schedules[Team 2 Name], B94, Schedules[Team 2 Outcome], "Win") -> 329 | G94: =IFERROR(OpenSingles[[#This Row],[Wins]]/OpenSingles[[#This Row],[Matches Played]],0%) -> 0 | H94: =SUMIFS(Schedules[Team 1 Score],Schedules[Team 1 Name],B94)+SUMIFS(Schedules[Team 2 Score],Schedules[Team 2 Name],B94) -> 9145 | I94: =SUMIFS(Schedules[Team 2 Score],Schedules[Team 1 Name],B94)+SUMIFS(Schedules[Team 1 Score],Schedules[Team 2 Name],B94) -> 9605 | J94: =IFERROR(OpenMxD[[#This Row],[Conceded Score]]/OpenMxD[[#This Row],[Total Score]],0%) -> 1.0503007
A95: ='Registrations'!A80 -> Open Mixed Doubles | B95: ='Registrations'!E80 -> 0 | C95: =_xlfn.RANK.EQ(OpenMxD[[#This Row],[Points]],OpenMxD[Points],0)+COUNTIFS(OpenMxD[Points],OpenMxD[[#This Row],[Points]],OpenMxD[Concession ratio %],"<"&OpenMxD[[#This Row],[Concession ratio %]])+COUNTIFS(OpenMxD[Points],OpenMxD[[#This Row],[Points]],OpenMxD[Concession ratio %],OpenMxD[[#This Row],[Concession ratio %]],OpenMxD[Teams],"<"&OpenMxD[[#This Row],[Teams]]) -> 1 | D95: =OpenMxD[[#This Row],[Wins]]*3 -> 987 | E95: =COUNTIF(Schedules[Team 1 Name], B95) + COUNTIF(Schedules[Team 2 Name], B95) -> 756 | F95: =COUNTIFS(Schedules[Team 1 Name], B95, Schedules[Team 1 Outcome], "Win") + COUNTIFS(Schedules[Team 2 Name], B95, Schedules[Team 2 Outcome], "Win") -> 329 | G95: =IFERROR(OpenSingles[[#This Row],[Wins]]/OpenSingles[[#This Row],[Matches Played]],0%) -> 0 | H95: =SUMIFS(Schedules[Team 1 Score],Schedules[Team 1 Name],B95)+SUMIFS(Schedules[Team 2 Score],Schedules[Team 2 Name],B95) -> 9145 | I95: =SUMIFS(Schedules[Team 2 Score],Schedules[Team 1 Name],B95)+SUMIFS(Schedules[Team 1 Score],Schedules[Team 2 Name],B95) -> 9605 | J95: =IFERROR(OpenMxD[[#This Row],[Conceded Score]]/OpenMxD[[#This Row],[Total Score]],0%) -> 1.0503007
A96: ='Registrations'!A81 -> Open Mixed Doubles | B96: ='Registrations'!E81 -> 0 | C96: =_xlfn.RANK.EQ(OpenMxD[[#This Row],[Points]],OpenMxD[Points],0)+COUNTIFS(OpenMxD[Points],OpenMxD[[#This Row],[Points]],OpenMxD[Concession ratio %],"<"&OpenMxD[[#This Row],[Concession ratio %]])+COUNTIFS(OpenMxD[Points],OpenMxD[[#This Row],[Points]],OpenMxD[Concession ratio %],OpenMxD[[#This Row],[Concession ratio %]],OpenMxD[Teams],"<"&OpenMxD[[#This Row],[Teams]]) -> 1 | D96: =OpenMxD[[#This Row],[Wins]]*3 -> 987 | E96: =COUNTIF(Schedules[Team 1 Name], B96) + COUNTIF(Schedules[Team 2 Name], B96) -> 756 | F96: =COUNTIFS(Schedules[Team 1 Name], B96, Schedules[Team 1 Outcome], "Win") + COUNTIFS(Schedules[Team 2 Name], B96, Schedules[Team 2 Outcome], "Win") -> 329 | G96: =IFERROR(OpenSingles[[#This Row],[Wins]]/OpenSingles[[#This Row],[Matches Played]],0%) -> 0 | H96: =SUMIFS(Schedules[Team 1 Score],Schedules[Team 1 Name],B96)+SUMIFS(Schedules[Team 2 Score],Schedules[Team 2 Name],B96) -> 9145 | I96: =SUMIFS(Schedules[Team 2 Score],Schedules[Team 1 Name],B96)+SUMIFS(Schedules[Team 1 Score],Schedules[Team 2 Name],B96) -> 9605 | J96: =IFERROR(OpenMxD[[#This Row],[Conceded Score]]/OpenMxD[[#This Row],[Total Score]],0%) -> 1.0503007
A97: ='Registrations'!A82 -> Open Mixed Doubles | B97: ='Registrations'!E82 -> 0 | C97: =_xlfn.RANK.EQ(OpenMxD[[#This Row],[Points]],OpenMxD[Points],0)+COUNTIFS(OpenMxD[Points],OpenMxD[[#This Row],[Points]],OpenMxD[Concession ratio %],"<"&OpenMxD[[#This Row],[Concession ratio %]])+COUNTIFS(OpenMxD[Points],OpenMxD[[#This Row],[Points]],OpenMxD[Concession ratio %],OpenMxD[[#This Row],[Concession ratio %]],OpenMxD[Teams],"<"&OpenMxD[[#This Row],[Teams]]) -> 1 | D97: =OpenMxD[[#This Row],[Wins]]*3 -> 987 | E97: =COUNTIF(Schedules[Team 1 Name], B97) + COUNTIF(Schedules[Team 2 Name], B97) -> 756 | F97: =COUNTIFS(Schedules[Team 1 Name], B97, Schedules[Team 1 Outcome], "Win") + COUNTIFS(Schedules[Team 2 Name], B97, Schedules[Team 2 Outcome], "Win") -> 329 | G97: =IFERROR(OpenSingles[[#This Row],[Wins]]/OpenSingles[[#This Row],[Matches Played]],0%) -> 0 | H97: =SUMIFS(Schedules[Team 1 Score],Schedules[Team 1 Name],B97)+SUMIFS(Schedules[Team 2 Score],Schedules[Team 2 Name],B97) -> 9145 | I97: =SUMIFS(Schedules[Team 2 Score],Schedules[Team 1 Name],B97)+SUMIFS(Schedules[Team 1 Score],Schedules[Team 2 Name],B97) -> 9605 | J97: =IFERROR(OpenMxD[[#This Row],[Conceded Score]]/OpenMxD[[#This Row],[Total Score]],0%) -> 1.0503007
